Workbook
Name _: #REF!
Name _: #REF!
Name _?: #N/A
Name _?_컛?___i: #REF!
Name _?_컛?___i: #REF!
Name _?쨲?f: #REF!
Name _?쨲?f: #REF!
Name __?: #REF!
Name __?: #REF!
Name __?_컛?___i: #REF!
Name __?_컛?___i: #REF!
Name __?쨲?f: #REF!
Name __?쨲?f: #REF!
Name ___?: #REF!
Name ___?: #REF!
Name ___?_컛?___i: #REF!
Name ___?_컛?___i: #REF!
Name ___?쨲?f: #REF!
Name ___?쨲?f: #REF!
Name ____?: #REF!
Name ____?: #REF!
Name ____?_컛?___i: #REF!
Name ____?_컛?___i: #REF!
Name ____?쨲?f: #REF!
Name ____?쨲?f: #REF!
Name _____?: #REF!
Name _____?: #REF!
Name _____?_컛?___i: #REF!
Name _____?_컛?___i: #REF!
Name _____?쨲?f: #REF!
Name _____?쨲?f: #REF!
Name ______?: #REF!
Name ______?: #REF!
Name ______?_컛?___i: #REF!
Name ______?_컛?___i: #REF!
Name ______?쨲?f: #REF!
Name ______?쨲?f: #REF!
Name _______?: #REF!
Name _______?: #REF!
Name _______?_컛?___i: #REF!
Name _______?_컛?___i: #REF!
Name _______?쨲?f: #REF!
Name _______?쨲?f: #REF!
Name ________?: #REF!
Name ________?: #REF!
Name ________?_컛?___i: #REF!
Name ________?_컛?___i: #REF!
Name ________?쨲?f: #REF!
Name ________?쨲?f: #REF!
Name _________?: #REF!
Name _________?: #REF!
Name _________?_컛?___i: #REF!
Name _________?_컛?___i: #REF!
Name _________?쨲?f: #REF!
Name _________?쨲?f: #REF!
Name __________?: #REF!
Name __________?: #REF!
Name __________a3: #REF!
Name __________a3: #REF!
Name _________a1: #REF!

Sheet 경영실적▶

Sheet 3.경영실적 PT
B1: ○ 2024년 만누르공장 손익실적 | F1: 해당월 입력(Month change) | G1: 3
P2: (단위 : 백만원, %)
B3: 계정 과목명 | C3: 2024년 계획 | E3: 2월 당월실적 | I3: 누계실적 | P3: 계획대비 분석
C4: 금액 | D4: % | E4: 계획 | F4: % | G4: 실적 | H4: % | I4: 계획 | J4: % | K4: 실적 | L4: % | M4: 차액 | N4: 차율 | O4: 실적율 | P4: 증감사유
B5: 매출액 | C5: =SUM(C6:C9) -> 104614.07 | D5: =C5/C$5 -> 1 | E5: =SUM(E6:E9) -> 9209.4917 | F5: =E5/E$5 -> 1 | G5: =SUM(G6:G9) -> 0 | H5: =G5/G$5 -> #DIV/0! | I5: =SUM(I6:I9) -> 26299.702 | J5: =I5/I$5 -> 1 | K5: =SUM(K6:K9) -> 17085.148 | L5: =K5/K$5 -> 1 | M5: =K5-I5 -> -9214.554 | N5: =L5-J5 -> 0 | O5: =K5/I5 -> 0.64963276 | P5: 계획 대비 실적 100% 달성
B6: 제품매출 | C6: =103134.64514176 -> 103134.65 | D6: =C6/C$5 -> 0.98585824 | E6: ='월계획 '!D81/1000 -> 9082.5158 | F6: =E6/E$5 -> 0.9862125 | G6: ='월계획 '!D113/1000 -> 0 | H6: =G6/G$5 -> #DIV/0! | I6: ='월계획 '!F81/1000 -> 25927.073 | J6: =I6/I$5 -> 0.98583144 | K6: ='월계획 '!F113/1000 -> 16477.453 | L6: =K6/K$5 -> 0.96443143 | M6: =K6-I6 -> -9449.6195 | N6: =L6-J6 -> -0.021400016 | O6: =K6/I6 -> 0.6355308 | P6: • AI3 17%(7.7억), BI3 7%(1억), QXI 6%(3.6억) 계획대비↑
B7: 상품매출 | C7: =1076.84561904 -> 1076.8456 | D7: =C7/C$5 -> 0.010293506 | E7: ='월계획 '!D82/1000 -> 92.084603 | F7: =E7/E$5 -> 0.00999888 | G7: ='월계획 '!D114/1000 -> 0 | H7: =G7/G$5 -> #DIV/0! | I7: ='월계획 '!F82/1000 -> 272.52022 | J7: =I7/I$5 -> 0.010362103 | K7: ='월계획 '!F114/1000 -> 479.81838 | L7: =K7/K$5 -> 0.028083947 | M7: =K7-I7 -> 207.29816 | N7: =L7-J7 -> 0.017721844 | O7: =K7/I7 -> 1.7606707 | P7: • BN7I -28%(3.3억), PS7 -34%(7억), SU2I -18%(3.4억)↓
B8: 기타매출 | C8: =741.192226300696 -> 741.19223 | D8: =C8/C$5 -> 0.0070850145 | E8: ='월계획 '!D83/1000 -> 65.151491 | F8: =E8/E$5 -> 0.0070743852 | G8: ='월계획 '!D115/1000 -> 0 | H8: =G8/G$5 -> #DIV/0! | I8: ='월계획 '!F83/1000 -> 186.64721 | J8: =I8/I$5 -> 0.0070969325 | K8: ='월계획 '!F115/1000 -> 127.87596 | L8: =K8/K$5 -> 0.0074846269 | M8: =K8-I8 -> -58.771252 | N8: =L8-J8 -> 0.00038769436 | O8: =K8/I8 -> 0.68512118
B9: CR | C9: =-338.610363153872 -> -338.61036 | D9: =C9/C$5 -> -0.0032367573 | E9: ='월계획 '!D84/1000 -> -30.260252 | F9: =E9/E$5 -> -0.0032857678 | G9: ='월계획 '!D116/1000 -> 0 | H9: =G9/G$5 -> #DIV/0! | I9: ='월계획 '!F84/1000 -> -86.538581 | J9: =I9/I$5 -> -0.0032904777 | K9: ='월계획 '!F116/1000 -> 0 | L9: =K9/K$5 -> 0 | M9: =K9-I9 -> 86.538581 | N9: =L9-J9 -> 0.0032904777 | O9: 0
B10: 판매원가 | C10: =C11+C14+C17 -> 97651.718 | D10: =C10/C$5 -> 0.93344725 | E10: =(E11+E14+E17) -> 8522.2503 | F10: =E10/E$5 -> 0.92537683 | G10: =G11+G14+G17 -> 0 | H10: =G10/G$5 -> #DIV/0! | I10: =I11+I14+I17 -> 24407.853 | J10: =I10/I$5 -> 0.92806578 | K10: =K11+K14+K17 -> 15963.992 | L10: =K10/K$5 -> 0.93437833 | M10: =M11+M14+M17 -> -8443.8613 | N10: =L10-J10 -> 0.0063125559 | O10: =K10/I10 -> 0.65405146
B11: 재료비 소계 | C11: =C12-C13 -> 84123.149 | D11: =C11/C$5 -> 0.80412842 | E11: =E12-E13 -> 7424.4875 | F11: =E11/E$5 -> 0.80617777 | G11: =G12-G13 -> 0 | H11: =G11/G$5 -> #DIV/0! | I11: =I12-I13 -> 21226.141 | J11: =I11/I$5 -> 0.80708676 | K11: =K12-K13 -> 13919.821 | L11: =K11/K$5 -> 0.81473227 | M11: =K11-I11 -> -7306.32 | N11: =L11-J11 -> 0.0076455029 | O11: =K11/I11 -> 0.6557867 | P11: 계획 대비 실적 재료비 0.7% ↑
B12: (재료비) | C12: 84123.149 | D12: =C12/C$5 -> 0.80412842 | E12: ='월계획 '!D87/1000 -> 7424.4875 | F12: =E12/E$5 -> 0.80617777 | G12: ='월계획 '!D119/1000 -> 0 | H12: =G12/G$5 -> #DIV/0! | I12: ='월계획 '!F87/1000 -> 21226.141 | J12: =I12/I$5 -> 0.80708676 | K12: ='월계획 '!F119/1000 -> 13883.384 | L12: =K12/K$5 -> 0.81259956 | M12: =K12-I12 -> -7342.7576 | N12: =L12-J12 -> 0.0055127996 | O12: =K12/I12 -> 0.65407007 | P12: • 리어 단가소급 (22년 M2EL 차종) 52백만 (0.30%) • 전년도 인보이스 (모비스) 51백만 (0.30%) • KD 환율변경 45백만 (0.26%) • 직구매 코일 가격 변동 -29백만 (-0.17%)
B13: (재고증감) | C13: 0 | D13: =C13/C$5 -> 0 | E13: ='월계획 '!D88/1000 -> 0 | F13: =E13/E$5 -> 0 | G13: ='월계획 '!D120/1000 -> 0 | H13: =G13/G$5 -> #DIV/0! | I13: ='월계획 '!F88/1000 -> 0 | J13: =I13/I$5 -> 0 | K13: ='월계획 '!F120/1000 -> -36.437552 | L13: =K13/K$5 -> -0.0021327034 | M13: =K13-I13 -> -36.437552 | N13: =L13-J13 -> -0.0021327034 | O13: 0
B14: 노무비 소계 | C14: =SUM(C15:C16) -> 4228.2977 | D14: =C14/C$5 -> 0.040418058 | E14: =SUM(E15:E16) -> 332.22012 | F14: =E14/E$5 -> 0.036073665 | G14: =SUM(G15:G16) -> 0 | H14: =G14/G$5 -> #DIV/0! | I14: =SUM(I15:I16) -> 973.40709 | J14: =I14/I$5 -> 0.037012096 | K14: =SUM(K15:K16) -> 641.47117 | L14: =K14/K$5 -> 0.037545544 | M14: =SUM(M15:M16) -> -331.93591 | N14: =L14-J14 -> 0.00053344845 | O14: =K14/I14 -> 0.65899579 | P14: 계획 대비 실적 0.0%
B15: (직접노무비) | C15: 2846.6259 | D15: =C15/C$5 -> 0.027210736 | E15: ='월계획 '!D90/1000 -> 222.21474 | F15: =E15/E$5 -> 0.024128882 | G15: ='월계획 '!D122/1000 -> 0 | H15: =G15/G$5 -> #DIV/0! | I15: ='월계획 '!F90/1000 -> 647.97444 | J15: =I15/I$5 -> 0.024638091 | K15: ='월계획 '!F122/1000 -> 424.69515 | L15: =K15/K$5 -> 0.024857564 | M15: =K15-I15 -> -223.27929 | N15: =L15-J15 -> 0.00021947294 | O15: =K15/I15 -> 0.6554196 | P15: • 직접직 0.01% ↑(계획 467, 실적 446명→21명↓), 휴일특근 ↑
B16: (간접노무비) | C16: 1381.6718 | D16: =C16/C$5 -> 0.013207322 | E16: ='월계획 '!D91/1000 -> 110.00538 | F16: =E16/E$5 -> 0.011944783 | G16: ='월계획 '!D123/1000 -> 0 | H16: =G16/G$5 -> #DIV/0! | I16: ='월계획 '!F91/1000 -> 325.43265 | J16: =I16/I$5 -> 0.012374005 | K16: ='월계획 '!F123/1000 -> 216.77602 | L16: =K16/K$5 -> 0.012687981 | M16: =K16-I16 -> -108.65662 | N16: =L16-J16 -> 0.00031397552 | O16: =K16/I16 -> 0.66611641 | P16: • 간접직 0.01% ↓(계획 93, 실적 97명→4명 ↑, 푸네지원)
B17: 경비 소계 | C17: =SUM(C18:C19) -> 9300.272 | D17: =C17/C$5 -> 0.088900774 | E17: =SUM(E18:E19) -> 765.54264 | F17: =E17/E$5 -> 0.083125396 | G17: =SUM(G18:G19) -> 0 | H17: =G17/G$5 -> #DIV/0! | I17: =SUM(I18:I19) -> 2208.3049 | J17: =I17/I$5 -> 0.083966918 | K17: =SUM(K18:K19) -> 1402.6996 | L17: =K17/K$5 -> 0.082100523 | M17: =SUM(M18:M19) -> -805.60534 | N17: =L17-J17 -> -0.0018663955 | O17: =K17/I17 -> 0.63519288 | P17: 계획 대비 실적 -0.2 %↓
B18: (감가상각비) | C18: 3532.9484 | D18: =C18/C$5 -> 0.033771254 | E18: ='월계획 '!D93/1000 -> 267.54299 | F18: =E18/E$5 -> 0.029050788 | G18: ='월계획 '!D125/1000 -> 0 | H18: =G18/G$5 -> #DIV/0! | I18: ='월계획 '!F93/1000 -> 763.02838 | J18: =I18/I$5 -> 0.029012815 | K18: ='월계획 '!F125/1000 -> 477.01773 | L18: =K18/K$5 -> 0.027920023 | M18: =K18-I18 -> -286.01065 | N18: =L18-J18 -> -0.0010927914 | O18: =K18/I18 -> 0.62516381 | P18: • 건물 수선비 33백만 ↑ └ KM 캐노피,정화조 10백만, 지붕보수 9백만, 기타 (도로,수도,식당) 14백만 • 복리후생 (체육대회연기, 식대등) 40백만 ↓
B19: (기타경비) | C19: 5767.3236 | D19: =C19/C$5 -> 0.05512952 | E19: ='월계획 '!D94/1000 -> 497.99965 | F19: =E19/E$5 -> 0.054074608 | G19: ='월계획 '!D126/1000 -> 0 | H19: =G19/G$5 -> #DIV/0! | I19: ='월계획 '!F94/1000 -> 1445.2765 | J19: =I19/I$5 -> 0.054954103 | K19: ='월계획 '!F126/1000 -> 925.68183 | L19: =K19/K$5 -> 0.054180499 | M19: =K19-I19 -> -519.59469 | N19: =L19-J19 -> -0.00077360404 | O19: =K19/I19 -> 0.6404877
B20: 영업이익 | C20: =C5-C10 -> 6962.3544 | D20: =C20/C$5 -> 0.066552752 | E20: =E5-E10 -> 687.24144 | F20: =E20/E$5 -> 0.074623167 | G20: =G5-G10 -> 0 | H20: =G20/G$5 -> #DIV/0! | I20: =I5-I10 -> 1891.8486 | J20: =I20/I$5 -> 0.071934223 | K20: =K5-K10 -> 1121.1559 | L20: =K20/K$5 -> 0.065621667 | M20: =M5-M10 -> -770.69274 | N20: =L20-J20 -> -0.0063125559 | O20: =-K20/I20 -> -0.59262452 | P20: * 영업이익 0.5% ↓
B21: 영업외수익 | C21: =SUM(C22:C23) -> 307.2 | D21: =C21/C$5 -> 0.0029365074 | E21: =SUM(E22:E23) -> 25.6 | F21: =E21/E$5 -> 0.0027797408 | G21: =SUM(G22:G23) -> 0 | H21: =G21/G$5 -> #DIV/0! | I21: =SUM(I22:I23) -> 76.8 | J21: =I21/I$5 -> 0.0029201852 | K21: =SUM(K22:K23) -> 197.20415 | L21: =K21/K$5 -> 0.011542432 | M21: =K21-I21 -> 120.40415 | N21: =L21-J21 -> 0.0086222466 | O21: =K21/I21 -> 2.5677624 | P21: 임대수익 0.5억, 외환차익 1억, 이자수익 0.2억
B22: (환차익) | D22: =C22/C$5 -> 0 | E22: ='월계획 '!D97/1000 -> 0 | F22: =E22/E$5 -> 0 | G22: ='월계획 '!D129/1000 -> 0 | H22: =G22/G$5 -> #DIV/0! | I22: ='월계획 '!F97/1000 -> 0 | J22: =I22/I$5 -> 0 | K22: ='월계획 '!F129/1000 -> 114.0296 | L22: =K22/K$5 -> 0.0066741946 | M22: =K22-I22 -> 114.0296 | N22: =L22-J22 -> 0.0066741946 | O22: =IF(K22<=1000,0,K22/I22) -> 0
B23: (환차익외) | C23: 307.2 | D23: =C23/C$5 -> 0.0029365074 | E23: =SUM('월계획 '!D98:D100)/1000 -> 25.6 | F23: =E23/E$5 -> 0.0027797408 | G23: =SUM('월계획 '!D130:D132)/1000 -> 0 | H23: =G23/G$5 -> #DIV/0! | I23: =SUM('월계획 '!F98:F100)/1000 -> 76.8 | J23: =I23/I$5 -> 0.0029201852 | K23: =SUM('월계획 '!F130:F132)/1000 -> 83.174551 | L23: =K23/K$5 -> 0.0048682372 | M23: =K23-I23 -> 6.3745512 | N23: =L23-J23 -> 0.001948052 | O23: =K23/I23 -> 1.083002
B24: 영업외비용 | C24: =SUM(C25:C27) -> 1657.7971 | D24: =C24/C$5 -> 0.015846789 | E24: =SUM(E25:E27) -> 113.05056 | F24: =E24/E$5 -> 0.012275439 | G24: =SUM(G25:G27) -> 0 | H24: =G24/G$5 -> #DIV/0! | I24: =SUM(I25:I27) -> 329.00167 | J24: =I24/I$5 -> 0.012509711 | K24: =SUM(K25:K27) -> 371.40019 | L24: =K24/K$5 -> 0.02173819 | M24: =SUM(M25:M27) -> 42.398514 | N24: =L24-J24 -> 0.0092284788 | O24: =K24/I24 -> 1.1288702 | P24: 환차손 0.2억, 이자비용 3억
B25: (환차손) | D25: =C25/C$5 -> 0 | E25: ='월계획 '!D102/1000 -> 0 | F25: =E25/E$5 -> 0 | G25: ='월계획 '!D134/1000 -> 0 | H25: =G25/G$5 -> #DIV/0! | I25: ='월계획 '!F102/1000 -> 0 | J25: =I25/I$5 -> 0 | K25: ='월계획 '!F134/1000 -> 17.179297 | L25: =K25/K$5 -> 0.0010055106 | M25: =K25-I25 -> 17.179297 | N25: =L25-J25 -> 0.0010055106 | O25: =K25/I25 -> #DIV/0!
B26: (이자비용) | C26: 1625.0117 | D26: =C26/C$5 -> 0.015533395 | E26: ='월계획 '!D103/1000 -> 106.13954 | F26: =E26/E$5 -> 0.011525016 | G26: ='월계획 '!D135/1000 -> 0 | H26: =G26/G$5 -> #DIV/0! | I26: ='월계획 '!F103/1000 -> 305.45832 | J26: =I26/I$5 -> 0.011614516 | K26: ='월계획 '!F135/1000 -> 335.79798 | L26: =K26/K$5 -> 0.01965438 | M26: =K26-I26 -> 30.339667 | N26: =L26-J26 -> 0.0080398635 | O26: =K26/I26 -> 1.0993251
B27: (환차손외) | C27: 32.785407 | D27: =C27/C$5 -> 0.00031339385 | E27: =SUM('월계획 '!D104:D105)/1000 -> 6.9110174 | F27: =E27/E$5 -> 0.00075042332 | G27: =SUM('월계획 '!D136:D137)/1000 -> 0 | H27: =G27/G$5 -> #DIV/0! | I27: =SUM('월계획 '!F104:F105)/1000 -> 23.543357 | J27: =I27/I$5 -> 0.00089519481 | K27: =SUM('월계획 '!F136:F137)/1000 -> 18.422906 | L27: =K27/K$5 -> 0.0010782995 | M27: =K27-I27 -> -5.1204503 | N27: =L27-J27 -> 0.00018310469 | O27: =K27/I27 -> 0.78250976
B28: 소계 | C28: =C21-C24 -> -1350.5971 | D28: =C28/C$5 -> -0.012910281 | E28: =E21-E24 -> -87.450558 | F28: =E28/E$5 -> -0.0094956987 | G28: =G21-G24 -> 0 | H28: =G28/G$5 -> #DIV/0! | I28: =I21-I24 -> -252.20167 | J28: =I28/I$5 -> -0.009589526 | K28: =K21-K24 -> -174.19603 | L28: =K28/K$5 -> -0.010195758 | M28: =K28-I28 -> 78.005639 | N28: =L28-J28 -> -0.00060623218 | O28: =K28/I28 -> 0.69070134
B29: 경상이익 | C29: =C20+C28 -> 5611.7573 | D29: =C29/C$5 -> 0.053642471 | E29: =(E20+E28) -> 599.79088 | F29: =E29/E$5 -> 0.065127468 | G29: =G20+G28 -> 0 | H29: =G29/G$5 -> #DIV/0! | I29: =I20+I28 -> 1639.6469 | J29: =I29/I$5 -> 0.062344697 | K29: =K20+K28 -> 946.95985 | L29: =K29/K$5 -> 0.055425909 | M29: =K29-I29 -> -692.6871 | N29: =L29-J29 -> -0.0069187881 | O29: =-K29/I29 -> -0.57753887
B30: 경상이익(환차손제외) | C30: =C29+C25-C22 -> 5611.7573 | D30: =C30/C$5 -> 0.053642471 | E30: =E29+E25-E22 -> 599.79088 | F30: =E30/E$5 -> 0.065127468 | G30: =G29+G25-G22 -> 0 | H30: =G30/G$5 -> #DIV/0! | I30: =I29+I25-I22 -> 1639.6469 | J30: =I30/I$5 -> 0.062344697 | K30: =K29+K25-K22 -> 850.10955 | L30: =K30/K$5 -> 0.049757225 | M30: =K30-I30 -> -789.5374 | N30: =L30-J30 -> -0.012587472 | O30: =-K30/I30 -> -0.51847109
B31: ☞ 파워포인트 양식으로 옮기기 (1.엑셀에서 범위설정 "복사" 2. 파워포인트에서 "편집"선택 -> "선택하여 붙여넣기" 선택 -> "그림(확장 메타파일)"형식 저장)
C36: ▣ 재료비 초과 내역 (누계 기준)
C37: 1. 초과 금액
C38: (1) 총 매출액 | E38: =K5 -> 17085.148
C39: (2) 초과 비율 | E39: =N11 -> 0.0076455029
C40: 초과 금액 | E40: =E38*E39 -> 130.62455
C42: 2. 주요 내역 | F42: + 재료비 증가, - 재료비 감소
D43: 내역 | G43: 금액
C44: 리어 단가소급 (22년 M2EL 차종) | G44: 52 | H44: =G44/$E$38 -> 0.0030435792
C45: 전년도 인보이스 (모비스) | G45: 51 | H45: =G45/$E$38 -> 0.0029850488
C46: KD 환율변경 | G46: 45 | H46: =G46/$E$38 -> 0.0026338666
C47: 직구매 코일 가격 변동 | G47: -28.683291 | H47: =G47/$E$38 -> -0.0016788436
C51: 기타
C53: 합계 | G53: =SUM(G44:G52) -> 119.31671
C54: 차이 | G54: =E40-G53 -> 11.307838
C56: BOM 미반영 | G56: 41 | H56: =G56/$E$38 -> 0.0023997451
B60: 계정과목명 | C60: 2024년 계획 | E60: 2월 당월실적 | I60: 누계실적 | P60: 계획대비 분석
C61: 금액 | D61: % | E61: 계획 | F61: % | G61: 실적 | H61: % | I61: 계획 | J61: % | K61: 실적 | L61: % | M61: 차액 | N61: 차율 | O61: 실적율 | P61: 증감사유
B62: 매출액 | C62: =C5 -> 104614.07 | D62: =D5 -> 1 | E62: =E5 -> 9209.4917 | F62: =F5 -> 1 | G62: =G5 -> 0 | H62: =H5 -> #DIV/0! | I62: =I5 -> 26299.702 | J62: =J5 -> 1 | ... P62: =P5 -> 계획 대비 실적 100% 달성
B63: 제품매출 | C63: =C6 -> 103134.65 | D63: =D6 -> 0.98585824 | E63: =E6 -> 9082.5158 | F63: =F6 -> 0.9862125 | G63: =G6 -> 0 | H63: =H6 -> #DIV/0! | I63: =I6 -> 25927.073 | J63: =J6 -> 0.98583144 | ... P63: =P6 -> • AI3 17%(7.7억), BI3 7%(1억), QXI 6%(3.6억) 계획대비↑
B64: 상품매출 | C64: =C7 -> 1076.8456 | D64: =D7 -> 0.010293506 | E64: =E7 -> 92.084603 | F64: =F7 -> 0.00999888 | G64: =G7 -> 0 | H64: =H7 -> #DIV/0! | I64: =I7 -> 272.52022 | J64: =J7 -> 0.010362103 | ... P64: =P7 -> • BN7I -28%(3.3억), PS7 -34%(7억), SU2I -18%(3.4억)↓
B65: 기타매출 | C65: =C8+C9 -> 402.58186 | D65: =D8+D9 -> 0.0038482572 | E65: =E8+E9 -> 34.89124 | F65: =F8+F9 -> 0.0037886173 | G65: =G8+G9 -> 0 | H65: =H8+H9 -> #DIV/0! | I65: =I8+I9 -> 100.10863 | J65: =J8+J9 -> 0.0038064548 | ... O65: =O8+O9 -> 0.68512118
B66: 판매원가 | C66: =C10 -> 97651.718 | D66: =D10 -> 0.93344725 | E66: =E10 -> 8522.2503 | F66: =F10 -> 0.92537683 | G66: =G10 -> 0 | H66: =H10 -> #DIV/0! | I66: =I10 -> 24407.853 | J66: =J10 -> 0.92806578 | ... O66: =O10 -> 0.65405146
B67: 재료비 소계 | C67: =C11 -> 84123.149 | D67: =D11 -> 0.80412842 | E67: =E11 -> 7424.4875 | F67: =F11 -> 0.80617777 | G67: =G11 -> 0 | H67: =H11 -> #DIV/0! | I67: =I11 -> 21226.141 | J67: =J11 -> 0.80708676 | ... P67: =P11 -> 계획 대비 실적 재료비 0.7% ↑
B68: (재료비) | C68: =C12 -> 84123.149 | D68: =D12 -> 0.80412842 | E68: =E12 -> 7424.4875 | F68: =F12 -> 0.80617777 | G68: =G12 -> 0 | H68: =H12 -> #DIV/0! | I68: =I12 -> 21226.141 | J68: =J12 -> 0.80708676 | ... P68: =P12 -> • 리어 단가소급 (22년 M2EL 차종) 52백만 (0.30%) • 전년도 인보이스 (모비스) 51백만 (0.30%) • KD 환율변경 45백만 (0.26%) • 직구매 코일 가격 변동 -29백만 (-0.17%)
B69: (재고증감) | C69: =C13 -> 0 | D69: =D13 -> 0 | E69: =E13 -> 0 | F69: =F13 -> 0 | G69: =G13 -> 0 | H69: =H13 -> #DIV/0! | I69: =I13 -> 0 | J69: =J13 -> 0 | ... O69: =O13 -> 0
B70: 노무비 소계 | C70: =C14 -> 4228.2977 | D70: =D14 -> 0.040418058 | E70: =E14 -> 332.22012 | F70: =F14 -> 0.036073665 | G70: =G14 -> 0 | H70: =H14 -> #DIV/0! | I70: =I14 -> 973.40709 | J70: =J14 -> 0.037012096 | ... P70: =P14 -> 계획 대비 실적 0.0%
B71: (직접노무비) | C71: =C15 -> 2846.6259 | D71: =D15 -> 0.027210736 | E71: =E15 -> 222.21474 | F71: =F15 -> 0.024128882 | G71: =G15 -> 0 | H71: =H15 -> #DIV/0! | I71: =I15 -> 647.97444 | J71: =J15 -> 0.024638091 | ... P71: =P15 -> • 직접직 0.01% ↑(계획 467, 실적 446명→21명↓), 휴일특근 ↑
B72: (간접노무비) | C72: =C16 -> 1381.6718 | D72: =D16 -> 0.013207322 | E72: =E16 -> 110.00538 | F72: =F16 -> 0.011944783 | G72: =G16 -> 0 | H72: =H16 -> #DIV/0! | I72: =I16 -> 325.43265 | J72: =J16 -> 0.012374005 | ... P72: =P16 -> • 간접직 0.01% ↓(계획 93, 실적 97명→4명 ↑, 푸네지원)
B73: 경비 소계 | C73: =C17 -> 9300.272 | D73: =D17 -> 0.088900774 | E73: =E17 -> 765.54264 | F73: =F17 -> 0.083125396 | G73: =G17 -> 0 | H73: =H17 -> #DIV/0! | I73: =I17 -> 2208.3049 | J73: =J17 -> 0.083966918 | ... P73: =P17 -> 계획 대비 실적 -0.2 %↓
B74: (감가상각비) | C74: =C18 -> 3532.9484 | D74: =D18 -> 0.033771254 | E74: =E18 -> 267.54299 | F74: =F18 -> 0.029050788 | G74: =G18 -> 0 | H74: =H18 -> #DIV/0! | I74: =I18 -> 763.02838 | J74: =J18 -> 0.029012815 | ... O74: =O18 -> 0.62516381 | P74: • 건물 수선비 33백만 ↑ └ KM 캐노피,정화조 10백만, 지붕보수 9백만, 기타 (도로,수도,식당) 14백만 • 복리후생 (체육대회연기, 식대등) 40백만 ↓
B75: (기타경비) | C75: =C19 -> 5767.3236 | D75: =D19 -> 0.05512952 | E75: =E19 -> 497.99965 | F75: =F19 -> 0.054074608 | G75: =G19 -> 0 | H75: =H19 -> #DIV/0! | I75: =I19 -> 1445.2765 | J75: =J19 -> 0.054954103 | ... O75: =O19 -> 0.6404877
B76: 영업이익 | C76: =C20 -> 6962.3544 | D76: =D20 -> 0.066552752 | E76: =E20 -> 687.24144 | F76: =F20 -> 0.074623167 | G76: =G20 -> 0 | H76: =H20 -> #DIV/0! | I76: =I20 -> 1891.8486 | J76: =J20 -> 0.071934223 | ... P76: =P20 -> * 영업이익 0.5% ↓
B77: 영업외수익 | C77: =C21 -> 307.2 | D77: =D21 -> 0.0029365074 | E77: =E21 -> 25.6 | F77: =F21 -> 0.0027797408 | G77: =G21 -> 0 | H77: =H21 -> #DIV/0! | I77: =I21 -> 76.8 | J77: =J21 -> 0.0029201852 | ... P77: =P21 -> 임대수익 0.5억, 외환차익 1억, 이자수익 0.2억
B78: 영업외비용 | C78: =C24 -> 1657.7971 | D78: =D24 -> 0.015846789 | E78: =E24 -> 113.05056 | F78: =F24 -> 0.012275439 | G78: =G24 -> 0 | H78: =H24 -> #DIV/0! | I78: =I24 -> 329.00167 | J78: =J24 -> 0.012509711 | ... P78: =P24 -> 환차손 0.2억, 이자비용 3억
B79: 소계 | C79: =C28 -> -1350.5971 | D79: =D28 -> -0.012910281 | E79: =E28 -> -87.450558 | F79: =F28 -> -0.0094956987 | G79: =G28 -> 0 | H79: =H28 -> #DIV/0! | I79: =I28 -> -252.20167 | J79: =J28 -> -0.009589526 | ... O79: =O28 -> 0.69070134
B80: 경상이익 | C80: =C29 -> 5611.7573 | D80: =D29 -> 0.053642471 | E80: =E29 -> 599.79088 | F80: =F29 -> 0.065127468 | G80: =G29 -> 0 | H80: =H29 -> #DIV/0! | I80: =I29 -> 1639.6469 | J80: =J29 -> 0.062344697 | ... O80: =O29 -> -0.57753887

Sheet 생산현황 PT
A1: ○ 2024년 만누르 경영실적
AU3: (단위 : 대)
H4: '24년 | Q4: 24년 당월 | AE4: 24년 누계 | AS4: 연간 달성율
H5: 계 획 | M5: 구성비 | Q5: 계 획 | V5: 실 적 | AA5: 달성율 | AE5: 계 획 | AJ5: 실 적 | AO5: 달성율
A6: 연 간 생 산 계 획 내 림 차 순 | C6: AI3 | H6: 270300 | M6: =H6/$H$17 -> 0.33907022 | AA6: =V6/Q6 -> #DIV/0! | AO6: =AJ6/AE6 -> #DIV/0! | AS6: =AJ6/H6 -> 0
C7: QXI | H7: 163440 | M7: =H7/$H$17 -> 0.20502271 | AA7: =V7/Q7 -> #DIV/0! | AO7: =AJ7/AE7 -> #DIV/0! | AS7: =AJ7/H7 -> 0
C8: SU2 | H8: 163200 | M8: =H8/$H$17 -> 0.20472164 | AA8: =V8/Q8 -> #DIV/0! | AO8: =AJ8/AE8 -> #DIV/0! | AS8: =AJ8/H8 -> 0
C9: BN7 | H9: 90500 | M9: =H9/$H$17 -> 0.11352518 | AA9: =V9/Q9 -> #DIV/0! | AO9: =AJ9/AE9 -> #DIV/0! | AS9: =AJ9/H9 -> 0
C10: BI3 | H10: 77300 | M10: =H10/$H$17 -> 0.096966808 | AA10: =V10/Q10 -> #DIV/0! | AO10: =AJ10/AE10 -> #DIV/0! | AS10: =AJ10/H10 -> 0
C11: PS7 | H11: 32440 | M11: =H11/$H$17 -> 0.040693444 | AA11: =V11/Q11 -> #DIV/0! | AO11: =AJ11/AE11 -> #DIV/0! | AS11: =AJ11/H11 -> 0
M12: =H12/$H$17 -> 0 | AA12: =V12/Q12 -> #DIV/0! | AO12: =AJ12/AE12 -> #DIV/0! | AS12: =AJ12/H12 -> #DIV/0!
M13: =H13/$H$17 -> 0 | AA13: =V13/Q13 -> #DIV/0! | AO13: =AJ13/AE13 -> #DIV/0! | AS13: =AJ13/H13 -> #DIV/0!
M14: =H14/$H$17 -> 0 | AA14: =V14/Q14 -> #DIV/0! | AO14: =AJ14/AE14 -> #DIV/0! | AS14: =AJ14/H14 -> #DIV/0!
M15: =H15/$H$17 -> 0 | AA15: =V15/Q15 -> #DIV/0! | AO15: =AJ15/AE15 -> #DIV/0! | AS15: =AJ15/H15 -> #DIV/0!
M16: =H16/$H$17 -> 0 | AA16: =V16/Q16 -> #DIV/0! | AO16: =AJ16/AE16 -> #DIV/0! | AS16: =AJ16/H16 -> #DIV/0!
C17: 생산 계 | H17: =SUM(H6:H16) -> 797180 | M17: =H17/$H$17 -> 1 | Q17: =SUM(Q6:Q16) -> 0 | V17: =SUM(V6:V16) -> 0 | AA17: =V17/Q17 -> #DIV/0! | AE17: =SUM(AE6:AE16) -> 0 | AJ17: =SUM(AJ6:AJ16) -> 0 | AO17: =AJ17/AE17 -> #DIV/0! | AS17: =AJ17/H17 -> 0

Sheet 경영실적 추이도 PT
A1: ○ 2024년 만누르 경영실적 추이현황
W20: (단위 : 백만원)
A21: 구 분 | F21: '23년 | J21: '24년
F22: 연간 실적 | J22: 연간 목표 | K22: 1월 | L22: 2월 | M22: 3월 | N22: 4월 | O22: 5월 | P22: 6월 | Q22: 7월 | R22: 8월 | S22: 9월 | T22: 10월 | U22: 11월 | V22: 12월 | W22: 누 계
A23: 매출액 (A) | F23: =('월계획 '!B4)/1000 -> 100374.62 | J23: =('월계획 '!B80)/1000 -> 104614.07 | K23: =('월계획 '!H112)/1000 -> 8161.5523 | L23: =('월계획 '!I112)/1000 -> 8923.5955 | M23: =('월계획 '!J112)/1000 -> 0 | N23: =('월계획 '!K112)/1000 -> 0 | O23: =('월계획 '!L112)/1000 -> 0 | P23: =('월계획 '!M112)/1000 -> 0 | Q23: =('월계획 '!N112)/1000 -> 0 | R23: =('월계획 '!O112)/1000 -> 0 | ... V23: =('월계획 '!S112)/1000 -> 0 | W23: =SUM(K23:V23) -> 17085.148
A25: 영업이익 | F25: =('월계획 '!B18)/1000 -> 5580.3287 | J25: =('월계획 '!B95)/1000 -> 6962.3544 | K25: =('월계획 '!H127)/1000 -> 375.01735 | L25: =('월계획 '!I127)/1000 -> 746.13854 | M25: =('월계획 '!J127)/1000 -> 0 | N25: =('월계획 '!K127)/1000 -> 0 | O25: =('월계획 '!L127)/1000 -> 0 | P25: =('월계획 '!M127)/1000 -> 0 | Q25: =('월계획 '!N127)/1000 -> 0 | R25: =('월계획 '!O127)/1000 -> 0 | ... V25: =('월계획 '!S127)/1000 -> 0 | W25: =SUM(K25:V25) -> 1121.1559
F26: =F25/F23 -> 0.055595015 | J26: =J25/J23 -> 0.066552752 | K26: =K25/K23 -> 0.045949267 | L26: =L25/L23 -> 0.083614115 | M26: =M25/M23 -> #DIV/0! | N26: =N25/N23 -> #DIV/0! | O26: =O25/O23 -> #DIV/0! | P26: =P25/P23 -> #DIV/0! | Q26: =Q25/Q23 -> #DIV/0! | ... W26: =W25/W23 -> 0.065621667
A27: 경상이익 | F27: =('월계획 '!B22)/1000 -> 3621.727 | J27: =('월계획 '!B107)/1000 -> 5611.7573 | K27: =('월계획 '!H139)/1000 -> 311.46003 | L27: =('월계획 '!I139)/1000 -> 635.49982 | M27: =('월계획 '!J139)/1000 -> 0 | N27: =('월계획 '!K139)/1000 -> 0 | O27: =('월계획 '!L139)/1000 -> 0 | P27: =('월계획 '!M139)/1000 -> 0 | Q27: =('월계획 '!N139)/1000 -> 0 | R27: =('월계획 '!O139)/1000 -> 0 | ... V27: =('월계획 '!S139)/1000 -> 0 | W27: =SUM(K27:V27) -> 946.95985
F28: =F27/F23 -> 0.036082097 | J28: =J27/J23 -> 0.053642471 | K28: =K27/K23 -> 0.038161862 | L28: =L27/L23 -> 0.071215669 | M28: =M27/M23 -> #DIV/0! | N28: =N27/N23 -> #DIV/0! | O28: =O27/O23 -> #DIV/0! | P28: =P27/P23 -> #DIV/0! | Q28: =Q27/Q23 -> #DIV/0! | ... W28: =W27/W23 -> 0.055425909

Sheet 경영실적 PT
A1: ○ 2024년 만누르 경영실적
AS3: (단위 : 백만원)
A4: 구 분 | H4: '23년 | M4: '24년
H5: 연간 실적 | M5: 연간 계획 | R5: 당 월 | AG5: 누 계
R6: 계 획 | W6: 실 적 | AB6: 차 이 | AG6: 계 획 | AL6: 실 적 | AQ6: 차 이
A7: 매출액 (A) | H7: ='월계획 '!B4/1000 -> 100374.62 | M7: ='월계획 '!B80/1000 -> 104614.07 | R7: ='월계획 '!D80/1000 -> 9209.4917 | W7: ='월계획 '!D112/1000 -> 0 | AB7: =W7-R7 -> -9209.4917 | AG7: ='월계획 '!F80/1000 -> 26299.702 | AL7: ='월계획 '!B112/1000 -> 17085.148 | AQ7: =AL7-AG7 -> -9214.554
A9: 판매원가 | C9: 재료비 | H9: ='월계획 '!B9/1000 -> 81330.816 | M9: ='월계획 '!B86/1000 -> 84123.149 | R9: ='월계획 '!D86/1000 -> 7424.4875 | W9: ='월계획 '!D118/1000 -> 0 | AB9: =W9-R9 -> -7424.4875 | AG9: ='월계획 '!F86/1000 -> 21226.141 | AL9: ='월계획 '!B118/1000 -> 13919.821 | AQ9: =AL9-AG9 -> -7306.32
C10: (B) | H10: =IFERROR(H9/H$7,"") -> 0.81027269 | M10: =IFERROR(M9/M$7,"") -> 0.80412842 | R10: =IFERROR(R9/R$7,"") -> 0.80617777 | W10: =IFERROR(W9/W$7,"") | AB10: =W10-R10 -> #VALUE! | AG10: =IFERROR(AG9/AG$7,"") -> 0.80708676 | AL10: =IFERROR(AL9/AL$7,"") -> 0.81473227 | AQ10: =AL10-AG10 -> 0.0076455029
C11: 노무비 | H11: ='월계획 '!B12/1000 -> 4143.6937 | M11: ='월계획 '!B89/1000 -> 4228.2977 | R11: ='월계획 '!D89/1000 -> 332.22012 | W11: ='월계획 '!D121/1000 -> 0 | AB11: =W11-R11 -> -332.22012 | AG11: ='월계획 '!F89/1000 -> 973.40709 | AL11: ='월계획 '!B121/1000 -> 641.47117 | AQ11: =AL11-AG11 -> -331.93591
C12: (C) | H12: =IFERROR(H11/H$7,"") -> 0.041282284 | M12: =IFERROR(M11/M$7,"") -> 0.040418058 | R12: =IFERROR(R11/R$7,"") -> 0.036073665 | W12: =IFERROR(W11/W$7,"") | AB12: =W12-R12 -> #VALUE! | AG12: =IFERROR(AG11/AG$7,"") -> 0.037012096 | AL12: =IFERROR(AL11/AL$7,"") -> 0.037545544 | AQ12: =AL12-AG12 -> 0.00053344845
C13: 경 비 | H13: ='월계획 '!B15/1000 -> 9319.7854 | M13: ='월계획 '!B92/1000 -> 9300.272 | R13: ='월계획 '!D92/1000 -> 765.54264 | W13: ='월계획 '!D124/1000 -> 0 | AB13: =W13-R13 -> -765.54264 | AG13: ='월계획 '!F92/1000 -> 2208.3049 | AL13: ='월계획 '!B124/1000 -> 1402.6996 | AQ13: =AL13-AG13 -> -805.60534
C14: (D) | H14: =IFERROR(H13/H$7,"") -> 0.092850016 | M14: =IFERROR(M13/M$7,"") -> 0.088900774 | R14: =IFERROR(R13/R$7,"") -> 0.083125396 | W14: =IFERROR(W13/W$7,"") | AB14: =W14-R14 -> #VALUE! | AG14: =IFERROR(AG13/AG$7,"") -> 0.083966918 | AL14: =IFERROR(AL13/AL$7,"") -> 0.082100523 | AQ14: =AL14-AG14 -> -0.0018663955
C15: 계 | H15: =H9+H11+H13 -> 94794.295 | M15: =M9+M11+M13 -> 97651.718 | R15: =R9+R11+R13 -> 8522.2503 | W15: =W9+W11+W13 -> 0 | AB15: =W15-R15 -> -8522.2503 | AG15: =AG9+AG11+AG13 -> 24407.853 | AL15: =AL9+AL11+AL13 -> 15963.992 | AQ15: =AL15-AG15 -> -8443.8613
C16: (E=B+C+D) | H16: =IFERROR(H15/H$7,"") -> 0.94440499 | M16: =IFERROR(M15/M$7,"") -> 0.93344725 | R16: =IFERROR(R15/R$7,"") -> 0.92537683 | W16: =IFERROR(W15/W$7,"") | AB16: =W16-R16 -> #VALUE! | AG16: =IFERROR(AG15/AG$7,"") -> 0.92806578 | AL16: =IFERROR(AL15/AL$7,"") -> 0.93437833 | AQ16: =AL16-AG16 -> 0.0063125559
A17: 영업이익 | H17: =H7-H15 -> 5580.3287 | M17: =M7-M15 -> 6962.3544 | R17: =R7-R15 -> 687.24144 | W17: =W7-W15 -> 0 | AB17: =W17-R17 -> -687.24144 | AG17: =AG7-AG15 -> 1891.8486 | AL17: =AL7-AL15 -> 1121.1559 | AQ17: =AL17-AG17 -> -770.69274
A18: (F=A-E) | H18: =IFERROR(H17/H$7,"") -> 0.055595015 | M18: =IFERROR(M17/M$7,"") -> 0.066552752 | R18: =IFERROR(R17/R$7,"") -> 0.074623167 | W18: =IFERROR(W17/W$7,"") | AB18: =W18-R18 -> #VALUE! | AG18: =IFERROR(AG17/AG$7,"") -> 0.071934223 | AL18: =IFERROR(AL17/AL$7,"") -> 0.065621667 | AQ18: =AL18-AG18 -> -0.0063125559
A19: 영업외수지 | H19: ='월계획 '!B21/1000 -> -1958.6017 | M19: ='월계획 '!B106/1000 -> -1350.5971 | R19: ='월계획 '!D106/1000 -> -87.450558 | W19: ='월계획 '!D138/1000 -> 0 | AB19: =W19-R19 -> 87.450558 | AG19: ='월계획 '!F106/1000 -> -252.20167 | AL19: ='월계획 '!B138/1000 -> -174.19603 | AQ19: =AL19-AG19 -> 78.005639
A20: (G) | H20: =IFERROR(H19/H$7,"") -> -0.019512917 | M20: =IFERROR(M19/M$7,"") -> -0.012910281 | R20: =IFERROR(R19/R$7,"") -> -0.0094956987 | W20: =IFERROR(W19/W$7,"") | AB20: =W20-R20 -> #VALUE! | AG20: =IFERROR(AG19/AG$7,"") -> -0.009589526 | AL20: =IFERROR(AL19/AL$7,"") -> -0.010195758 | AQ20: =AL20-AG20 -> -0.00060623218
A21: 경상이익 | H21: =H17+H19 -> 3621.727 | M21: =M17+M19 -> 5611.7573 | R21: =R17+R19 -> 599.79088 | W21: =W17+W19 -> 0 | AB21: =W21-R21 -> -599.79088 | AG21: =AG17+AG19 -> 1639.6469 | AL21: =AL17+AL19 -> 946.95985 | AQ21: =AL21-AG21 -> -692.6871
A22: (H=F+G) | H22: =IFERROR(H21/H$7,"") -> 0.036082097 | M22: =IFERROR(M21/M$7,"") -> 0.053642471 | R22: =IFERROR(R21/R$7,"") -> 0.065127468 | W22: =IFERROR(W21/W$7,"") | AB22: =W22-R22 -> #VALUE! | AG22: =IFERROR(AG21/AG$7,"") -> 0.062344697 | AL22: =IFERROR(AL21/AL$7,"") -> 0.055425909 | AQ22: =AL22-AG22 -> -0.0069187881
A24: 주) “23년, “24년 년도별 사업계획 환율 적용
AX25: 경영실적 분석 PT 참고 | BA25: 매출액 | BB25: 당월 | BC25: 누계
AX26: (삭제금지) | BA26: =M7 -> 104614.07 | BB26: =R7 -> 9209.4917 | BC26: =AG7 -> 26299.702 | BG26: 계획
BB27: =W7 -> 0 | BC27: =AL7 -> 17085.148 | BG27: 실적
BA28: 노무비
AX29: 직접직 | BA29: ='월계획 '!B90/1000 -> 2846.6259 | BB29: ='월계획 '!D90/1000 -> 222.21474 | BC29: ='월계획 '!F90/1000 -> 647.97444 | BD29: =BA29/BA26 -> 0.027210736 | BE29: =BB29/BB26 -> 0.024128882 | BF29: =BC29/BC26 -> 0.024638091 | BG29: 계획
AX30: 간접직 | BA30: ='월계획 '!B91/1000 -> 1381.6718 | BB30: ='월계획 '!D91/1000 -> 110.00538 | BC30: ='월계획 '!F91/1000 -> 325.43265 | BD30: =BA30/BA26 -> 0.013207322 | BE30: =BB30/BB26 -> 0.011944783 | BF30: =BC30/BC26 -> 0.012374005
AX31: 계 | BA31: =SUM(BA29:BA30) -> 4228.2977 | BB31: =SUM(BB29:BB30) -> 332.22012 | BC31: =SUM(BC29:BC30) -> 973.40709
AX32: 직접직 | BB32: ='월계획 '!D122/1000 -> 0 | BC32: ='월계획 '!F122/1000 -> 424.69515 | BE32: =BB32/BB27 -> #DIV/0! | BF32: =BC32/BC27 -> 0.024857564 | BG32: 실적
AX33: 간접직 | BB33: ='월계획 '!D123/1000 -> 0 | BC33: ='월계획 '!F123/1000 -> 216.77602 | BE33: =BB33/BB27 -> #DIV/0! | BF33: =BC33/BC27 -> 0.012687981
AX34: 계 | BB34: =SUM(BB32:BB33) -> 0 | BC34: =SUM(BC32:BC33) -> 641.47117
BA35: 경비
AX36: 감가 | BA36: ='월계획 '!B93/1000 -> 3532.9484 | BB36: ='월계획 '!D93/1000 -> 267.54299 | BC36: ='월계획 '!F93/1000 -> 763.02838 | BD36: =BA36/BA26 -> 0.033771254 | BE36: =BB36/BB26 -> 0.029050788 | BF36: =BC36/BC26 -> 0.029012815 | BG36: 계획
AX37: 일반 | BA37: ='월계획 '!B94/1000 -> 5767.3236 | BB37: ='월계획 '!D94/1000 -> 497.99965 | BC37: ='월계획 '!F94/1000 -> 1445.2765 | BD37: =BA37/BA26 -> 0.05512952 | BE37: =BB37/BB26 -> 0.054074608 | BF37: =BC37/BC26 -> 0.054954103
AX38: 계 | BA38: =SUM(BA36:BA37) -> 9300.272 | BB38: =SUM(BB36:BB37) -> 765.54264 | BC38: =SUM(BC36:BC37) -> 2208.3049
BB39: ='월계획 '!D125/1000 -> 0 | BC39: ='월계획 '!F125/1000 -> 477.01773 | BE39: =BB39/BB27 -> #DIV/0! | BF39: =BC39/BC27 -> 0.027920023 | BG39: 실적
BB40: ='월계획 '!D126/1000 -> 0 | BC40: ='월계획 '!F126/1000 -> 925.68183 | BE40: =BB40/BB27 -> #DIV/0! | BF40: =BC40/BC27 -> 0.054180499
BB41: =SUM(BB39:BB40) -> 0 | BC41: =SUM(BC39:BC40) -> 1402.6996

Sheet 경영실적 분석 PT 1
B1: ○ 2024년 만누르 실적분석
B4: 구 분 | D4: 추이도 | O4: 실적 분석
B6: 매출액 | O6: ○ 판매가 : ○ 생산량 : ○ 기타 : 계획 대비 실적 100% 달성 • AI3 17%(7.7억), BI3 7%(1억), QXI 6%(3.6억) 계획대비↑ • BN7I -28%(3.3억), PS7 -34%(7억), SU2I -18%(3.4억)↓
B8: 재료비 | O8: ○ 매입가 : ○ 재고수불 : ○ 기타 : 계획 대비 실적 재료비 0.7% ↑ • 리어 단가소급 (22년 M2EL 차종) 52백만 (0.30%) • 전년도 인보이스 (모비스) 51백만 (0.30%) • KD 환율변경 45백만 (0.26%) • 직구매 코일 가격 변동 -29백만 (-0.17%)
B11: 구 분 | D11: 추이도 | O11: 실적 분석
B13: 노무비 | O13: ○ 직접직 노무비 : - 직접직 0.01% ↑(계획 467, 실적 446명→21명↓), 휴일특근 ↑ ○ 간접직 노무비 : - 간접직 0.01% ↓(계획 93, 실적 97명→4명 ↑, 푸네지원)
D15: 항 목 | F15: 당 월 | J15: 누 계 | O15: ○ 세부 차이내용 (주요항목) [노무비 지급인원 기재]
F16: 계 획 | G16: % | H16: 실 적 | I16: % | J16: 계 획 | K16: % | L16: 실 적 | M16: %
D17: 매출액 | F17: ='경영실적 PT'!R7 -> 9209.4917 | G17: =F17/F17 -> 1 | H17: ='경영실적 PT'!W7 -> 0 | I17: 1 | J17: ='경영실적 PT'!AG7 -> 26299.702 | K17: =J17/J17 -> 1 | L17: ='경영실적 PT'!AL7 -> 17085.148 | M17: 1
D18: 직접직 | E18: 금액 | F18: ='경영실적 PT'!BB29 -> 222.21474 | G18: =F18/F17 -> 0.024128882 | H18: ='경영실적 PT'!BB32 -> 0 | I18: =H18/H17 -> #DIV/0! | J18: ='경영실적 PT'!BC29 -> 647.97444 | K18: =J18/J17 -> 0.024638091 | L18: ='경영실적 PT'!BC32 -> 424.69515 | M18: =L18/L17 -> 0.024857564
E19: 인원 | F19: =월지표!D60 -> 461 | H19: =월지표!D25 -> 0 | J19: =월지표!F60 -> 462.66667 | L19: =월지표!F25 -> 436
D20: 인당 노무비 | F20: =F18/F19 -> 0.48202763 | H20: =H18/H19 -> #DIV/0! | J20: =J18/J19 -> 1.4005211 | L20: =L18/L19 -> 0.97407144
D21: 간접직 | E21: 금액 | F21: ='경영실적 PT'!BB30 -> 110.00538 | G21: =F21/F17 -> 0.011944783 | H21: ='경영실적 PT'!BB33 -> 0 | I21: =H21/H17 -> #DIV/0! | J21: ='경영실적 PT'!BC30 -> 325.43265 | K21: =J21/J17 -> 0.012374005 | L21: ='경영실적 PT'!BC33 -> 216.77602 | M21: =L21/L17 -> 0.012687981
E22: 인원 | F22: =월지표!D61 -> 93 | H22: =월지표!D26 -> 0 | J22: =월지표!F61 -> 93 | L22: =월지표!F26 -> 98
D23: 인당 노무비 | F23: =F21/F22 -> 1.1828536 | H23: =H21/H22 -> #DIV/0! | J23: =J21/J22 -> 3.4992758 | L23: =L21/L22 -> 2.2120003
D24: 합 계 | F24: =F18+F21 -> 332.22012 | G24: =F24/F17 -> 0.036073665 | H24: =H18+H21 -> 0 | I24: =H24/H17 -> #DIV/0! | J24: =J18+J21 -> 973.40709 | K24: =J24/J17 -> 0.037012096 | L24: =L18+L21 -> 641.47117 | M24: =L24/L17 -> 0.037545544
B26: 구 분 | D26: 추이도 | O26: 실적 분석
B28: 경 비 | O28: ○ 감가상각비 : - 감가상각비 0.1% ↓ ○ 일반경비 : • 건물 수선비 33백만 ↑ └ KM 캐노피,정화조 10백만, 지붕보수 9백만, 기타 (도로,수도,식당) 14백만 • 복리후생 (체육대회연기, 식대등) 40백만 ↓
D30: 항 목 | F30: 당 월 | J30: 누 계 | O30: ○ 일반경비 세부 차이내용 (주요항목)
F31: 계 획 | G31: % | H31: 실 적 | I31: % | J31: 계 획 | K31: % | L31: 실 적 | M31: %
D32: 매출액 | F32: ='경영실적 PT'!R7 -> 9209.4917 | G32: =F32/F32 -> 1 | H32: ='경영실적 PT'!W7 -> 0 | I32: 1 | J32: ='경영실적 PT'!AG7 -> 26299.702 | K32: =J32/J32 -> 1 | L32: ='경영실적 PT'!AL7 -> 17085.148 | M32: 1
D33: 복리후생비 | F33: =경비!M7 -> 63.449312 | G33: =F33/$F$32 -> 0.0068895564 | H33: =경비!M42 -> 0 | I33: =H33/$H$32 -> #DIV/0! | J33: =경비!C42 -> 205.94794 | K33: =J33/$J$32 -> 0.0078308088 | L33: =경비!E42 -> 102.76455 | M33: =L33/$L$32 -> 0.0060148472 | O33: • 체육대회 연기 (우천) 16백만, 항공료 일정변경 8백만, 식대 12백만 ↓
D34: 운반비 | F34: =경비!M14 -> 52.894171 | G34: =F34/$F$32 -> 0.0057434409 | H34: =경비!M49 -> 0 | I34: =H34/$H$32 -> #DIV/0! | J34: =경비!C49 -> 151.16657 | K34: =J34/$J$32 -> 0.0057478434 | L34: =경비!E49 -> 94.064351 | M34: =L34/$L$32 -> 0.0055056212
D35: 소모품비 | F35: =경비!M16 -> 22.936501 | G35: =F35/$F$32 -> 0.0024905285 | H35: =경비!M51 -> 0 | I35: =H35/$H$32 -> #DIV/0! | J35: =경비!C51 -> 65.498983 | K35: =J35/$J$32 -> 0.0024904839 | L35: =경비!E51 -> 37.6166 | M35: =L35/$L$32 -> 0.0022017135
D36: 여비교통비 | F36: =경비!M21 -> 36.8 | G36: =F36/$F$32 -> 0.0039958774 | H36: =경비!M56 -> 0 | I36: =H36/$H$32 -> #DIV/0! | J36: =경비!C56 -> 110.4 | K36: =J36/$J$32 -> 0.0041977662 | L36: =경비!E56 -> 76.26794 | M36: =L36/$L$32 -> 0.0044639906 | O36: • 푸네출장 항공료 ↑(자재, 공무, 회계)
D37: 접대비 | F37: =경비!M22 -> 0.88 | G37: =F37/$F$32 -> 9.5553591e-05 | H37: =경비!M57 -> 0 | I37: =H37/$H$32 -> #DIV/0! | J37: =경비!C57 -> 2.64 | K37: =J37/$J$32 -> 0.00010038137 | L37: =경비!E57 -> 1.932096 | M37: =L37/$L$32 -> 0.00011308629
D38: 지급임차료 | F38: =경비!M19+경비!M20 -> 4.192 | G38: =F38/$F$32 -> 0.00045518256 | H38: =경비!M54+경비!M55 -> 0 | I38: =H38/$H$32 -> #DIV/0! | J38: =경비!C54+경비!C55 -> 12.576 | K38: =J38/$J$32 -> 0.00047818033 | L38: =경비!E54+경비!E55 -> 8.297856 | M38: =L38/$L$32 -> 0.00048567657
D39: 기 타 | F39: =SUM(경비!M8:M13,경비!M15,경비!M17:M18,경비!M23:M26) -> 318.6272 | G39: =F39/$F$32 -> 0.034597697 | H39: =SUM(경비!M43:M48,경비!M50,경비!M52:M53,경비!M58:M61) -> 0 | I39: =H39/$H$32 -> #DIV/0! | J39: =SUM(경비!C43:C48,경비!C50,경비!C52:C53,경비!C58:C61) -> 900.72922 | K39: =J39/$J$32 -> 0.034248648 | L39: =SUM(경비!E43:E48,경비!E50,경비!E52:E53,경비!E58:E61) -> 604.73844 | M39: =L39/$L$32 -> 0.035395564 | O39: • 매출증가에 따른 로열티 감소 • CMM 머신 검교정 3백만, HMI 협력사 회비 1백만
D40: 합 계 | F40: =SUM(F33:F39) -> 499.77919 | G40: =F40/$F$32 -> 0.054267836 | H40: =SUM(H33:H39) -> 0 | I40: =H40/$H$32 -> #DIV/0! | J40: =SUM(J33:J39) -> 1448.9587 | K40: =J40/$J$32 -> 0.055094112 | L40: =SUM(L33:L39) -> 925.68183 | M40: =L40/$L$32 -> 0.054180499
F42: =경비!M31-F40 -> 0 | H42: =경비!M66-H40 -> 0 | J42: =경비!C66-J40 -> 0 | L42: =경비!E66-L40 -> 0

Sheet 경영실적 분석 PT 2
B1: ○ 2024년 만누르 실적분석
B4: 구 분 | D4: 추이도 | P4: 실적 분석
B6: 투자비 | P6: • Repeat mold, crate, PS7I Lever spring - ₩ 19 M
B8: 미수 채권 | D8: 고객사명 | E8: 계약조건 | F8: 미회수 채권 기간별 현황 | P8: ○ 고객사별 미회수 채권 회수방안 [미회수 기간 산정기준 : 전월말 ~ 인보이스 발생일까지 미회수된 채권] [투자비 채권 포함]
F9: 180일 초과 | H9: 90일 초과 | J9: 60일 초과 | L9: 60일 이내 | N9: 계
F10: 건 | G10: 금액 | H10: 건 | I10: 금액 | J10: 건 | K10: 금액 | L10: 건 | M10: 금액
D11: GD Guna Enterprises | E11: 60 day | N11: =G11+I11+K11+M11 -> 0
D12: HTL - SEAT | E12: 45 day | N12: =G12+I12+K12+M12 -> 0
D13: Lear -Chakan | E13: 45 day | N13: =G13+I13+K13+M13 -> 0
D14: Lear -Plant - II | E14: 45 day | N14: =G14+I14+K14+M14 -> 0
D15: Lear Korea | E15: 45 day | N15: =G15+I15+K15+M15 -> 0
D16: METAL | E16: 45 day | N16: =G16+I16+K16+M16 -> 0
D17: MOBIS NEW | E17: 30 day | N17: =G17+I17+K17+M17 -> 0
D18: MOBIS HYD | E18: 30 day | N18: =G18+I18+K18+M18 -> 0
D19: MOBIS | E19: 45 day | N19: =G19+I19+K19+M19 -> 0
D20: NISSAN | E20: 45 day | N20: =G20+I20+K20+M20 -> 0
D21: P.T INDONESIA | E21: 60 day | N21: =G21+I21+K21+M21 -> 0
D22: SPACK | E22: 74 day | N22: =G22+I22+K22+M22 -> 0
D23: UNO | E23: 64 day | N23: =G23+I23+K23+M23 -> 0
D24: 계 | F24: =SUM(F11:F23) -> 0 | G24: =SUM(G11:G23) -> 0 | H24: =SUM(H11:H23) -> 0 | I24: =SUM(I11:I23) -> 0 | J24: =SUM(J11:J23) -> 0 | K24: =SUM(K11:K23) -> 0 | L24: =SUM(L11:L23) -> 0 | M24: =SUM(M11:M23) -> 0 | N24: =G24+I24+K24+M24 -> 0
N25: ='재무상태표(BS)'!I11/1000000 -> 13508.19

Sheet 월계획 
A1: 1. 2023년 월별 실적 | D1: 금액단위: 천원 | F1: 금액단위: 천원 | S1: (단위 : 천원)
A2: 계정과목명 | B2: 2023년 실적 | H2: 01월 | I2: 02월 | J2: 03월 | K2: 04월 | L2: 05월 | M2: 06월 | N2: 07월 | O2: 8월 | P2: 9월 | Q2: 10월 | R2: 11월 | S2: 12월
B3: 금액 | C3: % | H3: 금액 | I3: 금액 | J3: 금액 | K3: 금액 | L3: 금액 | M3: 금액 | N3: 금액 | O3: 금액 | P3: 금액 | Q3: 금액 | R3: 금액 | S3: 금액
A4: 매출액 | B4: =SUM(B5:B7) -> 1.0037462e+08 | C4: =B4/B$4 -> 1 | H4: =SUM(H5:H7) -> 6548315.7 | I4: =SUM(I5:I7) -> 7413490.3 | J4: =SUM(J5:J7) -> 9699250.2 | K4: =SUM(K5:K7) -> 8218007.9 | L4: =SUM(L5:L7) -> 6778472.2 | M4: =SUM(M5:M7) -> 7590160.3 | N4: =SUM(N5:N7) -> 8245472.7 | O4: =SUM(O5:O7) -> 9253877.5 | ... S4: =SUM(S5:S7) -> 9461147.8
A5: 제품매출 | B5: =SUM(H5:S5) -> 98887360 | C5: =B5/B$4 -> 0.98518287 | H5: 6383694.1 | I5: 7336310.8 | J5: 9617694.1 | K5: 8126464.3 | L5: 6689624.5 | M5: 7418345.6 | N5: 7991683.9 | O5: 9023883.2 | P5: 9062873.6 | Q5: 9021749.7 | R5: 8824854.3 | S5: 9390181.7
A6: 상품매출 | B6: =SUM(H6:S6) -> 769207.5 | C6: =B6/B$4 -> 0.0076633662 | H6: 76046.408 | I6: 99640.495 | J6: 42770.167 | K6: 57065.492 | L6: 39624.304 | M6: 111735.14 | N6: 145284.92 | O6: 152892 | P6: 44148.562
A7: 기타매출 | B7: =SUM(H7:S7) -> 718056.65 | C7: =B7/B$4 -> 0.0071537668 | H7: 88575.146 | I7: -22461.021 | J7: 38785.919 | K7: 34478.077 | L7: 49223.423 | M7: 60079.529 | N7: 108503.81 | O7: 77102.274 | P7: 67307.767 | Q7: 66219.778 | R7: 79275.85 | S7: 70966.104
A8: 판매원가 | B8: =B9+B12+B15 -> 94794295 | C8: =B8/B$4 -> 0.94440499 | H8: =H9+H12+H15 -> 6141476.6 | I8: =I9+I12+I15 -> 7094983.6 | J8: =J9+J12+J15 -> 7885538.5 | K8: =K9+K12+K15 -> 7678849.2 | L8: =L9+L12+L15 -> 6446141.1 | M8: =M9+M12+M15 -> 8016315 | N8: =N9+N12+N15 -> 8141281.1 | O8: =O9+O12+O15 -> 8275436.2 | ... S8: =S9+S12+S15 -> 9250509.4
A9: 재료비 소계 | B9: =B10-B11 -> 81330816 | C9: =B9/B$4 -> 0.81027269 | H9: =H10-H11 -> 5114493.7 | I9: =I10-I11 -> 6011002.4 | J9: =J10-J11 -> 6528654.9 | K9: =K10-K11 -> 6617032.8 | L9: =L10-L11 -> 5514531.4 | M9: =M10-M11 -> 7028115.9 | N9: =N10-N11 -> 7099188.4 | O9: =O10-O11 -> 7205634.2 | ... S9: =S10-S11 -> 7952447.2
A10: (재료비) | B10: =SUM(H10:S10) -> 81932486 | C10: =B10/B$4 -> 0.81626693 | H10: 5291853.5 | I10: 6394995.9 | J10: 6084545.3 | K10: 7054801.3 | L10: 6200127.9 | M10: 7095407 | N10: 6714702.2 | O10: 7260304.6 | P10: 7857460.5 | Q10: 7259194.9 | R10: 7023317.6 | S10: 7695775.2
A11: (재고증감) | B11: =SUM(H11:S11) -> 601669.73 | C11: =B11/B$4 -> 0.0059942414 | H11: 177359.87 | I11: 383993.5 | J11: -444109.63 | K11: 437768.49 | L11: 685596.53 | M11: 67291.136 | N11: -384486.17 | O11: 54670.378 | P11: 383205.71 | Q11: -349600.06 | R11: -153348.04 | S11: -256671.99
A12: 노무비 소계 | B12: =SUM(B13:B14) -> 4143693.7 | C12: =B12/B$4 -> 0.041282284 | H12: =SUM(H13:H14) -> 302856.4 | I12: =SUM(I13:I14) -> 299916.28 | J12: =SUM(J13:J14) -> 374812.02 | K12: =SUM(K13:K14) -> 334554.51 | L12: =SUM(L13:L14) -> 299816.72 | M12: =SUM(M13:M14) -> 329662.28 | N12: =SUM(N13:N14) -> 318342.04 | O12: =SUM(O13:O14) -> 327110.41 | ... S12: =SUM(S13:S14) -> 369855.15
A13: (직접노무비) | B13: =SUM(H13:S13) -> 2779247 | C13: =B13/B$4 -> 0.027688741 | H13: 194052.59 | I13: 194614.52 | J13: 233984.94 | K13: 227545.5 | L13: 197624.39 | M13: 230233.45 | N13: 220691 | O13: 231208.31 | P13: 230500.89 | Q13: 226238.02 | R13: 347085.95 | S13: 245467.41
A14: (간접노무비) | B14: =SUM(H14:S14) -> 1364446.7 | C14: =B14/B$4 -> 0.013593543 | H14: 108803.81 | I14: 105301.76 | J14: 140827.08 | K14: 107009.01 | L14: 102192.33 | M14: 99428.832 | N14: 97651.036 | O14: 95902.101 | P14: 105867.11 | Q14: 118540.52 | R14: 158535.39 | S14: 124387.73
A15: 경비 소계 | B15: =SUM(B16:B17) -> 9319785.4 | C15: =B15/B$4 -> 0.092850016 | H15: =SUM(H16:H17) -> 724126.48 | I15: =SUM(I16:I17) -> 784064.92 | J15: =SUM(J16:J17) -> 982071.58 | K15: =SUM(K16:K17) -> 727261.88 | L15: =SUM(L16:L17) -> 631792.95 | M15: =SUM(M16:M17) -> 658536.84 | N15: =SUM(N16:N17) -> 723750.67 | O15: =SUM(O16:O17) -> 742691.55 | ... S15: =SUM(S16:S17) -> 928207.03
A16: (감가상각비) | B16: =SUM(H16:S16) -> 3605812.5 | C16: =B16/B$4 -> 0.035923546 | H16: 286651.54 | I16: 290178.41 | J16: 387236.78 | K16: 263965.71 | L16: 272835.14 | M16: 265450.22 | N16: 277114.83 | O16: 280523.06 | P16: 274954.32 | Q16: 310213.41 | R16: 306870.42 | S16: 389818.62
A17: (기타경비) | B17: =SUM(H17:S17) -> 5713972.9 | C17: =B17/B$4 -> 0.056926469 | H17: 437474.95 | I17: 493886.5 | J17: 594834.79 | K17: 463296.17 | L17: 358957.81 | M17: 393086.61 | N17: 446635.84 | O17: 462168.5 | P17: 468711.8 | Q17: 519334.51 | R17: 537197.05 | S17: 538388.4
A18: 영업이익 | B18: =B4-B8 -> 5580328.7 | C18: =B18/B$4 -> 0.055595015 | H18: =H4-H8 -> 406839.09 | I18: =I4-I8 -> 318506.63 | J18: =J4-J8 -> 1813711.7 | K18: =K4-K8 -> 539158.7 | L18: =L4-L8 -> 332331.15 | M18: =M4-M8 -> -426154.77 | N18: =N4-N8 -> 104191.58 | O18: =O4-O8 -> 978441.34 | ... S18: =S4-S8 -> 210638.41
A19: 영업외수익 | B19: =SUM(H19:S19) -> 1053653.5 | C19: =B19/B$4 -> 0.01049721 | H19: 82997.527 | I19: 71882.296 | J19: 285238.02 | K19: 79927.602 | L19: 66883.713 | M19: 55034.176 | N19: 114393.65 | O19: 72466.191 | P19: 45907.662 | Q19: 51351.343 | R19: 81539.7 | S19: 46031.653
A20: 영업외비용 | B20: =SUM(H20:S20) -> 3012255.3 | C20: =B20/B$4 -> 0.030010128 | H20: 445599.68 | I20: 533815.86 | J20: 497607.9 | K20: 166072.26 | L20: 86913.321 | M20: 135120.62 | N20: 380630.58 | O20: 162624.72 | P20: 191701.71 | Q20: 74872.431 | R20: 137947.14 | S20: 199349.05
A21: 소계 | B21: =B19-B20 -> -1958601.7 | C21: =B21/B$4 -> -0.019512917 | H21: =H19-H20 -> -362602.16 | I21: =I19-I20 -> -461933.56 | J21: =J19-J20 -> -212369.89 | K21: =K19-K20 -> -86144.66 | L21: =L19-L20 -> -20029.608 | M21: =M19-M20 -> -80086.439 | N21: =N19-N20 -> -266236.93 | O21: =O19-O20 -> -90158.529 | ... S21: =S19-S20 -> -153317.4
A22: 경상이익 | B22: =B18+B21 -> 3621727 | C22: =B22/B$4 -> 0.036082097 | H22: =H18+H21 -> 44236.931 | I22: =I18+I21 -> -143426.94 | J22: =J18+J21 -> 1601341.8 | K22: =K18+K21 -> 453014.04 | L22: =L18+L21 -> 312301.55 | M22: =M18+M21 -> -506241.2 | N22: =N18+N21 -> -162045.35 | O22: =O18+O21 -> 888282.81 | ... S22: =S18+S21 -> 57321.016
B23: 3621727
A24: 2. 2024년 추정 손익계획 ← 계획단가 적용(수립시점 표준)
A25: 계정과목명 | B25: 2024년 추정액 | H25: 01월 | I25: 02월 | J25: 03월 | K25: 04월 | L25: 05월 | M25: 06월 | N25: 07월 | O25: 8월 | P25: 9월 | Q25: 10월 | R25: 11월 | S25: 12월
B26: 금액 | C26: % | H26: 금액 | I26: 금액 | J26: 금액 | K26: 금액 | L26: 금액 | M26: 금액 | N26: 금액 | O26: 금액 | P26: 금액 | Q26: 금액 | R26: 금액 | S26: 금액
A27: 매출액 | B27: =SUM(B28:B31) -> 1.0461407e+08 | C27: =B27/B$4 -> 1.0422363 | H27: =SUM(H28:H31) -> 8200673.2 | I27: =SUM(I28:I31) -> 8889536.9 | J27: =SUM(J28:J31) -> 9209491.7 | K27: =SUM(K28:K31) -> 8543837.1 | L27: =SUM(L28:L31) -> 7186028.8 | M27: =SUM(M28:M31) -> 8889304.6 | N27: =SUM(N28:N31) -> 9603975.8 | O27: =SUM(O28:O31) -> 9249341.9 | ... S27: =SUM(S28:S31) -> 8864750.1
A28: 제품매출 | B28: =SUM(H28:S28) -> 1.0313465e+08 | C28: =B28/B$4 -> 1.0274972 | H28: 8077001.9 | I28: 8767555.2 | J28: 9082515.8 | K28: 8419651.1 | L28: 7075977.9 | M28: 8767755.5 | N28: 9478919.2 | O28: 9126371 | P28: 8419649.8 | Q28: 8767656.3 | R28: 8419750.8 | S28: 8731840.6
A29: 상품매출 | B29: =SUM(H29:S29) -> 1076845.6 | C29: =B29/B$4 -> 0.010728266 | H29: 92223.875 | I29: 88211.743 | J29: 92084.603 | K29: 91612.144 | L29: 82233.956 | M29: 87747.092 | N29: 89478.926 | O29: 88599.773 | P29: 85122.735 | Q29: 93441.169 | R29: 92561.41 | S29: 93528.193
A30: 기타매출 | B30: =SUM(H30:S30) -> 741192.23 | C30: =B30/B$4 -> 0.0073842591 | H30: 58458.81 | I30: 63036.907 | J30: 65151.491 | K30: 60712.321 | L30: 51709.066 | M30: 63069.013 | N30: 67675.513 | O30: 65341.497 | P30: 60712.4 | Q30: 63053.083 | R30: 60728.576 | S30: 61543.549
A31: CR금액 | B31: =SUM(H31:S31) -> -338610.36 | C31: =B31/B$4 -> -0.0033734658 | H31: -27011.361 | I31: -29266.969 | J31: -30260.252 | K31: -28138.418 | L31: -23892.148 | M31: -29266.969 | N31: -32097.89 | O31: -30970.363 | P31: -28138.418 | Q31: -29266.969 | R31: -28138.418 | S31: -22162.189
A32: 판매원가 | B32: =B33+B36+B39 -> 98113298 | C32: =B32/B$4 -> 0.97747114 | H32: =H33+H36+H39 -> 7663729.1 | I32: =I33+I36+I39 -> 8239707.5 | J32: =J33+J36+J39 -> 8538930.1 | K32: =K33+K36+K39 -> 7962255.5 | L32: =L33+L36+L39 -> 6816667.7 | M32: =M33+M36+M39 -> 8277133.1 | N32: =N33+N36+N39 -> 8941670.6 | O32: =O33+O36+O39 -> 8629287.1 | ... S32: =S33+S36+S39 -> 8337625.5
A33: 재료비 소계 | B33: =B34-B35 -> 84496424 | C33: =B33/B$4 -> 0.84181061 | H33: =H34-H35 -> 6629660.1 | I33: =I34-I35 -> 7186415.6 | J33: =J34-J35 -> 7437976.3 | K33: =K34-K35 -> 6900296 | L33: =L34-L35 -> 5804719.5 | M33: =M34-M35 -> 7178994.2 | N33: =N34-N35 -> 7757252 | O33: =O34-O35 -> 7470364.5 | ... S33: =S34-S35 -> 7152684.8
A34: (재료비) | B34: =SUM(H34:S34) -> 84496424 | C34: =B34/B$4 -> 0.84181061 | H34: 6629660.1 | I34: 7186415.6 | J34: 7437976.3 | K34: 6900296 | L34: 5804719.5 | M34: 7178994.2 | N34: 7757252 | O34: 7470364.5 | P34: 6895392.5 | Q34: 7182103.4 | R34: 6900564.5 | S34: 7152684.8
A35: (재고증감) | B35: =SUM(H35:S35) -> 0 | C35: =B35/B$4 -> 0
A36: 노무비 소계 | B36: =SUM(B37:B38) -> 4267357.7 | C36: =B36/B$4 -> 0.042514308 | H36: =SUM(H37:H38) -> 314661.74 | I36: =SUM(I37:I38) -> 328034.36 | J36: =SUM(J37:J38) -> 333631.61 | K36: =SUM(K37:K38) -> 332536.94 | L36: =SUM(L37:L38) -> 308083.86 | M36: =SUM(M37:M38) -> 338974.68 | N36: =SUM(N37:N38) -> 351850.18 | O36: =SUM(O37:O38) -> 345412.43 | ... S36: =SUM(S37:S38) -> 368307.72
A37: (직접노무비) | B37: =SUM(H37:S37) -> 2882185.9 | C37: =B37/B$4 -> 0.028714289 | H37: 207958.28 | I37: 219175.33 | J37: 223499.75 | K37: 224467.84 | L37: 204522.57 | M37: 229778.64 | N37: 240400.22 | O37: 235089.43 | P37: 228806.26 | Q37: 235425.57 | R37: 385844.55 | S37: 247217.49
A38: (간접노무비) | B38: =SUM(H38:S38) -> 1385171.8 | C38: =B38/B$4 -> 0.01380002 | H38: 106703.46 | I38: 108859.03 | J38: 110131.86 | K38: 108069.1 | L38: 103561.29 | M38: 109196.05 | N38: 111449.95 | O38: 110323 | P38: 108069.1 | Q38: 115010.91 | R38: 172707.8 | S38: 121090.23
A39: 경비 소계 | B39: =SUM(B40:B41) -> 9349517 | C39: =B39/B$4 -> 0.093146222 | H39: =SUM(H40:H41) -> 719407.31 | I39: =SUM(I40:I41) -> 725257.59 | J39: =SUM(J40:J41) -> 767322.18 | K39: =SUM(K40:K41) -> 729422.58 | L39: =SUM(L40:L41) -> 703864.36 | M39: =SUM(M40:M41) -> 759164.18 | N39: =SUM(N40:N41) -> 832568.5 | O39: =SUM(O40:O41) -> 813510.2 | ... S39: =SUM(S40:S41) -> 816632.9
A40: (감가상각비) | B40: =SUM(H40:S40) -> 3532948.4 | C40: =B40/B$4 -> 0.035197625 | H40: 248195.19 | I40: 247290.19 | J40: 267542.99 | K40: 257266.54 | L40: 280155.5 | M40: 280457.16 | N40: 325179.25 | O40: 325179.25 | P40: 325179.25 | Q40: 325420.58 | R40: 325541.25 | S40: 325541.25
A41: (기타경비) | B41: =SUM(H41:S41) -> 5816568.6 | C41: =B41/B$4 -> 0.057948597 | H41: 471212.12 | I41: 477967.4 | J41: 499779.19 | K41: 472156.04 | L41: 423708.87 | M41: 478707.01 | N41: 507389.25 | O41: 488330.95 | P41: 460505.3 | Q41: 575222.44 | R41: 470498.39 | S41: 491091.65
A42: 영업이익 | B42: =B27-B32 -> 6500774.4 | C42: =B42/B$4 -> 0.064765119 | H42: =H27-H32 -> 536944.05 | I42: =I27-I32 -> 649829.36 | J42: =J27-J32 -> 670561.61 | K42: =K27-K32 -> 581581.6 | L42: =L27-L32 -> 369361.08 | M42: =M27-M32 -> 612171.55 | N42: =N27-N32 -> 662305.12 | O42: =O27-O32 -> 620054.75 | ... S42: =S27-S32 -> 527124.7
A43: 영업외수익 | B43: =SUM(H43:S43) -> 307200 | C43: =B43/B$4 -> 0.0030605345 | H43: =SUM(H44:H47) -> 25600 | I43: =SUM(I44:I47) -> 25600 | J43: =SUM(J44:J47) -> 25600 | K43: =SUM(K44:K47) -> 25600 | L43: =SUM(L44:L47) -> 25600 | M43: =SUM(M44:M47) -> 25600 | N43: =SUM(N44:N47) -> 25600 | O43: =SUM(O44:O47) -> 25600 | ... S43: =SUM(S44:S47) -> 25600
A44: 외환차/평가 | B44: =SUM(H44:S44) -> 0 | C44: =B44/B$85 -> 0
A45: 임대수익 | B45: =SUM(H45:S45) -> 288000 | C45: =B45/B$85 -> 0.0029492569 | H45: =24000000/1000 -> 24000 | I45: =24000000/1000 -> 24000 | J45: =24000000/1000 -> 24000 | K45: =24000000/1000 -> 24000 | L45: =24000000/1000 -> 24000 | M45: =24000000/1000 -> 24000 | N45: =24000000/1000 -> 24000 | O45: =24000000/1000 -> 24000 | ... S45: =24000000/1000 -> 24000
A46: 크레임 수익 | B46: =SUM(H46:S46) -> 0 | C46: =B46/B$85 -> 0
A47: 기타 | B47: =SUM(H47:S47) -> 19200 | C47: =B47/B$85 -> 0.00019661712 | H47: =1600000/1000 -> 1600 | I47: =1600000/1000 -> 1600 | J47: =1600000/1000 -> 1600 | K47: =1600000/1000 -> 1600 | L47: =1600000/1000 -> 1600 | M47: =1600000/1000 -> 1600 | N47: =1600000/1000 -> 1600 | O47: =1600000/1000 -> 1600 | ... S47: =1600000/1000 -> 1600
A48: 영업외비용 | B48: =SUM(H48:S48) -> 1745297.1 | C48: =B48/B$4 -> 0.017387832 | H48: =SUM(H49:H52) -> 107695.71 | I48: =SUM(I49:I52) -> 111636.09 | J48: =SUM(J49:J52) -> 116212.49 | K48: =SUM(K49:K52) -> 123062.59 | L48: =SUM(L49:L52) -> 133301.81 | M48: =SUM(M49:M52) -> 133472.14 | N48: =SUM(N49:N52) -> 154051.52 | O48: =SUM(O49:O52) -> 154016.06 | ... S48: =SUM(S49:S52) -> 249977.6
A49: 외환차/평가 | B49: =SUM(H49:S49) -> 0 | C49: =B49/B$80 -> 0
A50: 이자비용 | B50: =SUM(H50:S50) -> 1625011.7 | C50: =B50/B$80 -> 0.015533395 | H50: =IS!E106/1000 -> 97723.644 | I50: =IS!M106/1000 -> 101595.13 | J50: =IS!U106/1000 -> 106139.54 | K50: =IS!AC106/1000 -> 113056.21 | L50: =IS!AK106/1000 -> 123431.21 | M50: =IS!AS106/1000 -> 123431.21 | N50: =IS!BA106/1000 -> 143939.12 | O50: =IS!BI106/1000 -> 143939.12 | P50: =IS!BQ106/1000 -> 143939.12 | Q50: =IS!BY106/1000 -> 143939.12 | R50: =IS!CG106/1000 -> 143939.12 | S50: =(IS!CO106+IS!CO107)/1000 -> 239939.12
A51: 크레임 비용 | B51: =SUM(H51:S51) -> 10461.407 | C51: =B51/B$80 -> 0.0001 | H51: =IS!E105/1000 -> 820.06732 | I51: =IS!M105/1000 -> 888.95369 | J51: =IS!U105/1000 -> 920.94917 | K51: =IS!AC105/1000 -> 854.38371 | L51: =IS!AK105/1000 -> 718.60288 | M51: =IS!AS105/1000 -> 888.93046 | N51: =IS!BA105/1000 -> 960.39758 | O51: =IS!BI105/1000 -> 924.93419 | P51: =IS!BQ105/1000 -> 853.73465 | Q51: =IS!BY105/1000 -> 889.48836 | R51: =IS!CG105/1000 -> 854.49024 | S51: =IS!CO105/1000 -> 886.47501
A52: 기타 | B52: =SUM(H52:S52) -> 109824 | C52: =B52/B$80 -> 0.0010498014 | H52: =9152000/1000 -> 9152 | I52: =9152000/1000 -> 9152 | J52: =9152000/1000 -> 9152 | K52: =9152000/1000 -> 9152 | L52: =9152000/1000 -> 9152 | M52: =9152000/1000 -> 9152 | N52: =9152000/1000 -> 9152 | O52: =9152000/1000 -> 9152 | ... S52: =9152000/1000 -> 9152
A53: 소계 | B53: =B43-B48 -> -1438097.1 | C53: =B53/B$4 -> -0.014327297 | H53: =H43-H48 -> -82095.712 | I53: =I43-I48 -> -86036.085 | J53: =J43-J48 -> -90612.49 | K53: =K43-K48 -> -97462.591 | L53: =L43-L48 -> -107701.81 | M53: =M43-M48 -> -107872.14 | N53: =N43-N48 -> -128451.52 | O53: =O43-O48 -> -128416.06 | ... S53: =S43-S48 -> -224377.6
A54: 경상이익 | B54: =B42+B53 -> 5062677.3 | C54: =B54/B$4 -> 0.050437821 | H54: =H42+H53 -> 454848.34 | I54: =I42+I53 -> 563793.28 | J54: =J42+J53 -> 579949.12 | K54: =K42+K53 -> 484119.01 | L54: =L42+L53 -> 261659.27 | M54: =M42+M53 -> 504299.41 | N54: =N42+N53 -> 533853.6 | O54: =O42+O53 -> 491638.7 | ... S54: =S42+S53 -> 302747.1
B55: =IS!CW114/1000 -> 5062677.3
A56: 3-1) 원가절감 계획(법인 성과지표) | H56: 0.15 | I56: 0.15 | J56: 0.1 | K56: 0.1 | L56: 0.1 | M56: 0.1 | N56: 0.1 | O56: 0.1 | P56: 0.1
A57: 계정과목명 | B57: 2024년 계획 | H57: 01월 | I57: 02월 | J57: 03월 | K57: 04월 | L57: 05월 | M57: 06월 | N57: 07월 | O57: 8월 | P57: 9월 | Q57: 10월 | R57: 11월 | S57: 12월
B58: 금액 | C58: % | H58: 금액 | I58: 금액 | J58: 금액 | K58: 금액 | L58: 금액 | M58: 금액 | N58: 금액 | O58: 금액 | P58: 금액 | Q58: 금액 | R58: 금액 | S58: 금액
A59: 재료비 절감 | B59: 1066500 | C59: =B59/B$64 -> 0.67981897 | H59: 159975 | I59: 159975 | J59: 106650 | K59: 106650 | L59: 106650 | M59: 106650 | N59: 106650 | O59: 106650 | P59: 106650
A60: 직접노무비 절감 | B60: 101600 | C60: =B60/B$64 -> 0.064762876 | H60: 15240 | I60: 15240 | J60: 10160 | K60: 10160 | L60: 10160 | M60: 10160 | N60: 10160 | O60: 10160 | P60: 10160
A61: 간접노무비 절감 | B61: 10000 | C61: =B61/B$64 -> 0.0063742988 | H61: 1500 | I61: 1500 | J61: 1000 | K61: 1000 | L61: 1000 | M61: 1000 | N61: 1000 | O61: 1000 | P61: 1000
A62: 경비 절감 | B62: 140700 | C62: =B62/B$64 -> 0.089686384 | H62: 21105 | I62: 21105 | J62: 14070 | K62: 14070 | L62: 14070 | M62: 14070 | N62: 14070 | O62: 14070 | P62: 14070
A63: 영업외 비용 | B63: 250000 | C63: =B63/B$64 -> 0.15935747 | H63: 37500 | I63: 37500 | J63: 25000 | K63: 25000 | L63: 25000 | M63: 25000 | N63: 25000 | O63: 25000 | P63: 25000
A64: 합계-실행실적 | B64: =SUM(B59:B63) -> 1568800 | C64: =B64/B$64 -> 1 | H64: =SUM(H59:H63) -> 235320 | I64: =SUM(I59:I63) -> 235320 | J64: =SUM(J59:J63) -> 156880 | K64: =SUM(K59:K63) -> 156880 | L64: =SUM(L59:L63) -> 156880 | M64: =SUM(M59:M63) -> 156880 | N64: =SUM(N59:N63) -> 156880 | O64: =SUM(O59:O63) -> 156880 | ... S64: =SUM(S59:S63) -> 0
P65: 9월까지 년계획 달성
A66: 3-2) 원가절감 경영성효과 (법인계획의 경영성 효과 35%달성 계획) - 수식정정 금지 | H66: 12 | I66: 11 | J66: 10 | K66: 9 | L66: 8 | M66: 7 | N66: 6 | O66: 5 | P66: 4 | Q66: 3 | R66: 2 | S66: 1
A67: 계정과목명 | B67: 2024년 경영성 효과 | H67: 01월 | I67: 02월 | J67: 03월 | K67: 04월 | L67: 05월 | M67: 06월 | N67: 07월 | O67: 8월 | P67: 9월 | Q67: 10월 | R67: 11월 | S67: 12월
B68: 금액 | C68: % | H68: 금액 | I68: 금액 | J68: 금액 | K68: 금액 | L68: 금액 | M68: 금액 | N68: 금액 | O68: 금액 | P68: 금액 | Q68: 금액 | R68: 금액 | S68: 금액
A69: 재료비 절감 | B69: =SUM(H69:S69) -> 373275 | C69: 0.35 | H69: =(SUM(H59)/H$66*$C69)+G69 -> 4665.9375 | I69: =(SUM(I59)/I$66*$C69)+H69 -> 9756.0511 | J69: =(SUM(J59)/J$66*$C69)+I69 -> 13488.801 | K69: =(SUM(K59)/K$66*$C69)+J69 -> 17636.301 | L69: =(SUM(L59)/L$66*$C69)+K69 -> 22302.239 | M69: =(SUM(M59)/M$66*$C69)+L69 -> 27634.739 | N69: =(SUM(N59)/N$66*$C69)+M69 -> 33855.989 | O69: =(SUM(O59)/O$66*$C69)+N69 -> 41321.489 | ... S69: =(SUM(S59)/S$66*$C69)+R69 -> 50653.364
A70: 직접노무비 절감 | B70: =SUM(H70:S70) -> 35560 | C70: 0.35 | H70: =(SUM(H60)/H$66*$C70)+G70 -> 444.5 | I70: =(SUM(I60)/I$66*$C70)+H70 -> 929.40909 | J70: =(SUM(J60)/J$66*$C70)+I70 -> 1285.0091 | K70: =(SUM(K60)/K$66*$C70)+J70 -> 1680.1202 | L70: =(SUM(L60)/L$66*$C70)+K70 -> 2124.6202 | M70: =(SUM(M60)/M$66*$C70)+L70 -> 2632.6202 | N70: =(SUM(N60)/N$66*$C70)+M70 -> 3225.2869 | O70: =(SUM(O60)/O$66*$C70)+N70 -> 3936.4869 | ... S70: =(SUM(S60)/S$66*$C70)+R70 -> 4825.4869
A71: 간접노무비 절감 | B71: =SUM(H71:S71) -> 3500 | C71: 0.35 | H71: =(SUM(H61)/H$66*$C71)+G71 -> 43.75 | I71: =(SUM(I61)/I$66*$C71)+H71 -> 91.477273 | J71: =(SUM(J61)/J$66*$C71)+I71 -> 126.47727 | K71: =(SUM(K61)/K$66*$C71)+J71 -> 165.36616 | L71: =(SUM(L61)/L$66*$C71)+K71 -> 209.11616 | M71: =(SUM(M61)/M$66*$C71)+L71 -> 259.11616 | N71: =(SUM(N61)/N$66*$C71)+M71 -> 317.44949 | O71: =(SUM(O61)/O$66*$C71)+N71 -> 387.44949 | ... S71: =(SUM(S61)/S$66*$C71)+R71 -> 474.94949
A72: 경비 절감 | B72: =SUM(H72:S72) -> 49245 | C72: 0.35 | H72: =(SUM(H62)/H$66*$C72)+G72 -> 615.5625 | I72: =(SUM(I62)/I$66*$C72)+H72 -> 1287.0852 | J72: =(SUM(J62)/J$66*$C72)+I72 -> 1779.5352 | K72: =(SUM(K62)/K$66*$C72)+J72 -> 2326.7019 | L72: =(SUM(L62)/L$66*$C72)+K72 -> 2942.2644 | M72: =(SUM(M62)/M$66*$C72)+L72 -> 3645.7644 | N72: =(SUM(N62)/N$66*$C72)+M72 -> 4466.5144 | O72: =(SUM(O62)/O$66*$C72)+N72 -> 5451.4144 | ... S72: =(SUM(S62)/S$66*$C72)+R72 -> 6682.5394
A73: 영업외 비용 | B73: =SUM(H73:S73) -> 87500 | C73: 0.35 | H73: =(SUM(H63)/H$66*$C73)+G73 -> 1093.75 | I73: =(SUM(I63)/I$66*$C73)+H73 -> 2286.9318 | J73: =(SUM(J63)/J$66*$C73)+I73 -> 3161.9318 | K73: =(SUM(K63)/K$66*$C73)+J73 -> 4134.154 | L73: =(SUM(L63)/L$66*$C73)+K73 -> 5227.904 | M73: =(SUM(M63)/M$66*$C73)+L73 -> 6477.904 | N73: =(SUM(N63)/N$66*$C73)+M73 -> 7936.2374 | O73: =(SUM(O63)/O$66*$C73)+N73 -> 9686.2374 | ... S73: =(SUM(S63)/S$66*$C73)+R73 -> 11873.737
A74: 합계-경영성실적 | B74: =SUM(B69:B73) -> 549080 | H74: =SUM(H69:H73) -> 6863.5 | I74: =SUM(I69:I73) -> 14350.955 | J74: =SUM(J69:J73) -> 19841.755 | K74: =SUM(K69:K73) -> 25942.643 | L74: =SUM(L69:L73) -> 32806.143 | M74: =SUM(M69:M73) -> 40650.143 | N74: =SUM(N69:N73) -> 49801.477 | O74: =SUM(O69:O73) -> 60783.077 | ... S74: =SUM(S69:S73) -> 74510.077
A75: ☞ 원가절감 실행 후 2023년 실질적 효과볼 수 있는 월금액 재정리
B76: =B74/B64 -> 0.35
A77: 4. 2024년 경영계획 → 원가절감 경영성실적 원가 차감
A78: 계정과목명 | B78: 2024년 연간계획 | D78: 2024년 당월계획 | F78: 2024년 누계계획 | H78: 01월 | I78: 02월 | J78: 03월 | K78: 04월 | L78: 05월 | M78: 06월 | N78: 07월 | O78: 8월 | P78: 9월 | Q78: 10월 | R78: 11월 | S78: 12월
B79: 금액 | C79: % | D79: 금액 | E79: % | F79: 금액 | G79: % | H79: 금액 | I79: 금액 | J79: 금액 | K79: 금액 | L79: 금액 | M79: 금액 | N79: 금액 | O79: 금액 | P79: 금액 | Q79: 금액 | R79: 금액 | S79: 금액
A80: 매출액 | B80: =SUM(B81:B84) -> 1.0461407e+08 | C80: =B80/B$80 -> 1 | D80: =J80 -> 9209491.7 | E80: =D80/D$80 -> 1 | F80: =SUM(H80:J80) -> 26299702 | G80: =F80/F$80 -> 1 | H80: =SUM(H81:H84) -> 8200673.2 | I80: =SUM(I81:I84) -> 8889536.9 | J80: =SUM(J81:J84) -> 9209491.7 | K80: =SUM(K81:K84) -> 8543837.1 | L80: =SUM(L81:L84) -> 7186028.8 | M80: =SUM(M81:M84) -> 8889304.6 | N80: =SUM(N81:N84) -> 9603975.8 | O80: =SUM(O81:O84) -> 9249341.9 | ... S80: =SUM(S81:S84) -> 8864750.1
A81: 제품매출 | B81: =SUM(H81:S81) -> 1.0313465e+08 | C81: =B81/B$80 -> 0.98585824 | D81: =J81 -> 9082515.8 | E81: =D81/D$80 -> 0.9862125 | F81: =SUM(H81:J81) -> 25927073 | G81: =F81/F$80 -> 0.98583144 | H81: =H28 -> 8077001.9 | I81: =I28 -> 8767555.2 | J81: =J28 -> 9082515.8 | K81: =K28 -> 8419651.1 | L81: =L28 -> 7075977.9 | M81: =M28 -> 8767755.5 | N81: =N28 -> 9478919.2 | O81: =O28 -> 9126371 | ... S81: =S28 -> 8731840.6
A82: 상품매출 | B82: =SUM(H82:S82) -> 1076845.6 | C82: =B82/B$80 -> 0.010293506 | D82: =J82 -> 92084.603 | E82: =D82/D$80 -> 0.00999888 | F82: =SUM(H82:J82) -> 272520.22 | G82: =F82/F$80 -> 0.010362103 | H82: =H29 -> 92223.875 | I82: =I29 -> 88211.743 | J82: =J29 -> 92084.603 | K82: =K29 -> 91612.144 | L82: =L29 -> 82233.956 | M82: =M29 -> 87747.092 | N82: =N29 -> 89478.926 | O82: =O29 -> 88599.773 | ... S82: =S29 -> 93528.193
A83: 기타매출 | B83: =SUM(H83:S83) -> 741192.23 | C83: =B83/B$80 -> 0.0070850145 | D83: =J83 -> 65151.491 | E83: =D83/D$80 -> 0.0070743852 | F83: =SUM(H83:J83) -> 186647.21 | G83: =F83/F$80 -> 0.0070969325 | H83: =H30 -> 58458.81 | I83: =I30 -> 63036.907 | J83: =J30 -> 65151.491 | K83: =K30 -> 60712.321 | L83: =L30 -> 51709.066 | M83: =M30 -> 63069.013 | N83: =N30 -> 67675.513 | O83: =O30 -> 65341.497 | ... S83: =S30 -> 61543.549
A84: CR금액 | B84: =SUM(H84:S84) -> -338610.36 | C84: =B84/B$80 -> -0.0032367573 | D84: =J84 -> -30260.252 | E84: =D84/D$80 -> -0.0032857678 | F84: =SUM(H84:J84) -> -86538.581 | G84: =F84/F$80 -> -0.0032904777 | H84: =H31 -> -27011.361 | I84: =I31 -> -29266.969 | J84: =J31 -> -30260.252 | K84: =K31 -> -28138.418 | L84: =L31 -> -23892.148 | M84: =M31 -> -29266.969 | N84: =N31 -> -32097.89 | O84: =O31 -> -30970.363 | ... S84: =S31 -> -22162.189
A85: 판매원가 | B85: =B86+B89+B92 -> 97651718 | C85: =B85/B$80 -> 0.93344725 | D85: =J85 -> 8522250.3 | E85: =D85/D$80 -> 0.92537683 | F85: =SUM(H85:J85) -> 24407853 | G85: =F85/F$80 -> 0.92806578 | H85: =H86+H89+H92 -> 7657959.4 | I85: =I86+I89+I92 -> 8227643.5 | J85: =J86+J89+J92 -> 8522250.3 | K85: =K86+K89+K92 -> 7940447.1 | L85: =L86+L89+L92 -> 6789089.5 | M85: =M86+M89+M92 -> 8242960.8 | N85: =N86+N89+N92 -> 8899805.4 | O85: =O86+O89+O92 -> 8578190.3 | ... S85: =S86+S89+S92 -> 8274989.1
A86: 재료비 소계 | B86: =B87-B88 -> 84123149 | C86: =B86/B$80 -> 0.80412842 | D86: =J86 -> 7424487.5 | E86: =D86/D$80 -> 0.80617777 | F86: =SUM(H86:J86) -> 21226141 | G86: =F86/F$80 -> 0.80708676 | H86: =H87-H88 -> 6624994.2 | I86: =I87-I88 -> 7176659.5 | J86: =J87-J88 -> 7424487.5 | K86: =K87-K88 -> 6882659.7 | L86: =L87-L88 -> 5782417.3 | M86: =M87-M88 -> 7151359.5 | N86: =N87-N88 -> 7723396 | O86: =O87-O88 -> 7429043 | ... S86: =S87-S88 -> 7102031.5
A87: (재료비) | B87: =SUM(H87:S87) -> 84123149 | C87: =B87/B$80 -> 0.80412842 | D87: =J87 -> 7424487.5 | E87: =D87/D$80 -> 0.80617777 | F87: =SUM(H87:J87) -> 21226141 | G87: =F87/F$80 -> 0.80708676 | H87: =H34-H69 -> 6624994.2 | I87: =I34-I69 -> 7176659.5 | J87: =J34-J69 -> 7424487.5 | K87: =K34-K69 -> 6882659.7 | L87: =L34-L69 -> 5782417.3 | M87: =M34-M69 -> 7151359.5 | N87: =N34-N69 -> 7723396 | O87: =O34-O69 -> 7429043 | ... S87: =S34-S69 -> 7102031.5
A88: (재고증감) | B88: =SUM(H88:S88) -> 0 | C88: =B88/B$80 -> 0 | D88: =J88 -> 0 | E88: =D88/D$80 -> 0 | F88: =SUM(H88:J88) -> 0 | G88: =F88/F$80 -> 0 | H88: =H35 -> 0 | I88: =I35 -> 0 | J88: =J35 -> 0 | K88: =K35 -> 0 | L88: =L35 -> 0 | M88: =M35 -> 0 | N88: =N35 -> 0 | O88: =O35 -> 0 | ... S88: =S35 -> 0
A89: 노무비 소계 | B89: =SUM(B90:B91) -> 4228297.7 | C89: =B89/B$80 -> 0.040418058 | D89: =J89 -> 332220.12 | E89: =D89/D$80 -> 0.036073665 | F89: =SUM(H89:J89) -> 973407.09 | G89: =F89/F$80 -> 0.037012096 | H89: =SUM(H90:H91) -> 314173.49 | I89: =SUM(I90:I91) -> 327013.47 | J89: =SUM(J90:J91) -> 332220.12 | K89: =SUM(K90:K91) -> 330691.45 | L89: =SUM(L90:L91) -> 305750.12 | M89: =SUM(M90:M91) -> 336082.95 | N89: =SUM(N90:N91) -> 348307.44 | O89: =SUM(O90:O91) -> 341088.49 | ... S89: =SUM(S90:S91) -> 363007.28
A90: (직접노무비) | B90: =SUM(H90:S90) -> 2846625.9 | C90: =B90/B$80 -> 0.027210736 | D90: =J90 -> 222214.74 | E90: =D90/D$80 -> 0.024128882 | F90: =SUM(H90:J90) -> 647974.44 | G90: =F90/F$80 -> 0.024638091 | H90: =H37-H70 -> 207513.78 | I90: =I37-I70 -> 218245.92 | J90: =J37-J70 -> 222214.74 | K90: =K37-K70 -> 222787.72 | L90: =L37-L70 -> 202397.95 | M90: =M37-M70 -> 227146.02 | N90: =N37-N70 -> 237174.94 | O90: =O37-O70 -> 231152.94 | ... S90: =S37-S70 -> 242392
A91: (간접노무비) | B91: =SUM(H91:S91) -> 1381671.8 | C91: =B91/B$80 -> 0.013207322 | D91: =J91 -> 110005.38 | E91: =D91/D$80 -> 0.011944783 | F91: =SUM(H91:J91) -> 325432.65 | G91: =F91/F$80 -> 0.012374005 | H91: =H38-H71 -> 106659.71 | I91: =I38-I71 -> 108767.55 | J91: =J38-J71 -> 110005.38 | K91: =K38-K71 -> 107903.73 | L91: =L38-L71 -> 103352.17 | M91: =M38-M71 -> 108936.93 | N91: =N38-N71 -> 111132.5 | O91: =O38-O71 -> 109935.55 | ... S91: =S38-S71 -> 120615.28
A92: 경비 소계 | B92: =SUM(B93:B94) -> 9300272 | C92: =B92/B$80 -> 0.088900774 | D92: =J92 -> 765542.64 | E92: =D92/D$80 -> 0.083125396 | F92: =SUM(H92:J92) -> 2208304.9 | G92: =F92/F$80 -> 0.083966918 | H92: =SUM(H93:H94) -> 718791.75 | I92: =SUM(I93:I94) -> 723970.51 | J92: =SUM(J93:J94) -> 765542.64 | K92: =SUM(K93:K94) -> 727095.87 | L92: =SUM(L93:L94) -> 700922.1 | M92: =SUM(M93:M94) -> 755518.41 | N92: =SUM(N93:N94) -> 828101.98 | O92: =SUM(O93:O94) -> 808058.78 | ... S92: =SUM(S93:S94) -> 809950.36
A93: (감가상각비) | B93: =SUM(H93:S93) -> 3532948.4 | C93: =B93/B$80 -> 0.033771254 | D93: =J93 -> 267542.99 | E93: =D93/D$80 -> 0.029050788 | F93: =SUM(H93:J93) -> 763028.38 | G93: =F93/F$80 -> 0.029012815 | H93: =H40 -> 248195.19 | I93: =I40 -> 247290.19 | J93: =J40 -> 267542.99 | K93: =K40 -> 257266.54 | L93: =L40 -> 280155.5 | M93: =M40 -> 280457.16 | N93: =N40 -> 325179.25 | O93: =O40 -> 325179.25 | ... S93: =S40 -> 325541.25
A94: (기타경비) | B94: =SUM(H94:S94) -> 5767323.6 | C94: =B94/B$80 -> 0.05512952 | D94: =J94 -> 497999.65 | E94: =D94/D$80 -> 0.054074608 | F94: =SUM(H94:J94) -> 1445276.5 | G94: =F94/F$80 -> 0.054954103 | H94: =H41-H72 -> 470596.56 | I94: =I41-I72 -> 476680.31 | J94: =J41-J72 -> 497999.65 | K94: =K41-K72 -> 469829.34 | L94: =L41-L72 -> 420766.6 | M94: =M41-M72 -> 475061.25 | N94: =N41-N72 -> 502922.74 | O94: =O41-O72 -> 482879.54 | ... S94: =S41-S72 -> 484409.11
A95: 영업이익 | B95: =B80-B85 -> 6962354.4 | C95: =B95/B$80 -> 0.066552752 | D95: =J95 -> 687241.44 | E95: =D95/D$80 -> 0.074623167 | F95: =SUM(H95:J95) -> 1891848.6 | G95: =F95/F$80 -> 0.071934223 | H95: =H80-H85 -> 542713.8 | I95: =I80-I85 -> 661893.39 | J95: =J80-J85 -> 687241.44 | K95: =K80-K85 -> 603390.09 | L95: =L80-L85 -> 396939.32 | M95: =M80-M85 -> 646343.79 | N95: =N80-N85 -> 704170.36 | O95: =O80-O85 -> 671151.59 | ... S95: =S80-S85 -> 589761.04
A96: 영업외수익 | B96: =SUM(H96:S96) -> 307200 | C96: =B96/B$80 -> 0.0029365074 | D96: =J96 -> 25600 | E96: =D96/D$80 -> 0.0027797408 | F96: =SUM(H96:J96) -> 76800 | G96: =F96/F$80 -> 0.0029201852 | H96: =H43 -> 25600 | I96: =I43 -> 25600 | J96: =J43 -> 25600 | K96: =K43 -> 25600 | L96: =L43 -> 25600 | M96: =M43 -> 25600 | N96: =N43 -> 25600 | O96: =O43 -> 25600 | ... S96: =S43 -> 25600
A97: 외환차/평가 | B97: =SUM(H97:S97) -> 0 | C97: =B97/B$80 -> 0 | D97: =J97 -> 0 | E97: =D97/D$80 -> 0 | F97: =SUM(H97:J97) -> 0 | G97: =F97/F$80 -> 0 | H97: =H44 -> 0 | I97: =I44 -> 0 | J97: =J44 -> 0 | K97: =K44 -> 0 | L97: =L44 -> 0 | M97: =M44 -> 0 | N97: =N44 -> 0 | O97: =O44 -> 0 | ... S97: =S44 -> 0
A98: 임대수익 | B98: =SUM(H98:S98) -> 288000 | C98: =B98/B$80 -> 0.0027529757 | D98: =J98 -> 24000 | E98: =D98/D$80 -> 0.002606007 | F98: =SUM(H98:J98) -> 72000 | G98: =F98/F$80 -> 0.0027376736 | H98: =H45 -> 24000 | I98: =I45 -> 24000 | J98: =J45 -> 24000 | K98: =K45 -> 24000 | L98: =L45 -> 24000 | M98: =M45 -> 24000 | N98: =N45 -> 24000 | O98: =O45 -> 24000 | ... S98: =S45 -> 24000
A99: 크레임 수익 | B99: =SUM(H99:S99) -> 0 | C99: =B99/B$80 -> 0 | D99: =J99 -> 0 | E99: =D99/D$80 -> 0 | F99: =SUM(H99:J99) -> 0 | G99: =F99/F$80 -> 0 | H99: =H46 -> 0 | I99: =I46 -> 0 | J99: =J46 -> 0 | K99: =K46 -> 0 | L99: =L46 -> 0 | M99: =M46 -> 0 | N99: =N46 -> 0 | O99: =O46 -> 0 | ... S99: =S46 -> 0
A100: 기타 | B100: =SUM(H100:S100) -> 19200 | C100: =B100/B$80 -> 0.00018353171 | D100: =J100 -> 1600 | E100: =D100/D$80 -> 0.0001737338 | F100: =SUM(H100:J100) -> 4800 | G100: =F100/F$80 -> 0.00018251158 | H100: =H47 -> 1600 | I100: =I47 -> 1600 | J100: =J47 -> 1600 | K100: =K47 -> 1600 | L100: =L47 -> 1600 | M100: =M47 -> 1600 | N100: =N47 -> 1600 | O100: =O47 -> 1600 | ... S100: =S47 -> 1600
...

Sheet 투자비
A1: ■ 2024년 투자계획(예산)
M2: 단위 : 천원
A3: 자산유형 | B3: 프로젝트(차종) | C3: 내 용 | D3: 투자비 계획 | I3: 당 월 | K3: 누 계 | M3: 비 고
D4: 금 액 | E4: 1분기 | F4: 2분기 | G4: 3분기 | H4: 4분기 | I4: 계획 | J4: 실적 | K4: 계획 | L4: 실적
A5: 토 지
A6: 건 물
A8: 기계장치 | B8: 공용 | C8: 금형 공정개선 관련 금형신작 및 수정 업무 | D8: =SUM(E8:H8) -> 60000 | E8: =SUM(O47:Q47) -> 18000 | F8: =SUM(R47:T47) -> 18000 | G8: =SUM(U47:W47) -> 18000 | H8: =SUM(X47:Z47) -> 6000 | I8: =P47 -> 6000 | J8: =E74 -> 0 | K8: =SUM(O47:P47) -> 12000 | L8: =SUM(D74:E74) -> 0
A9: 기계장치 | B9: 공용 | C9: 밀링머신 구매 | D9: =SUM(E9:H9) -> 15000 | E9: =SUM(O48:Q48) -> 15000 | F9: =SUM(R48:T48) -> 0 | G9: =SUM(U48:W48) -> 0 | H9: =SUM(X48:Z48) -> 0 | I9: =P48 -> 0 | J9: =E75 -> 0 | K9: =SUM(O48:P48) -> 0 | L9: =SUM(D75:E75) -> 0
A10: 기계장치 | B10: QXI/PS7I/SU2I | C10: 신규라인, 미설치라인 유해GAS 배출기 설치 | D10: =SUM(E10:H10) -> 20000 | E10: =SUM(O49:Q49) -> 0 | F10: =SUM(R49:T49) -> 20000 | G10: =SUM(U49:W49) -> 0 | H10: =SUM(X49:Z49) -> 0 | I10: =P49 -> 0 | J10: =E76 -> 0 | K10: =SUM(O49:P49) -> 0 | L10: =SUM(D76:E76) -> 0
A11: 기계장치 | B11: 공용 | C11: 현대로보트 수리자재 구매(CO2로보트 - 설비 오바홀) | D11: =SUM(E11:H11) -> 30000 | E11: =SUM(O50:Q50) -> 0 | F11: =SUM(R50:T50) -> 10000 | G11: =SUM(U50:W50) -> 20000 | H11: =SUM(X50:Z50) -> 0 | I11: =P50 -> 0 | J11: =E77 -> 0 | K11: =SUM(O50:P50) -> 0 | L11: =SUM(D77:E77) -> 0
A12: 기계장치 | B12: 공용 | C12: 디젤보관장 안전라이센스 등록 | D12: =SUM(E12:H12) -> 7000 | E12: =SUM(O51:Q51) -> 7000 | F12: =SUM(R51:T51) -> 0 | G12: =SUM(U51:W51) -> 0 | H12: =SUM(X51:Z51) -> 0 | I12: =P51 -> 0 | J12: =E78 -> 0 | K12: =SUM(O51:P51) -> 0 | L12: =SUM(D78:E78) -> 0
A13: 기계장치 | B13: 공용 | C13: 24년 공정개선 및 원가절감 세부 추진 계획 관련 개선 투자 비용 (공정개선, 공정용/완성품 PLT 자체제작, 안전팬스 제작,설치 및 공장개선 활동) | D13: =SUM(E13:H13) -> 128000 | E13: =SUM(O52:Q52) -> 16000 | F13: =SUM(R52:T52) -> 48000 | G13: =SUM(U52:W52) -> 48000 | H13: =SUM(X52:Z52) -> 16000 | I13: =P52 -> 0 | J13: =E79 -> 0 | K13: =SUM(O52:P52) -> 0 | L13: =SUM(D79:E79) -> 0
A14: 기계장치 | B14: SU2I | C14: SU2I 다단레치 - 조립 및 검사 전용기 7EA / CO2로보트 1EA | D14: =SUM(E14:H14) -> 1000000 | E14: =SUM(O53:Q53) -> 0 | F14: =SUM(R53:T53) -> 0 | G14: =SUM(U53:W53) -> 1000000 | H14: =SUM(X53:Z53) -> 0 | I14: =P53 -> 0 | J14: =E80 -> 0 | K14: =SUM(O53:P53) -> 0 | L14: =SUM(D80:E80) -> 0
A15: 기계장치 | B15: SU2I | C15: SU2I 다단레치 금형(1 LOT) | D15: =SUM(E15:H15) -> 300000 | E15: =SUM(O54:Q54) -> 0 | F15: =SUM(R54:T54) -> 0 | G15: =SUM(U54:W54) -> 300000 | H15: =SUM(X54:Z54) -> 0 | I15: =P54 -> 0 | J15: =E81 -> 0 | K15: =SUM(O54:P54) -> 0 | L15: =SUM(D81:E81) -> 0
A16: 기계장치 | B16: SU2I EV | C16: SU2I EV 버스바 전용라인(2.6만대 기준) - 조립 및 검사 전용기 6EA | D16: =SUM(E16:H16) -> 1665000 | E16: =SUM(O55:Q55) -> 0 | F16: =SUM(R55:T55) -> 0 | G16: =SUM(U55:W55) -> 1665000 | H16: =SUM(X55:Z55) -> 0 | I16: =P55 -> 0 | J16: =E82 -> 0 | K16: =SUM(O55:P55) -> 0 | L16: =SUM(D82:E82) -> 0
A17: 기계장치 | B17: 공용 | C17: 3톤 지게차 구매(생산팀 지게차 교체) | D17: =SUM(E17:H17) -> 10000 | E17: =SUM(O56:Q56) -> 10000 | F17: =SUM(R56:T56) -> 0 | G17: =SUM(U56:W56) -> 0 | H17: =SUM(X56:Z56) -> 0 | I17: =P56 -> 0 | J17: =E83 -> 0 | K17: =SUM(O56:P56) -> 0 | L17: =SUM(D83:E83) -> 0
A18: 기계장치 | B18: UPS | C18: 에어컨(UPS BATTERY ROOM 설치) | D18: =SUM(E18:H18) -> 8000 | E18: =SUM(O57:Q57) -> 8000 | F18: =SUM(R57:T57) -> 0 | G18: =SUM(U57:W57) -> 0 | H18: =SUM(X57:Z57) -> 0 | I18: =P57 -> 8000 | J18: =E84 -> 0 | K18: =SUM(O57:P57) -> 8000 | L18: =SUM(D84:E84) -> 0
A19: 기계장치 | B19: 공용 | C19: LED 전등 신규 설치 및 노후 제품 교체 | D19: =SUM(E19:H19) -> 12000 | E19: =SUM(O58:Q58) -> 12000 | F19: =SUM(R58:T58) -> 0 | G19: =SUM(U58:W58) -> 0 | H19: =SUM(X58:Z58) -> 0 | I19: =P58 -> 4000 | J19: =E85 -> 0 | K19: =SUM(O58:P58) -> 8000 | L19: =SUM(D85:E85) -> 0
... A27: 기계장치 | B27: 공용 | C27: 프레스 소모품교체(모터베어링 8대분) | D27: =SUM(E27:H27) -> 8000 | E27: =SUM(O66:Q66) -> 0 | F27: =SUM(R66:T66) -> 0 | G27: =SUM(U66:W66) -> 0 | H27: =SUM(X66:Z66) -> 8000 | I27: =P66 -> 0 | J27: =E93 -> 0 | K27: =SUM(O66:P66) -> 0 | L27: =SUM(D93:E93) -> 0
D28: =SUM(E28:H28) -> 0 | J28: =E94 -> 0 | L28: =SUM(D94:E94) -> 0
J29: =E95 -> 19208 | L29: =SUM(D95:E95) -> 19208
A30: 차량운반구 | D30: =SUM(E30:H30) -> 0 | J30: =E96 -> 0 | L30: =SUM(D96:E96) -> 0
A31: 공구와기구 | D31: =SUM(E31:H31) -> 0 | J31: =E97 -> 0 | L31: =SUM(D97:E97) -> 0
A32: 비 품 | B32: 공용 | D32: =SUM(E32:H32) -> 0 | J32: =E98 -> 0 | L32: =SUM(D98:E98) -> 0
A33: 비 품 | B33: 공용 | D33: =SUM(E33:H33) -> 0 | J33: =E99 -> 0 | L33: =SUM(D99:E99) -> 0
A34: 건설중인 자산 | D34: =SUM(E34:H34) -> 0
A35: 금 형 | B35: 공용 | D35: =SUM(E35:H35) -> 0
A36: 무형자산 | B36: 공용 | D36: =SUM(E36:H36) -> 0
A37: 합 계 | D37: =SUM(D5:D36) -> 5804500 | I37: =SUM(I5:I36) -> 18000 | J37: =SUM(J5:J36) -> 19208 | K37: =SUM(K5:K36) -> 36000 | L37: =SUM(L5:L36) -> 19208
A43: 월별 투자비 계획
A45: 프로젝트 or 차종 | B45: 투자내용 | E45: 투자예상액 | F45: 투자기간 | G45: 비 고 | H45: 재분류
B46: 품목(항목) | C46: 수량 | D46: 내 용 | H46: 주관부서 | I46: 투자계정 | J46: 귀속법인 | O46: 1월 | P46: 2월 | Q46: 3월 | R46: 4월 | S46: 5월 | T46: 6월 | U46: 7월 | V46: 8월 | W46: 9월 | X46: 10월 | Y46: 11월 | Z46: 12월
A47: 공용 | B47: 금형 | C47: 6 | D47: 금형 공정개선 관련 금형신작 및 수정 업무 | E47: 60000 | F47: 1~10월 | H47: 금형팀 | I47: 금형 | J47: 인도1공장 | O47: =$E$47/10 -> 6000 | P47: =$E$47/10 -> 6000 | Q47: =$E$47/10 -> 6000 | R47: =$E$47/10 -> 6000 | S47: =$E$47/10 -> 6000 | T47: =$E$47/10 -> 6000 | U47: =$E$47/10 -> 6000 | V47: =$E$47/10 -> 6000 | ... X47: =$E$47/10 -> 6000 | AA47: =SUM(O47:Z47)-E47 -> 0
A48: 공용 | B48: 기계장치 | C48: 1 | D48: 밀링머신 구매 | E48: 15000 | F48: 3월 | H48: 보전팀 | I48: 기계장치 | J48: 인도1공장 | Q48: =E48 -> 15000 | AA48: =SUM(O48:Z48)-E48 -> 0
A49: QXI/PS7I/SU2I | B49: 구축물 | C49: 3 | D49: 신규라인, 미설치라인 유해GAS 배출기 설치 | E49: 20000 | F49: 4월 | H49: 보전팀 | I49: 구축물 | J49: 인도1공장 | R49: =E49 -> 20000 | AA49: =SUM(O49:Z49)-E49 -> 0
A50: 공용 | B50: 기계장치 | C50: 6 | D50: 현대로보트 수리자재 구매(CO2로보트 - 설비 오바홀) | E50: 30000 | F50: 6~9월 | H50: 보전팀 | I50: 기계장치 | J50: 인도1공장 | T50: =$E50/3 -> 10000 | U50: =$E50/3 -> 10000 | V50: =$E50/3 -> 10000 | AA50: =SUM(O50:Z50)-E50 -> 0
A51: 공용 | B51: 안전관리 | C51: 1 | D51: 디젤보관장 안전라이센스 등록 | E51: 7000 | F51: 3월 | H51: 보전팀 | I51: 무형자산 | J51: 인도1공장 | Q51: =E51 -> 7000 | AA51: =SUM(O51:Z51)-E51 -> 0
A52: 공용 | B52: 공정개선 &자체 제작 | C52: 1100 | D52: 24년 공정개선 및 원가절감 세부 추진 계획 관련 개선 투자 비용 (공정개선, 공정용/완성품 PLT 자체제작, 안전팬스 제작,설치 및 공장개선 활동) | E52: 128000 | F52: 3~10월 | H52: 보전팀 | I52: 공구와기구 | J52: 인도1공장 | Q52: =$E$52/8 -> 16000 | R52: =$E$52/8 -> 16000 | S52: =$E$52/8 -> 16000 | T52: =$E$52/8 -> 16000 | U52: =$E$52/8 -> 16000 | V52: =$E$52/8 -> 16000 | W52: =$E$52/8 -> 16000 | X52: =$E$52/8 -> 16000 | AA52: =SUM(O52:Z52)-E52 -> 0
A53: SU2I | B53: 전용기 | C53: 8 | D53: SU2I 다단레치 - 조립 및 검사 전용기 7EA / CO2로보트 1EA | E53: 1000000 | F53: 7월 | H53: 보전팀 | I53: 기계장치 | J53: 인도1공장 | U53: =E53 -> 1000000 | AA53: =SUM(O53:Z53)-E53 -> 0
A54: SU2I | B54: 금형 | C54: 1 | D54: SU2I 다단레치 금형(1 LOT) | E54: 300000 | F54: 7월 | H54: 금형팀 | I54: 금형 | J54: 인도1공장 | U54: =E54 -> 300000 | AA54: =SUM(O54:Z54)-E54 -> 0
A55: SU2I EV | B55: 전용기 | C55: 6 | D55: SU2I EV 버스바 전용라인(2.6만대 기준) - 조립 및 검사 전용기 6EA | E55: 1665000 | F55: 7월 | H55: 보전팀 | I55: 기계장치 | J55: 인도1공장 | U55: =E55 -> 1665000 | AA55: =SUM(O55:Z55)-E55 -> 0
A56: 공용 | B56: 기계장치 | C56: 1 | D56: 3톤 지게차 구매(생산팀 지게차 교체) | E56: 10000 | F56: 3월 | H56: 보전팀 | I56: 기계장치 | J56: 인도1공장 | Q56: =E56 -> 10000 | AA56: =SUM(O56:Z56)-E56 -> 0
A57: UPS | B57: 기계장치 | C57: 1 | D57: 에어컨(UPS BATTERY ROOM 설치) | E57: 8000 | F57: 2월 | H57: 보전팀 | I57: 기계장치 | J57: 인도1공장 | P57: =E57 -> 8000 | AA57: =SUM(O57:Z57)-E57 -> 0
A58: 공용 | B58: 비품 | C58: 128 | D58: LED 전등 신규 설치 및 노후 제품 교체 | E58: 12000 | F58: 1~3월 | H58: 보전팀 | I58: 비품 | J58: 인도1공장 | O58: =$E58/3 -> 4000 | P58: =$E58/3 -> 4000 | Q58: =$E58/3 -> 4000 | AA58: =SUM(O58:Z58)-E58 -> 0
A59: SU2I LWB PE | B59: 전용기 | C59: 1 | D59: SU2I LWB PE 2열,3열 시트 전용라인(1 LOT) | E59: 1000000 | F59: 3월 | H59: 보전팀 | I59: 기계장치 | J59: 인도1공장 | Q59: =E59 -> 1000000 | AA59: =SUM(O59:Z59)-E59 -> 0
A60: 공용 | B60: 선풍기 | C60: 50 | D60: 라인 작업자 선풍기 구매 및 수리 | E60: 2500 | F60: 5월 | H60: 보전팀 | I60: 기계장치 | J60: 인도1공장 | S60: =E60 -> 2500 | AA60: =SUM(O60:Z60)-E60 -> 0
A61: 공용 | B61: 설비보전 | C61: 1 | D61: 퐁갈 연휴 설비 보전활동 | E61: 8000 | F61: 1월 | H61: 보전팀 | I61: 기계장치 | J61: 인도1공장 | O61: =E61 -> 8000 | AA61: =SUM(O61:Z61)-E61 -> 0
A62: 공용 | B62: 설비보전 | C62: 1 | D62: 셧다운 연휴 설비 보전활동 | E62: 15000 | F62: 5월 | H62: 보전팀 | I62: 기계장치 | J62: 인도1공장 | S62: =E62 -> 15000 | AA62: =SUM(O62:Z62)-E62 -> 0
A63: 공용 | B63: 설비보전 | C63: 1 | D63: 디왈리 연휴 설비 보전활동 | E63: 8000 | F63: 11월 | H63: 보전팀 | I63: 기계장치 | J63: 인도1공장 | Y63: =E63 -> 8000 | AA63: =SUM(O63:Z63)-E63 -> 0
A64: SU2I EV | B64: 구축물 | C64: 1 | D64: SU2I EV 버스바 전용라인 폐쇄구조물 건축(중2층) - 리프트 2대 | E64: 1500000 | F64: 5~7월 | H64: 보전팀 | I64: 구축물 | J64: 인도1공장 | S64: =$E64/3 -> 500000 | T64: =$E64/3 -> 500000 | U64: =$E64/3 -> 500000 | AA64: =SUM(O64:Z64)-E64 -> 0
A65: 공용 | B65: 설비보전 | C65: 1 | D65: 컴프레셔 소모품교체(케이져 - 1대) | E65: 8000 | F65: 10월 | H65: 보전팀 | I65: 기계장치 | J65: 인도1공장 | X65: =E65 -> 8000 | AA65: =SUM(O65:Z65)-E65 -> 0
A66: 공용 | B66: 설비보전 | C66: 8 | D66: 프레스 소모품교체(모터베어링 8대분) | E66: 8000 | F66: 10월 | H66: 보전팀 | I66: 기계장치 | J66: 인도1공장 | X66: =E66 -> 8000 | AA66: =SUM(O66:Z66)-E66 -> 0
D68: 합계 | E68: =SUM(E47:E67) -> 5804500
A72: 월별 투자비 실적
D73: 1월 | E73: 2월 | F73: 3월 | G73: 4월 | H73: 5월 | I73: 6월 | J73: 7월 | K73: 8월 | L73: 9월 | M73: 10월 | N73: 11월 | O73: 12월
B74: 금형 공정개선 관련 금형신작 및 수정 업무
B75: 밀링머신 구매
B76: 신규라인, 미설치라인 유해GAS 배출기 설치
B77: 현대로보트 수리자재 구매(CO2로보트 - 설비 오바홀)
B78: 디젤보관장 안전라이센스 등록
B79: 24년 공정개선 및 원가절감 세부 추진 계획 관련 개선 투자 비용 (공정개선, 공정용/완성품 PLT 자체제작, 안전팬스 제작,설치 및 공장개선 활동)
B80: SU2I 다단레치 - 조립 및 검사 전용기 7EA / CO2로보트 1EA
B81: SU2I 다단레치 금형(1 LOT)
B82: SU2I EV 버스바 전용라인(2.6만대 기준) - 조립 및 검사 전용기 6EA
B83: 3톤 지게차 구매(생산팀 지게차 교체)
B84: 에어컨(UPS BATTERY ROOM 설치)
B85: LED 전등 신규 설치 및 노후 제품 교체
... B93: 프레스 소모품교체(모터베어링 8대분)
B95: Repeat mold, crate, PS7I Lever spring | E95: =(1000000+186500+14000)*16/1000 -> 19208

Sheet 매출매입
A1: ○ 2024년 만누르공장 매출매입(재료비 계획대비 실적)
I2: 단위 : 백만원
A3: 구 분(차종외) | C3: 2024년 3월 계획(누계) | F3: 2024년 3월 실적(누계) | I3: 계획대비 분석
C4: 매출 | D4: 재료비계획 | E4: 비율 | F4: 매출 | G4: 재료비실적 | H4: 비율 | I4: 비율차이 | J4: 주요사유
A5: 영업 매출 | B5: AI3 | C5: =C58/1000 -> 0 | D5: =D58/1000 -> 0 | E5: =D5/C5 -> #DIV/0! | F5: =F58/1000 -> 0 | G5: =G58/1000 -> 0 | H5: =G5/F5 -> #DIV/0! | I5: =H5-E5 -> #DIV/0! | L5: =F5-C5 -> 0 | M5: =L5/C5 -> #DIV/0!
B6: AI3 MOBIS | C6: =C59/1000 -> 0 | D6: =D59/1000 -> 0 | E6: =D6/C6 -> #DIV/0! | F6: =F59/1000 -> 0 | G6: =G59/1000 -> 0 | H6: =G6/F6 -> #DIV/0! | I6: =H6-E6 -> #DIV/0! | L6: =F6-C6 -> 0 | M6: =L6/C6 -> #DIV/0! | N6: =SUM(F5:F6)-SUM(C5:C6) -> 0 | O6: =N6/(C5+C6) -> #DIV/0!
B7: BI3 | C7: =C60/1000 -> 0 | D7: =D60/1000 -> 0 | E7: =D7/C7 -> #DIV/0! | F7: =F60/1000 -> 0 | G7: =G60/1000 -> 0 | H7: =G7/F7 -> #DIV/0! | I7: =H7-E7 -> #DIV/0! | L7: =F7-C7 -> 0 | M7: =L7/C7 -> #DIV/0!
B8: BI3 MOBIS | C8: =C61/1000 -> 0 | D8: =D61/1000 -> 0 | E8: =D8/C8 -> #DIV/0! | F8: =F61/1000 -> 0 | G8: =G61/1000 -> 0 | H8: =G8/F8 -> #DIV/0! | I8: =H8-E8 -> #DIV/0! | L8: =F8-C8 -> 0 | M8: =L8/C8 -> #DIV/0! | N8: =SUM(F7:F8)-SUM(C7:C8) -> 0 | O8: =N8/(C7+C8) -> #DIV/0!
B9: BN7I | C9: =C62/1000 -> 0 | D9: =D62/1000 -> 0 | E9: =D9/C9 -> #DIV/0! | F9: =F62/1000 -> 0 | G9: =G62/1000 -> 0 | H9: =G9/F9 -> #DIV/0! | I9: =H9-E9 -> #DIV/0! | L9: =F9-C9 -> 0 | M9: =L9/C9 -> #DIV/0!
B10: BN7I MOBIS | C10: =C63/1000 -> 0 | D10: =D63/1000 -> 0 | E10: =D10/C10 -> #DIV/0! | F10: =F63/1000 -> 0 | G10: =G63/1000 -> 0 | H10: =G10/F10 -> #DIV/0! | I10: =H10-E10 -> #DIV/0! | L10: =F10-C10 -> 0 | M10: =L10/C10 -> #DIV/0! | N10: =SUM(F9:F10)-SUM(C9:C10) -> 0 | O10: =N10/(C9+C10) -> #DIV/0!
B11: QY | C11: =C64/1000 -> 0 | D11: =D64/1000 -> 0 | E11: =D11/C11 -> #DIV/0! | F11: =F64/1000 -> 0 | G11: =G64/1000 -> 0 | H11: =G11/F11 -> #DIV/0! | I11: =H11-E11 -> #DIV/0! | L11: =F11-C11 -> 0 | M11: =L11/C11 -> #DIV/0!
B12: KY | C12: =C65/1000 -> 0 | D12: =D65/1000 -> 0 | E12: =D12/C12 -> #DIV/0! | F12: =F65/1000 -> 0 | G12: =G65/1000 -> 0 | H12: =G12/F12 -> #DIV/0! | I12: =H12-E12 -> #DIV/0! | L12: =F12-C12 -> 0 | M12: =L12/C12 -> #DIV/0!
B13: L02B | C13: =C66/1000 -> 0 | D13: =D66/1000 -> 0 | E13: =D13/C13 -> #DIV/0! | F13: =F66/1000 -> 0 | G13: =G66/1000 -> 0 | H13: =G13/F13 -> #DIV/0! | I13: =H13-E13 -> #DIV/0! | L13: =F13-C13 -> 0 | M13: =L13/C13 -> #DIV/0!
B14: M2EL | C14: =C67/1000 -> 0 | D14: =D67/1000 -> 0 | E14: =D14/C14 -> #DIV/0! | F14: =F67/1000 -> 0 | G14: =G67/1000 -> 0 | H14: =G14/F14 -> #DIV/0! | I14: =H14-E14 -> #DIV/0! | L14: =F14-C14 -> 0 | M14: =L14/C14 -> #DIV/0!
B15: PS7 | C15: =C68/1000 -> 0 | D15: =D68/1000 -> 0 | E15: =D15/C15 -> #DIV/0! | F15: =F68/1000 -> 0 | G15: =G68/1000 -> 0 | H15: =G15/F15 -> #DIV/0! | I15: =H15-E15 -> #DIV/0! | L15: =F15-C15 -> 0 | M15: =L15/C15 -> #DIV/0!
B16: PS7 MOBIS | C16: =C69/1000 -> 0 | D16: =D69/1000 -> 0 | E16: =D16/C16 -> #DIV/0! | F16: =F69/1000 -> 0 | G16: =G69/1000 -> 0 | H16: =G16/F16 -> #DIV/0! | I16: =H16-E16 -> #DIV/0! | L16: =F16-C16 -> 0 | M16: =L16/C16 -> #DIV/0! | N16: =SUM(F15:F16)-SUM(C15:C16) -> 0 | O16: =N16/(C15+C16) -> #DIV/0!
B17: QXIFL | C17: =C70/1000 -> 0 | D17: =D70/1000 -> 0 | E17: =D17/C17 -> #DIV/0! | F17: =F70/1000 -> 0 | G17: =G70/1000 -> 0 | H17: =G17/F17 -> #DIV/0! | I17: =H17-E17 -> #DIV/0! | L17: =F17-C17 -> 0 | M17: =L17/C17 -> #DIV/0!
B18: QXIFL MOBIS | C18: =C71/1000 -> 0 | D18: =D71/1000 -> 0 | E18: =D18/C18 -> #DIV/0! | F18: =F71/1000 -> 0 | G18: =G71/1000 -> 0 | H18: =G18/F18 -> #DIV/0! | I18: =H18-E18 -> #DIV/0! | L18: =F18-C18 -> 0 | M18: =L18/C18 -> #DIV/0!
B19: SU2I | C19: =C72/1000 -> 0 | D19: =D72/1000 -> 0 | E19: =D19/C19 -> #DIV/0! | F19: =F72/1000 -> 0 | G19: =G72/1000 -> 0 | H19: =G19/F19 -> #DIV/0! | I19: =H19-E19 -> #DIV/0! | L19: =F19-C19 -> 0 | M19: =L19/C19 -> #DIV/0!
B20: SU2I MOBIS | C20: =C73/1000 -> 0 | D20: =D73/1000 -> 0 | E20: =D20/C20 -> #DIV/0! | F20: =F73/1000 -> 0 | G20: =G73/1000 -> 0 | H20: =G20/F20 -> #DIV/0! | I20: =H20-E20 -> #DIV/0! | L20: =F20-C20 -> 0 | M20: =L20/C20 -> #DIV/0! | N20: =SUM(F17:F20)-SUM(C17:C20) -> 0 | O20: =N20/(C17+C18+C19+C20) -> #DIV/0!
B21: SU2i & PS7I | C21: =C74/1000 -> 0 | D21: =D74/1000 -> 0 | E21: =D21/C21 -> #DIV/0! | F21: =F74/1000 -> 0 | G21: =G74/1000 -> 0 | H21: =G21/F21 -> #DIV/0! | I21: =H21-E21 -> #DIV/0! | L21: =F21-C21 -> 0 | M21: =L21/C21 -> #DIV/0!
B22: SU2ID | C22: =C75/1000 -> 0 | D22: =D75/1000 -> 0 | E22: =D22/C22 -> #DIV/0! | F22: =F75/1000 -> 0 | G22: =G75/1000 -> 0 | H22: =G22/F22 -> #DIV/0! | I22: =H22-E22 -> #DIV/0! | L22: =F22-C22 -> 0 | M22: =L22/C22 -> #DIV/0!
B23: SU2I BUSBAR | C23: =C76/1000 -> 0 | D23: =D76/1000 -> 0 | E23: =D23/C23 -> #DIV/0! | F23: =F76/1000 -> 0 | G23: =G76/1000 -> 0 | H23: =G23/F23 -> #DIV/0! | I23: =H23-E23 -> #DIV/0! | L23: =F23-C23 -> 0 | M23: =L23/C23 -> #DIV/0!
C24: =C77/1000 -> 0 | D24: =D77/1000 -> 0 | E24: =D24/C24 -> #DIV/0! | F24: =F77/1000 -> 0 | G24: =G77/1000 -> 0 | H24: =G24/F24 -> #DIV/0! | I24: =H24-E24 -> #DIV/0! | L24: =F24-C24 -> 0 | M24: =L24/C24 -> #DIV/0! | N24: =SUM(F21:F24)-SUM(C21:C24) -> 0 | O24: =N24/(C21+C22+C23+C24) -> #DIV/0!
C25: =C78/1000 -> 0 | D25: =D78/1000 -> 0 | E25: =D25/C25 -> #DIV/0! | F25: =F78/1000 -> 0 | G25: =G78/1000 -> 0 | H25: =G25/F25 -> #DIV/0! | I25: =H25-E25 -> #DIV/0! | L25: =F25-C25 -> 0 | M25: =L25/C25 -> #DIV/0!
B26: AS PART SALES/Purchase | C26: =C79/1000 -> 0 | D26: =D79/1000 -> 0 | E26: =D26/C26 -> #DIV/0! | F26: =F79/1000 -> 0 | G26: =G79/1000 -> 0 | H26: =G26/F26 -> #DIV/0! | I26: =H26-E26 -> #DIV/0! | L26: =F26-C26 -> 0 | M26: =L26/C26 -> #DIV/0!
C27: =C80/1000 -> 0 | D27: =D80/1000 -> 0 | E27: =D27/C27 -> #DIV/0! | F27: =F80/1000 -> 0 | G27: =G80/1000 -> 0 | H27: =G27/F27 -> #DIV/0! | I27: =H27-E27 -> #DIV/0! | L27: =F27-C27 -> 0 | M27: =L27/C27 -> #DIV/0!
C28: =C81/1000 -> 0 | D28: =D81/1000 -> 0 | E28: =D28/C28 -> #DIV/0! | F28: =F81/1000 -> 0 | G28: =G81/1000 -> 0 | H28: =G28/F28 -> #DIV/0! | I28: =H28-E28 -> #DIV/0! | L28: =F28-C28 -> 0 | M28: =L28/C28 -> #DIV/0!
C29: =C82/1000 -> 0 | D29: =D82/1000 -> 0 | E29: =D29/C29 -> #DIV/0! | F29: =F82/1000 -> 0 | G29: =G82/1000 -> 0 | H29: =G29/F29 -> #DIV/0! | I29: =H29-E29 -> #DIV/0! | L29: =F29-C29 -> 0 | M29: =L29/C29 -> #DIV/0!
C30: =C83/1000 -> 0 | D30: =D83/1000 -> 0 | E30: =D30/C30 -> #DIV/0! | F30: =F83/1000 -> 0 | G30: =G83/1000 -> 0 | H30: =G30/F30 -> #DIV/0! | I30: =H30-E30 -> #DIV/0! | L30: =F30-C30 -> 0 | M30: =L30/C30 -> #DIV/0!
C31: =C84/1000 -> 0 | D31: =D84/1000 -> 0 | E31: =D31/C31 -> #DIV/0! | F31: =F84/1000 -> 0 | G31: =G84/1000 -> 0 | H31: =G31/F31 -> #DIV/0! | I31: =H31-E31 -> #DIV/0! | L31: =F31-C31 -> 0 | M31: =L31/C31 -> #DIV/0!
C32: =C85/1000 -> 0 | D32: =D85/1000 -> 0 | E32: =D32/C32 -> #DIV/0! | F32: =F85/1000 -> 0 | G32: =G85/1000 -> 0 | H32: =G32/F32 -> #DIV/0! | I32: =H32-E32 -> #DIV/0! | L32: =F32-C32 -> 0 | M32: =L32/C32 -> #DIV/0!
C33: =C86/1000 -> 0 | D33: =D86/1000 -> 0 | E33: =D33/C33 -> #DIV/0! | F33: =F86/1000 -> 0 | G33: =G86/1000 -> 0 | H33: =G33/F33 -> #DIV/0! | I33: =H33-E33 -> #DIV/0! | L33: =F33-C33 -> 0 | M33: =L33/C33 -> #DIV/0!
B34: 제품재고 증감 | C34: =C87/1000 -> 0 | D34: =D87/1000 -> 0 | E34: =D34/C34 -> #DIV/0! | F34: =F87/1000 -> 0 | G34: =G87/1000 -> 0 | H34: =G34/F34 -> #DIV/0! | I34: =H34-E34 -> #DIV/0! | L34: =F34-C34 -> 0 | M34: =L34/C34 -> #DIV/0!
B35: 기타 | C35: =C88/1000 -> 0 | D35: =D88/1000 -> 0 | E35: =D35/C35 -> #DIV/0! | F35: =F88/1000 -> 0 | G35: =G88/1000 -> 0 | H35: =G35/F35 -> #DIV/0! | I35: =H35-E35 -> #DIV/0! | L35: =F35-C35 -> 0 | M35: =L35/C35 -> #DIV/0!
B36: 스크랩 | C36: =C89/1000 -> 0 | D36: =D89/1000 -> 0 | E36: =D36/C36 -> #DIV/0! | F36: =F89/1000 -> 0 | G36: =G89/1000 -> 0 | H36: =G36/F36 -> #DIV/0! | I36: =H36-E36 -> #DIV/0! | L36: =F36-C36 -> 0 | M36: =L36/C36 -> #DIV/0!
B37: 부자재(CO2 GAS,WIRE) | C37: =C90/1000 -> 0 | D37: =D90/1000 -> 0 | E37: =D37/C37 -> #DIV/0! | F37: =F90/1000 -> 0 | G37: =G90/1000 -> 0 | H37: =G37/F37 -> #DIV/0! | I37: =H37-E37 -> #DIV/0! | L37: =F37-C37 -> 0 | M37: =L37/C37 -> #DIV/0!
B38: 관세(운반비포함) | C38: =C91/1000 -> 0 | D38: =D91/1000 -> 0 | E38: =D38/C38 -> #DIV/0! | F38: =F91/1000 -> 0 | G38: =G91/1000 -> 0 | H38: =G38/F38 -> #DIV/0! | I38: =H38-E38 -> #DIV/0! | L38: =F38-C38 -> 0 | M38: =L38/C38 -> #DIV/0!
B39: CR | C39: =C92/1000 -> 0 | D39: =D92/1000 -> 0 | E39: =D39/C39 -> #DIV/0! | F39: =F92/1000 -> 0 | G39: =G92/1000 -> 0 | H39: =G39/F39 -> #DIV/0! | I39: =H39-E39 -> #DIV/0! | L39: =F39-C39 -> 0 | M39: =L39/C39 -> #DIV/0!
B40: 소 계 | C40: =SUM(C5:C39) -> 0 | D40: =SUM(D5:D39) -> 0 | E40: =D40/C40 -> #DIV/0! | F40: =SUM(F5:F39) -> 0 | G40: =SUM(G5:G39) -> 0 | H40: =G40/F40 -> #DIV/0! | I40: =H40-E40 -> #DIV/0!
A41: 기타매출 | E41: =D41/C41 -> #DIV/0! | H41: =G41/F41 -> #DIV/0! | I41: =H41-E41 -> #DIV/0!
A42: 원가절감 예상효과 | D42: =D95/1000 -> -27.91079 | J42: 계획 마이너스(-) 표시
A43: 총 합 계 | C43: =SUM(C40:C42) -> 0 | D43: =SUM(D40:D42) -> -27.91079 | E43: =D43/C43 -> #DIV/0! | F43: =SUM(F40:F42) -> 0 | G43: =SUM(G40:G42) -> 0 | H43: =G43/F43 -> #DIV/0! | I43: =H43-E43 -> #DIV/0!
C44: ='경영실적 PT'!AG7-C43 -> 26299.702 | D44: ='경영실적 PT'!AG9-D43 -> 21254.052 | F44: ='경영실적 PT'!AL7-F43 -> 17085.148 | G44: ='경영실적 PT'!AL9-G43 -> 13919.821
C45: 경영보고서 체크 | G45: 경영보고서 체크
A56: 구 분(차종외) | C56: 2024년 3월 계획(누계) | F56: 2024년 3월 실적(누계) | I56: 계획대비 분석
C57: 매출 | D57: 재료비계획 | E57: 비율 | F57: 매출 | G57: 재료비실적 | H57: 비율 | I57: 비율차이 | J57: 주요사유
A58: 영업 매출 | B58: AI3 | E58: =D58/C58 -> #DIV/0! | H58: =G58/F58 -> #DIV/0! | I58: =H58-E58 -> #DIV/0! | L58: =F58-C58 -> 0 | M58: =L58/C58 -> #DIV/0!
B59: AI3 MOBIS | E59: =D59/C59 -> #DIV/0! | H59: =G59/F59 -> #DIV/0! | I59: =H59-E59 -> #DIV/0! | L59: =F59-C59 -> 0 | M59: =L59/C59 -> #DIV/0! | N59: =SUM(F58:F59)-SUM(C58:C59) -> 0 | O59: =N59/(C58+C59) -> #DIV/0!
B60: BI3 | E60: =D60/C60 -> #DIV/0! | H60: =G60/F60 -> #DIV/0! | I60: =H60-E60 -> #DIV/0! | L60: =F60-C60 -> 0 | M60: =L60/C60 -> #DIV/0!
B61: BI3 MOBIS | E61: =D61/C61 -> #DIV/0! | H61: =G61/F61 -> #DIV/0! | I61: =H61-E61 -> #DIV/0! | L61: =F61-C61 -> 0 | M61: =L61/C61 -> #DIV/0! | N61: =SUM(F60:F61)-SUM(C60:C61) -> 0 | O61: =N61/(C60+C61) -> #DIV/0!
B62: BN7I | E62: =D62/C62 -> #DIV/0! | H62: =G62/F62 -> #DIV/0! | I62: =H62-E62 -> #DIV/0! | L62: =F62-C62 -> 0 | M62: =L62/C62 -> #DIV/0!
B63: BN7I MOBIS | E63: =D63/C63 -> #DIV/0! | H63: =G63/F63 -> #DIV/0! | I63: =H63-E63 -> #DIV/0! | L63: =F63-C63 -> 0 | M63: =L63/C63 -> #DIV/0! | N63: =SUM(F62:F63)-SUM(C62:C63) -> 0 | O63: =N63/(C62+C63) -> #DIV/0!
B64: QY | E64: =D64/C64 -> #DIV/0! | H64: =G64/F64 -> #DIV/0! | I64: =H64-E64 -> #DIV/0! | L64: =F64-C64 -> 0 | M64: =L64/C64 -> #DIV/0!
B65: KY | E65: =D65/C65 -> #DIV/0! | H65: =G65/F65 -> #DIV/0! | I65: =H65-E65 -> #DIV/0! | L65: =F65-C65 -> 0 | M65: =L65/C65 -> #DIV/0!
B66: L02B | E66: =D66/C66 -> #DIV/0! | H66: =G66/F66 -> #DIV/0! | I66: =H66-E66 -> #DIV/0! | L66: =F66-C66 -> 0 | M66: =L66/C66 -> #DIV/0!
B67: M2EL | E67: =D67/C67 -> #DIV/0! | H67: =G67/F67 -> #DIV/0! | I67: =H67-E67 -> #DIV/0! | L67: =F67-C67 -> 0 | M67: =L67/C67 -> #DIV/0!
B68: PS7 | E68: =D68/C68 -> #DIV/0! | H68: =G68/F68 -> #DIV/0! | I68: =H68-E68 -> #DIV/0! | L68: =F68-C68 -> 0 | M68: =L68/C68 -> #DIV/0!
B69: PS7 MOBIS | E69: =D69/C69 -> #DIV/0! | H69: =G69/F69 -> #DIV/0! | I69: =H69-E69 -> #DIV/0! | L69: =F69-C69 -> 0 | M69: =L69/C69 -> #DIV/0! | N69: =SUM(F68:F69)-SUM(C68:C69) -> 0 | O69: =N69/(C68+C69) -> #DIV/0!
B70: QXIFL | E70: =D70/C70 -> #DIV/0! | H70: =G70/F70 -> #DIV/0! | I70: =H70-E70 -> #DIV/0! | L70: =F70-C70 -> 0 | M70: =L70/C70 -> #DIV/0!
B71: QXIFL MOBIS | E71: =D71/C71 -> #DIV/0! | H71: =G71/F71 -> #DIV/0! | I71: =H71-E71 -> #DIV/0! | L71: =F71-C71 -> 0 | M71: =L71/C71 -> #DIV/0!
B72: SU2I | E72: =D72/C72 -> #DIV/0! | H72: =G72/F72 -> #DIV/0! | I72: =H72-E72 -> #DIV/0! | L72: =F72-C72 -> 0 | M72: =L72/C72 -> #DIV/0!
B73: SU2I MOBIS | E73: =D73/C73 -> #DIV/0! | H73: =G73/F73 -> #DIV/0! | I73: =H73-E73 -> #DIV/0! | L73: =F73-C73 -> 0 | M73: =L73/C73 -> #DIV/0! | N73: =SUM(F70:F73)-SUM(C70:C73) -> 0 | O73: =N73/(C70+C71+C72+C73) -> #DIV/0!
B74: SU2i & PS7I | E74: =D74/C74 -> #DIV/0! | H74: =G74/F74 -> #DIV/0! | I74: =H74-E74 -> #DIV/0! | L74: =F74-C74 -> 0 | M74: =L74/C74 -> #DIV/0!
B75: SU2ID | E75: =D75/C75 -> #DIV/0! | H75: =G75/F75 -> #DIV/0! | I75: =H75-E75 -> #DIV/0! | L75: =F75-C75 -> 0 | M75: =L75/C75 -> #DIV/0!
B76: SU2I BUSBAR | E76: =D76/C76 -> #DIV/0! | H76: =G76/F76 -> #DIV/0! | I76: =H76-E76 -> #DIV/0! | L76: =F76-C76 -> 0 | M76: =L76/C76 -> #DIV/0!
E77: =D77/C77 -> #DIV/0! | H77: =G77/F77 -> #DIV/0! | I77: =H77-E77 -> #DIV/0! | L77: =F77-C77 -> 0 | M77: =L77/C77 -> #DIV/0! | N77: =SUM(F74:F77)-SUM(C74:C77) -> 0 | O77: =N77/(C74+C75+C76+C77) -> #DIV/0!
E78: =D78/C78 -> #DIV/0! | H78: =G78/F78 -> #DIV/0! | I78: =H78-E78 -> #DIV/0! | L78: =F78-C78 -> 0 | M78: =L78/C78 -> #DIV/0!
B79: AS PART SALES/Purchase | E79: =D79/C79 -> #DIV/0! | H79: =G79/F79 -> #DIV/0! | I79: =H79-E79 -> #DIV/0! | L79: =F79-C79 -> 0 | M79: =L79/C79 -> #DIV/0!
E80: =D80/C80 -> #DIV/0! | H80: =G80/F80 -> #DIV/0! | I80: =H80-E80 -> #DIV/0! | L80: =F80-C80 -> 0 | M80: =L80/C80 -> #DIV/0!
E81: =D81/C81 -> #DIV/0! | H81: =G81/F81 -> #DIV/0! | I81: =H81-E81 -> #DIV/0! | L81: =F81-C81 -> 0 | M81: =L81/C81 -> #DIV/0!
E82: =D82/C82 -> #DIV/0! | H82: =G82/F82 -> #DIV/0! | I82: =H82-E82 -> #DIV/0! | L82: =F82-C82 -> 0 | M82: =L82/C82 -> #DIV/0!
E83: =D83/C83 -> #DIV/0! | H83: =G83/F83 -> #DIV/0! | I83: =H83-E83 -> #DIV/0! | L83: =F83-C83 -> 0 | M83: =L83/C83 -> #DIV/0!
E84: =D84/C84 -> #DIV/0! | H84: =G84/F84 -> #DIV/0! | I84: =H84-E84 -> #DIV/0! | L84: =F84-C84 -> 0 | M84: =L84/C84 -> #DIV/0!
E85: =D85/C85 -> #DIV/0! | H85: =G85/F85 -> #DIV/0! | I85: =H85-E85 -> #DIV/0! | L85: =F85-C85 -> 0 | M85: =L85/C85 -> #DIV/0!
E86: =D86/C86 -> #DIV/0! | H86: =G86/F86 -> #DIV/0! | I86: =H86-E86 -> #DIV/0! | L86: =F86-C86 -> 0 | M86: =L86/C86 -> #DIV/0!
B87: 제품재고 증감 | E87: =D87/C87 -> #DIV/0! | H87: =G87/F87 -> #DIV/0! | I87: =H87-E87 -> #DIV/0! | L87: =F87-C87 -> 0 | M87: =L87/C87 -> #DIV/0!
B88: 기타 | E88: =D88/C88 -> #DIV/0! | H88: =G88/F88 -> #DIV/0! | I88: =H88-E88 -> #DIV/0! | L88: =F88-C88 -> 0 | M88: =L88/C88 -> #DIV/0!
B89: 스크랩 | E89: =D89/C89 -> #DIV/0! | H89: =G89/F89 -> #DIV/0! | I89: =H89-E89 -> #DIV/0! | L89: =F89-C89 -> 0 | M89: =L89/C89 -> #DIV/0!
B90: 부자재(CO2 GAS,WIRE) | E90: =D90/C90 -> #DIV/0! | H90: =G90/F90 -> #DIV/0! | I90: =H90-E90 -> #DIV/0! | L90: =F90-C90 -> 0 | M90: =L90/C90 -> #DIV/0!
B91: 관세(운반비포함) | E91: =D91/C91 -> #DIV/0! | H91: =G91/F91 -> #DIV/0! | I91: =H91-E91 -> #DIV/0! | L91: =F91-C91 -> 0 | M91: =L91/C91 -> #DIV/0!
B92: CR | E92: =D92/C92 -> #DIV/0! | H92: =G92/F92 -> #DIV/0! | I92: =H92-E92 -> #DIV/0! | L92: =F92-C92 -> 0 | M92: =L92/C92 -> #DIV/0!
B93: 소 계 | C93: =SUM(C58:C92) -> 0 | D93: =SUM(D58:D92) -> 0 | E93: =D93/C93 -> #DIV/0! | F93: =SUM(F58:F92) -> 0 | G93: =SUM(G58:G92) -> 0 | H93: =G93/F93 -> #DIV/0! | I93: =H93-E93 -> #DIV/0!
A94: 기타매출 | E94: =D94/C94 -> #DIV/0! | H94: =G94/F94 -> #DIV/0! | I94: =H94-E94 -> #DIV/0!
A95: 원가절감 예상효과 | D95: =-SUM('월계획 '!H69:J69) -> -27910.79 | J95: 계획 마이너스(-) 표시
A96: 총 합 계 | C96: =SUM(C93:C95) -> 0 | D96: =SUM(D93:D95) -> -27910.79 | E96: =D96/C96 -> #DIV/0! | F96: =SUM(F93:F95) -> 0 | G96: =SUM(G93:G95) -> 0 | H96: =G96/F96 -> #DIV/0! | I96: =H96-E96 -> #DIV/0!

Sheet 경비
A1: ■ 경비 계정별 월별계획
A2: 1.2023년 실적 및 2024년 계획 | G2: (금액단위 : 백만원) | K2: 1000
A3: 구분 | C3: 2023년 누계실적 | E3: 2024년 누계목표 | G3: 계획대비 분석 | I3: 주요변동사유 | K3: ▶ 월별 실적
C4: 금액 | D4: % | E4: 금액 | F4: % | G4: 증가액 | H4: 증가율 | K4: 1월 | L4: 2월 | M4: 3월 | N4: 4월 | O4: 5월 | P4: 6월 | Q4: 7월 | R4: 8월 | S4: 9월 | T4: 10월 | U4: 11월 | V4: 12월
A5: 매출액 | C5: 100374.62 | D5: =C5/$C$5 -> 1 | E5: =SUM(K5:V5) -> 104614.07 | F5: =E5/$E$5 -> 1 | G5: =E5-C5 -> 4239.4486 | H5: =IFERROR(G5/C5,0) -> 0.042236259 | K5: 8200.6732 | L5: 8889.5369 | M5: 9209.4917 | N5: 8543.8371 | O5: 7186.0288 | P5: 8889.3046 | Q5: 9603.9758 | R5: 9249.3419 | S5: 8537.3465 | T5: 8894.8836 | U5: 8544.9024 | V5: 8864.7501
A6: 구분 | B6: 감가상각비 계 | C6: 3605.8125 | D6: =C6/$C$5 -> 0.035923546 | E6: =SUM(K6:V6) -> 3532.9484 | F6: =E6/$E$5 -> 0.033771254 | G6: =E6-C6 -> -72.864083 | H6: =IFERROR(G6/C6,0) -> -0.020207397 | K6: 248.19519 | L6: 247.29019 | M6: 267.54299 | N6: 257.26654 | O6: 280.1555 | P6: 280.45716 | Q6: 325.17925 | R6: 325.17925 | S6: 325.17925 | T6: 325.42058 | U6: 325.54125 | V6: 325.54125
A7: 금액순정렬 | B7: 복리후생비 | C7: 793.09034 | D7: =C7/$C$5 -> 0.0079013033 | E7: =SUM(K7:V7) -> 859.34374 | F7: =E7/$E$5 -> 0.0082144182 | G7: =E7-C7 -> 66.253401 | H7: =IFERROR(G7/C7,0) -> 0.083538277 | K7: 81.449312 | L7: 61.049312 | M7: 63.449312 | N7: 67.449312 | O7: 72.921312 | P7: 59.449312 | Q7: 61.529312 | R7: 57.849312 | S7: 57.849312 | T7: 145.44931 | U7: 67.449312 | V7: 63.449312
B8: 전력비 | C8: 656.77886 | D8: =C8/$C$5 -> 0.006543276 | E8: =SUM(K8:V8) -> 732.29851 | F8: =E8/$E$5 -> 0.007 | G8: =E8-C8 -> 75.519644 | H8: =IFERROR(G8/C8,0) -> 0.11498489 | K8: 57.404712 | L8: 62.226758 | M8: 64.466442 | N8: 59.80686 | O8: 50.302202 | P8: 62.225132 | Q8: 67.22783 | R8: 64.745393 | S8: 59.761425 | T8: 62.264185 | U8: 59.814317 | V8: 62.053251
B9: 발전기사용료 | C9: 193.65639 | D9: =C9/$C$5 -> 0.0019293361 | E9: =SUM(K9:V9) -> 209.22815 | F9: =E9/$E$5 -> 0.002 | G9: =E9-C9 -> 15.571758 | H9: =IFERROR(G9/C9,0) -> 0.080409215 | K9: 16.401346 | L9: 17.779074 | M9: 18.418983 | N9: 17.087674 | O9: 14.372058 | P9: 17.778609 | Q9: 19.207952 | R9: 18.498684 | S9: 17.074693 | T9: 17.789767 | U9: 17.089805 | V9: 17.7295
B10: 수도광열비 | C10: 37.54832 | D10: =C10/$C$5 -> 0.0003740818 | E10: =SUM(K10:V10) -> 32.8 | F10: =E10/$E$5 -> 0.00031353334 | G10: =E10-C10 -> -4.74832 | H10: =IFERROR(G10/C10,0) -> -0.12645892 | K10: 2.4 | L10: 2.4 | M10: 3.2 | N10: 3.2 | O10: 3.2 | P10: 3.2 | Q10: 3.2 | R10: 2.4 | S10: 2.4 | T10: 2.4 | U10: 2.4 | V10: 2.4
B11: 기술지원료 | C11: 1543.7159 | D11: =C11/$C$5 -> 0.015379544 | E11: =SUM(K11:V11) -> 1768.9329 | F11: =E11/$E$5 -> 0.01690913 | G11: =E11-C11 -> 225.21701 | H11: =IFERROR(G11/C11,0) -> 0.14589278 | K11: 138.65496 | L11: 150.33291 | M11: 155.75512 | N11: 144.47279 | O11: 121.46101 | P11: 150.32842 | Q11: 162.45828 | R11: 156.447 | S11: 144.36245 | T11: 150.42353 | U11: 144.49063 | V11: 149.74584
B12: 수선비 - 장비 | C12: 582.56654 | D12: =C12/$C$5 -> 0.0058039225 | E12: =SUM(K12:V12) -> 523.07036 | F12: =E12/$E$5 -> 0.005 | G12: =E12-C12 -> -59.496173 | H12: =IFERROR(G12/C12,0) -> -0.10212769 | K12: 41.003366 | L12: 44.447685 | M12: 46.047458 | N12: 42.719186 | O12: 35.930144 | P12: 44.446523 | Q12: 48.019879 | R12: 46.24671 | S12: 42.686732 | T12: 44.474418 | U12: 42.724512 | V12: 44.323751
B13: 기타수선비 - 건물등 | C13: 280.53107 | D13: =C13/$C$5 -> 0.0027948406 | E13: =SUM(K13:V13) -> 88.32 | F13: =E13/$E$5 -> 0.00084424588 | G13: =E13-C13 -> -192.21107 | H13: =IFERROR(G13/C13,0) -> -0.68516857 | K13: 7.36 | L13: 7.36 | M13: 7.36 | N13: 7.36 | O13: 7.36 | P13: 7.36 | Q13: 7.36 | R13: 7.36 | S13: 7.36 | T13: 7.36 | U13: 7.36 | V13: 7.36
B14: 운반비 | C14: 614.01721 | D14: =C14/$C$5 -> 0.0061172554 | E14: =SUM(K14:V14) -> 600.53601 | F14: =E14/$E$5 -> 0.0057404898 | G14: =E14-C14 -> -13.481196 | H14: =IFERROR(G14/C14,0) -> -0.02195573 | K14: 47.195359 | L14: 51.077039 | M14: 52.894171 | N14: 49.140696 | O14: 41.423416 | P14: 51.212261 | Q14: 55.121008 | R14: 53.178423 | S14: 49.140755 | T14: 51.14528 | U14: 49.209035 | V14: 49.798573
B15: 수출비용 | C15: 25.662406 | D15: =C15/$C$5 -> 0.00025566627 | E15: =SUM(K15:V15) -> 5.76 | F15: =E15/$E$5 -> 5.5059514e-05 | G15: =E15-C15 -> -19.902406 | H15: =IFERROR(G15/C15,0) -> -0.77554716 | K15: 0.48 | L15: 0.48 | M15: 0.48 | N15: 0.48 | O15: 0.48 | P15: 0.48 | Q15: 0.48 | R15: 0.48 | S15: 0.48 | T15: 0.48 | U15: 0.48 | V15: 0.48
B16: 소모품비 - 현장 | C16: 269.3323 | D16: =C16/$C$5 -> 0.0026832708 | E16: =SUM(K16:V16) -> 260.52873 | F16: =E16/$E$5 -> 0.0024903794 | G16: =E16-C16 -> -8.8035749 | H16: =IFERROR(G16/C16,0) -> -0.032686666 | K16: 20.423064 | L16: 22.139417 | M16: 22.936501 | N16: 21.278158 | O16: 17.89553 | P16: 22.138756 | Q16: 23.920995 | R16: 23.037427 | S16: 21.261931 | T16: 22.152744 | U16: 21.280781 | V16: 22.063422
B17: 소모품비 - 기타(사무,청소용품등) | C17: 16.766473 | D17: =C17/$C$5 -> 0.00016703896 | E17: =SUM(K17:V17) -> 15.456 | F17: =E17/$E$5 -> 0.00014774303 | G17: =E17-C17 -> -1.310473 | H17: =IFERROR(G17/C17,0) -> -0.078160324 | K17: 1.288 | L17: 1.288 | M17: 1.288 | N17: 1.288 | O17: 1.288 | P17: 1.288 | Q17: 1.288 | R17: 1.288 | S17: 1.288 | T17: 1.288 | U17: 1.288 | V17: 1.288
B18: 지급수수료 | C18: 84.184773 | D18: =C18/$C$5 -> 0.00083870573 | E18: =SUM(K18:V18) -> 100.71016 | F18: =E18/$E$5 -> 0.00096268272 | G18: =E18-C18 -> 16.525387 | H18: =IFERROR(G18/C18,0) -> 0.19629901 | K18: 5.52 | L18: 5.7552 | M18: 11.8512 | N18: 6.24136 | O18: 5.4432 | P18: 7.168 | Q18: 5.944 | R18: 5.168 | S18: 5.208 | T18: 18.3632 | U18: 5.28 | V18: 18.768
B19: 지급임차료-장비등 | C19: 4.9888 | D19: =C19/$C$5 -> 4.9701805e-05 | E19: =SUM(K19:V19) -> 5.76 | F19: =E19/$E$5 -> 5.5059514e-05 | G19: =E19-C19 -> 0.7712 | H19: =IFERROR(G19/C19,0) -> 0.15458627 | K19: 0.48 | L19: 0.48 | M19: 0.48 | N19: 0.48 | O19: 0.48 | P19: 0.48 | Q19: 0.48 | R19: 0.48 | S19: 0.48 | T19: 0.48 | U19: 0.48 | V19: 0.48
... B26: 기타비용 | C26: 0 | D26: =C26/$C$5 -> 0 | E26: =SUM(K26:V26) -> 1.92 | F26: =E26/$E$5 -> 1.8353171e-05 | G26: =E26-C26 -> 1.92 | H26: =IFERROR(G26/C26,0) -> 0 | K26: 0.16 | L26: 0.16 | M26: 0.16 | N26: 0.16 | O26: 0.16 | P26: 0.16 | Q26: 0.16 | R26: 0.16 | S26: 0.16 | T26: 0.16 | U26: 0.16 | V26: 0.16
D27: =C27/$C$5 -> 0 | E27: =SUM(K27:V27) -> 0 | F27: =E27/$E$5 -> 0 | G27: =E27-C27 -> 0 | H27: =IFERROR(G27/C27,0) -> 0
D28: =C28/$C$5 -> 0 | E28: =SUM(K28:V28) -> 0 | F28: =E28/$E$5 -> 0 | G28: =E28-C28 -> 0 | H28: =IFERROR(G28/C28,0) -> 0
D29: =C29/$C$5 -> 0 | E29: =SUM(K29:V29) -> 0 | F29: =E29/$E$5 -> 0 | G29: =E29-C29 -> 0 | H29: =IFERROR(G29/C29,0) -> 0
D30: =C30/$C$5 -> 0 | F30: =E30/$E$5 -> 0
B31: 일반경비 소계 | C31: =SUM(C7:C30) -> 5713.9729 | D31: =C31/$C$5 -> 0.056926469 | E31: =SUM(K31:V31) -> 5816.5686 | F31: =E31/$E$5 -> 0.05560025 | G31: =E31-C31 -> 102.59566 | H31: =IFERROR(G31/C31,0) -> 0.017955224 | K31: =SUM(K7:K30) -> 471.21212 | L31: =SUM(L7:L30) -> 477.9674 | M31: =SUM(M7:M30) -> 499.77919 | N31: =SUM(N7:N30) -> 472.15604 | O31: =SUM(O7:O30) -> 423.70887 | P31: =SUM(P7:P30) -> 478.70701 | Q31: =SUM(Q7:Q30) -> 507.38925 | R31: =SUM(R7:R30) -> 488.33095 | ... V31: =SUM(V7:V30) -> 491.09165
A32: 원가절감 예상효과 | D32: =C32/$C$5 -> 0 | E32: =SUM(K32:V32) -> -49.245 | F32: =E32/$E$5 -> -0.00047073017 | K32: =-'월계획 '!H72/1000 -> -0.6155625 | L32: =-'월계획 '!I72/1000 -> -1.2870852 | M32: =-'월계획 '!J72/1000 -> -1.7795352 | N32: =-'월계획 '!K72/1000 -> -2.3267019 | O32: =-'월계획 '!L72/1000 -> -2.9422644 | P32: =-'월계획 '!M72/1000 -> -3.6457644 | Q32: =-'월계획 '!N72/1000 -> -4.4665144 | R32: =-'월계획 '!O72/1000 -> -5.4514144 | ... V32: =-'월계획 '!S72/1000 -> -6.6825394
A33: 경비 합계 | C33: =C6+C31 -> 9319.7854 | D33: =C33/$C$5 -> 0.092850016 | E33: =SUM(K33:V33) -> 9300.272 | F33: =E33/$E$5 -> 0.088900774 | G33: =E33-C33 -> -19.513418 | H33: =IFERROR(G33/C33,0) -> -0.0020937626 | K33: =SUM(K6+K31+K32) -> 718.79175 | L33: =SUM(L6+L31+L32) -> 723.97051 | M33: =SUM(M6+M31+M32) -> 765.54264 | N33: =SUM(N6+N31+N32) -> 727.09587 | O33: =SUM(O6+O31+O32) -> 700.9221 | P33: =SUM(P6+P31+P32) -> 755.51841 | Q33: =SUM(Q6+Q31+Q32) -> 828.10198 | R33: =SUM(R6+R31+R32) -> 808.05878 | ... V33: =SUM(V6+V31+V32) -> 809.95036
J36: 매출비교 | K36: =K40-K37 -> 0 | L36: =L40-L37 -> 0 | M36: =M40-M37 -> 0 | N36: =N40-N37 -> 0 | O36: =O40-O37 -> 0 | P36: =P40-P37 -> 0 | Q36: =Q40-Q37 -> 0 | R36: =R40-R37 -> 0 | ... V36: =V40-V37 -> 0
A37: 2. 2024년 계획 및 실적 | G37: (금액단위 : 백만원) | J37: CHECK→ | K37: ='월계획 '!H112/1000 -> 8161.5523 | L37: ='월계획 '!I112/1000 -> 8923.5955 | M37: ='월계획 '!J112/1000 -> 0 | N37: ='월계획 '!K112/1000 -> 0 | O37: ='월계획 '!L112/1000 -> 0 | P37: ='월계획 '!M112/1000 -> 0 | Q37: ='월계획 '!N112/1000 -> 0 | R37: ='월계획 '!O112/1000 -> 0 | ... V37: ='월계획 '!S112/1000 -> 0
A38: 구분 | C38: 2024년 누계목표 | E38: 2024년 누계실적 | G38: 계획대비 분석 | I38: 주요변동사유 | K38: ▶ 월별 실적
C39: 금액 | D39: % | E39: 금액 | F39: % | G39: 증가액 | H39: 증가율 | K39: 1월 | L39: 2월 | M39: 3월 | N39: 4월 | O39: 5월 | P39: 6월 | Q39: 7월 | R39: 8월 | S39: 9월 | T39: 10월 | U39: 11월 | V39: 12월
A40: 매출액 | C40: =SUM(K5:M5) -> 26299.702 | D40: =C40/$C$40 -> 1 | E40: =SUM(K40:V40) -> 17085.148 | F40: =E40/$E$40 -> 1 | G40: =E40-C40 -> -9214.554 | H40: =IFERROR(G40/C40,0) -> -0.35036724 | K40: ='월계획 '!H112/1000 -> 8161.5523 | L40: ='월계획 '!I112/1000 -> 8923.5955 | M40: ='월계획 '!J112/1000 -> 0 | N40: ='월계획 '!K112/1000 -> 0 | O40: ='월계획 '!L112/1000 -> 0 | P40: ='월계획 '!M112/1000 -> 0 | Q40: ='월계획 '!N112/1000 -> 0 | R40: ='월계획 '!O112/1000 -> 0 | ... V40: ='월계획 '!S112/1000 -> 0
A41: 구분 | B41: 감가상각비 계 | C41: =SUM(K6:M6) -> 763.02838 | D41: =C41/$C$40 -> 0.029012815 | E41: =SUM(K41:V41) -> 477.01773 | F41: =E41/$E$40 -> 0.027920023 | G41: =E41-C41 -> -286.01065 | H41: =IFERROR(G41/C41,0) -> -0.37483619 | K41: =IS!E220/1000 -> 238.50886 | L41: =IS!F220/1000 -> 238.50886 | M41: =IS!G220/1000 -> 0 | N41: =IS!H220/1000 -> 0 | O41: =IS!I220/1000 -> 0 | P41: =IS!J220/1000 -> 0 | Q41: =IS!K220/1000 -> 0 | R41: =IS!L220/1000 -> 0 | ... V41: =IS!P220/1000 -> 0
A42: 금액순정렬 | B42: 복리후생비 | C42: =SUM(K7:M7) -> 205.94794 | D42: =C42/$C$40 -> 0.0078308088 | E42: =SUM(K42:V42) -> 102.76455 | F42: =E42/$E$40 -> 0.0060148472 | G42: =E42-C42 -> -103.18338 | H42: =IFERROR(G42/C42,0) -> -0.50101683 | I42: • 체육대회 연기 (우천) 16백만, 항공료 일정변경 8백만, 식대 12백만 ↓ | K42: =IS!E200/1000 -> 51.187306 | L42: =IS!F200/1000 -> 51.577247 | M42: =IS!G200/1000 -> 0 | N42: =IS!H200/1000 -> 0 | O42: =IS!I200/1000 -> 0 | P42: =IS!J200/1000 -> 0 | Q42: =IS!K200/1000 -> 0 | R42: =IS!L200/1000 -> 0 | ... V42: =IS!P200/1000 -> 0
B43: 전력비 | C43: =SUM(K8:M8) -> 184.09791 | D43: =C43/$C$40 -> 0.007 | E43: =SUM(K43:V43) -> 111.7799 | F43: =E43/$E$40 -> 0.006542519 | G43: =E43-C43 -> -72.318009 | H43: =IFERROR(G43/C43,0) -> -0.39282362 | K43: =IS!E201/1000 -> 57.614752 | L43: =IS!F201/1000 -> 54.165152 | M43: =IS!G201/1000 -> 0 | N43: =IS!H201/1000 -> 0 | O43: =IS!I201/1000 -> 0 | P43: =IS!J201/1000 -> 0 | Q43: =IS!K201/1000 -> 0 | R43: =IS!L201/1000 -> 0 | ... V43: =IS!P201/1000 -> 0
B44: 발전기사용료 | C44: =SUM(K9:M9) -> 52.599404 | D44: =C44/$C$40 -> 0.002 | E44: =SUM(K44:V44) -> 20.3328 | F44: =E44/$E$40 -> 0.0011900863 | G44: =E44-C44 -> -32.266604 | H44: =IFERROR(G44/C44,0) -> -0.61344048 | I44: • 단전 감소 | K44: =IS!E202/1000 -> 10.1664 | L44: =IS!F202/1000 -> 10.1664 | M44: =IS!G202/1000 -> 0 | N44: =IS!H202/1000 -> 0 | O44: =IS!I202/1000 -> 0 | P44: =IS!J202/1000 -> 0 | Q44: =IS!K202/1000 -> 0 | R44: =IS!L202/1000 -> 0 | ... V44: =IS!P202/1000 -> 0
B45: 수도광열비 | C45: =SUM(K10:M10) -> 8 | D45: =C45/$C$40 -> 0.00030418596 | E45: =SUM(K45:V45) -> 5.784736 | F45: =E45/$E$40 -> 0.00033858273 | G45: =E45-C45 -> -2.215264 | H45: =IFERROR(G45/C45,0) -> -0.276908 | K45: =IS!E203/1000 -> 2.780832 | L45: =IS!F203/1000 -> 3.003904 | M45: =IS!G203/1000 -> 0 | N45: =IS!H203/1000 -> 0 | O45: =IS!I203/1000 -> 0 | P45: =IS!J203/1000 -> 0 | Q45: =IS!K203/1000 -> 0 | R45: =IS!L203/1000 -> 0 | ... V45: =IS!P203/1000 -> 0
B46: 기술지원료 | C46: =SUM(K11:M11) -> 444.743 | D46: =C46/$C$40 -> 0.016910572 | E46: =SUM(K46:V46) -> 269.15461 | F46: =E46/$E$40 -> 0.015753718 | G46: =E46-C46 -> -175.58839 | H46: =IFERROR(G46/C46,0) -> -0.39480866 | I46: • 매출증가에 따른 로열티 감소 | K46: =IS!E204/1000 -> 127.78624 | L46: =IS!F204/1000 -> 141.36837 | M46: =IS!G204/1000 -> 0 | N46: =IS!H204/1000 -> 0 | O46: =IS!I204/1000 -> 0 | P46: =IS!J204/1000 -> 0 | Q46: =IS!K204/1000 -> 0 | R46: =IS!L204/1000 -> 0 | ... V46: =IS!P204/1000 -> 0
B47: 수선비 - 장비 | C47: =SUM(K12:M12) -> 131.49851 | D47: =C47/$C$40 -> 0.005 | E47: =SUM(K47:V47) -> 89.601553 | F47: =E47/$E$40 -> 0.0052444119 | G47: =E47-C47 -> -41.896956 | H47: =IFERROR(G47/C47,0) -> -0.31861164 | I47: • 팔레트수선 7백만, 레이저센서교체 4백만 | K47: =IS!E205/1000 -> 34.704807 | L47: =IS!F205/1000 -> 54.896746 | M47: =IS!G205/1000 -> 0 | N47: =IS!H205/1000 -> 0 | O47: =IS!I205/1000 -> 0 | P47: =IS!J205/1000 -> 0 | Q47: =IS!K205/1000 -> 0 | R47: =IS!L205/1000 -> 0 | ... V47: =IS!P205/1000 -> 0
B48: 기타수선비 - 건물등 | C48: =SUM(K13:M13) -> 22.08 | D48: =C48/$C$40 -> 0.00083955325 | E48: =SUM(K48:V48) -> 48.16044 | F48: =E48/$E$40 -> 0.0028188483 | G48: =E48-C48 -> 26.08044 | H48: =IFERROR(G48/C48,0) -> 1.1811794 | I48: • KM 공사(캐노피,정화조) 10백만, 지붕보수 9백만, 도색 5백만, 기타(도로,수도,식당) 7백만 | K48: =IS!E206/1000 -> 25.341112 | L48: =IS!F206/1000 -> 22.819328 | M48: =IS!G206/1000 -> 0 | N48: =IS!H206/1000 -> 0 | O48: =IS!I206/1000 -> 0 | P48: =IS!J206/1000 -> 0 | Q48: =IS!K206/1000 -> 0 | R48: =IS!L206/1000 -> 0 | ... V48: =IS!P206/1000 -> 0
B49: 운반비 | C49: =SUM(K14:M14) -> 151.16657 | D49: =C49/$C$40 -> 0.0057478434 | E49: =SUM(K49:V49) -> 94.064351 | F49: =E49/$E$40 -> 0.0055056212 | G49: =E49-C49 -> -57.102217 | H49: =IFERROR(G49/C49,0) -> -0.37774369 | K49: =IS!E207/1000 -> 44.857943 | L49: =IS!F207/1000 -> 49.206408 | M49: =IS!G207/1000 -> 0 | N49: =IS!H207/1000 -> 0 | O49: =IS!I207/1000 -> 0 | P49: =IS!J207/1000 -> 0 | Q49: =IS!K207/1000 -> 0 | R49: =IS!L207/1000 -> 0 | ... V49: =IS!P207/1000 -> 0
B50: 수출비용 | C50: =SUM(K15:M15) -> 1.44 | D50: =C50/$C$40 -> 5.4753473e-05 | E50: =SUM(K50:V50) -> 2.078624 | F50: =E50/$E$40 -> 0.00012166263 | G50: =E50-C50 -> 0.638624 | H50: =IFERROR(G50/C50,0) -> 0.44348889 | K50: =IS!E208/1000 -> 1.997904 | L50: =IS!F208/1000 -> 0.08072 | M50: =IS!G208/1000 -> 0 | N50: =IS!H208/1000 -> 0 | O50: =IS!I208/1000 -> 0 | P50: =IS!J208/1000 -> 0 | Q50: =IS!K208/1000 -> 0 | R50: =IS!L208/1000 -> 0 | ... V50: =IS!P208/1000 -> 0
B51: 소모품비 - 현장 | C51: =SUM(K16:M16) -> 65.498983 | D51: =C51/$C$40 -> 0.0024904839 | E51: =SUM(K51:V51) -> 37.6166 | F51: =E51/$E$40 -> 0.0022017135 | G51: =E51-C51 -> -27.882383 | H51: =IFERROR(G51/C51,0) -> -0.42569185 | K51: =IS!E209/1000 -> 21.832008 | L51: =IS!F209/1000 -> 15.784592 | M51: =IS!G209/1000 -> 0 | N51: =IS!H209/1000 -> 0 | O51: =IS!I209/1000 -> 0 | P51: =IS!J209/1000 -> 0 | Q51: =IS!K209/1000 -> 0 | R51: =IS!L209/1000 -> 0 | ... V51: =IS!P209/1000 -> 0
B52: 소모품비 - 기타(사무,청소용품등) | C52: =SUM(K17:M17) -> 3.864 | D52: =C52/$C$40 -> 0.00014692182 | E52: =SUM(K52:V52) -> 2.117636 | F52: =E52/$E$40 -> 0.00012394602 | G52: =E52-C52 -> -1.746364 | H52: =IFERROR(G52/C52,0) -> -0.45195756 | K52: =IS!E210/1000 -> 1.002552 | L52: =IS!F210/1000 -> 1.115084 | M52: =IS!G210/1000 -> 0 | N52: =IS!H210/1000 -> 0 | O52: =IS!I210/1000 -> 0 | P52: =IS!J210/1000 -> 0 | Q52: =IS!K210/1000 -> 0 | R52: =IS!L210/1000 -> 0 | ... V52: =IS!P210/1000 -> 0
B53: 지급수수료 | C53: =SUM(K18:M18) -> 23.1264 | D53: =C53/$C$40 -> 0.00087934077 | E53: =SUM(K53:V53) -> 15.245715 | F53: =E53/$E$40 -> 0.0008923373 | G53: =E53-C53 -> -7.8806854 | H53: =IFERROR(G53/C53,0) -> -0.34076577 | I53: • CMM 머신 검교정 3백만, HMI 협력사 회비 1백만 | K53: =IS!E211/1000 -> 10.385381 | L53: =IS!F211/1000 -> 4.8603336 | M53: =IS!G211/1000 -> 0 | N53: =IS!H211/1000 -> 0 | O53: =IS!I211/1000 -> 0 | P53: =IS!J211/1000 -> 0 | Q53: =IS!K211/1000 -> 0 | R53: =IS!L211/1000 -> 0 | ... V53: =IS!P211/1000 -> 0
B54: 지급임차료-장비등 | C54: =SUM(K19:M19) -> 1.44 | D54: =C54/$C$40 -> 5.4753473e-05 | E54: =SUM(K54:V54) -> 0 | F54: =E54/$E$40 -> 0 | G54: =E54-C54 -> -1.44 | H54: =IFERROR(G54/C54,0) -> -1 | K54: =IS!E212/1000 -> 0 | L54: =IS!F212/1000 -> 0 | M54: =IS!G212/1000 -> 0 | N54: =IS!H212/1000 -> 0 | O54: =IS!I212/1000 -> 0 | P54: =IS!J212/1000 -> 0 | Q54: =IS!K212/1000 -> 0 | R54: =IS!L212/1000 -> 0 | ... V54: =IS!P212/1000 -> 0
B55: 지급임차료-부동산 | C55: =SUM(K20:M20) -> 11.136 | D55: =C55/$C$40 -> 0.00042342685 | E55: =SUM(K55:V55) -> 8.297856 | F55: =E55/$E$40 -> 0.00048567657 | G55: =E55-C55 -> -2.838144 | H55: =IFERROR(G55/C55,0) -> -0.25486207 | K55: =IS!E213/1000 -> 4.379936 | L55: =IS!F213/1000 -> 3.91792 | M55: =IS!G213/1000 -> 0 | N55: =IS!H213/1000 -> 0 | O55: =IS!I213/1000 -> 0 | P55: =IS!J213/1000 -> 0 | Q55: =IS!K213/1000 -> 0 | R55: =IS!L213/1000 -> 0 | ... V55: =IS!P213/1000 -> 0
B56: 여비교통비 | C56: =SUM(K21:M21) -> 110.4 | D56: =C56/$C$40 -> 0.0041977662 | E56: =SUM(K56:V56) -> 76.26794 | F56: =E56/$E$40 -> 0.0044639906 | G56: =E56-C56 -> -34.13206 | H56: =IFERROR(G56/C56,0) -> -0.30916721 | I56: • 푸네출장 항공료 ↑(자재, 공무, 회계) | K56: =IS!E214/1000 -> 36.911443 | L56: =IS!F214/1000 -> 39.356497 | M56: =IS!G214/1000 -> 0 | N56: =IS!H214/1000 -> 0 | O56: =IS!I214/1000 -> 0 | P56: =IS!J214/1000 -> 0 | Q56: =IS!K214/1000 -> 0 | R56: =IS!L214/1000 -> 0 | ... V56: =IS!P214/1000 -> 0
B57: 접대비 | C57: =SUM(K22:M22) -> 2.64 | D57: =C57/$C$40 -> 0.00010038137 | E57: =SUM(K57:V57) -> 1.932096 | F57: =E57/$E$40 -> 0.00011308629 | G57: =E57-C57 -> -0.707904 | H57: =IFERROR(G57/C57,0) -> -0.26814545 | K57: =IS!E215/1000 -> 0 | L57: =IS!F215/1000 -> 1.932096 | M57: =IS!G215/1000 -> 0 | N57: =IS!H215/1000 -> 0 | O57: =IS!I215/1000 -> 0 | P57: =IS!J215/1000 -> 0 | Q57: =IS!K215/1000 -> 0 | R57: =IS!L215/1000 -> 0 | ... V57: =IS!P215/1000 -> 0
B58: 통신비 | C58: =SUM(K23:M23) -> 3.36 | D58: =C58/$C$40 -> 0.0001277581 | E58: =SUM(K58:V58) -> 1.4074822 | F58: =E58/$E$40 -> 8.2380455e-05 | G58: =E58-C58 -> -1.9525178 | H58: =IFERROR(G58/C58,0) -> -0.58110648 | K58: =IS!E216/1000 -> 0.383408 | L58: =IS!F216/1000 -> 1.0240742 | M58: =IS!G216/1000 -> 0 | N58: =IS!H216/1000 -> 0 | O58: =IS!I216/1000 -> 0 | P58: =IS!J216/1000 -> 0 | Q58: =IS!K216/1000 -> 0 | R58: =IS!L216/1000 -> 0 | ... V58: =IS!P216/1000 -> 0
B59: 보험료 | C59: =SUM(K24:M24) -> 24 | D59: =C59/$C$40 -> 0.00091255788 | E59: =SUM(K59:V59) -> 34.080267 | F59: =E59/$E$40 -> 0.0019947306 | G59: =E59-C59 -> 10.080267 | H59: =IFERROR(G59/C59,0) -> 0.42001114 | I59: • 선급보험료 인식 | K59: =IS!E217/1000 -> 34.080267 | L59: =IS!F217/1000 -> 0 | M59: =IS!G217/1000 -> 0 | N59: =IS!H217/1000 -> 0 | O59: =IS!I217/1000 -> 0 | P59: =IS!J217/1000 -> 0 | Q59: =IS!K217/1000 -> 0 | R59: =IS!L217/1000 -> 0 | ... V59: =IS!P217/1000 -> 0
B60: 차량유지비 | C60: =SUM(K25:M25) -> 1.44 | D60: =C60/$C$40 -> 5.4753473e-05 | E60: =SUM(K60:V60) -> 4.994672 | F60: =E60/$E$40 -> 0.00029233999 | G60: =E60-C60 -> 3.554672 | H60: =IFERROR(G60/C60,0) -> 2.4685222 | I60: • 침수차량 수선비 | K60: =IS!E218/1000 -> 0.627744 | L60: =IS!F218/1000 -> 4.366928 | M60: =IS!G218/1000 -> 0 | N60: =IS!H218/1000 -> 0 | O60: =IS!I218/1000 -> 0 | P60: =IS!J218/1000 -> 0 | Q60: =IS!K218/1000 -> 0 | R60: =IS!L218/1000 -> 0 | ... V60: =IS!P218/1000 -> 0
B61: 기타비용 | C61: =SUM(K26:M26) -> 0.48 | D61: =C61/$C$40 -> 1.8251158e-05 | E61: =SUM(K61:V61) -> 0 | F61: =E61/$E$40 -> 0 | G61: =E61-C61 -> -0.48 | H61: =IFERROR(G61/C61,0) -> -1 | K61: =IS!E219/1000 -> 0 | L61: =IS!F219/1000 -> 0 | M61: =IS!G219/1000 -> 0 | N61: =IS!H219/1000 -> 0 | O61: =IS!I219/1000 -> 0 | P61: =IS!J219/1000 -> 0 | Q61: =IS!K219/1000 -> 0 | R61: =IS!L219/1000 -> 0 | ... V61: =IS!P219/1000 -> 0
C62: =SUM(K27:M27) -> 0 | D62: =C62/$C$40 -> 0 | E62: =SUM(K62:V62) -> 0 | F62: =E62/$E$40 -> 0 | G62: =E62-C62 -> 0 | H62: =IFERROR(G62/C62,0) -> 0
C63: =SUM(K28:M28) -> 0 | D63: =C63/$C$40 -> 0 | E63: =SUM(K63:V63) -> 0 | F63: =E63/$E$40 -> 0 | G63: =E63-C63 -> 0 | H63: =IFERROR(G63/C63,0) -> 0
C64: =SUM(K29:M29) -> 0 | D64: =C64/$C$40 -> 0 | E64: =SUM(K64:V64) -> 0 | F64: =E64/$E$40 -> 0 | G64: =E64-C64 -> 0 | H64: =IFERROR(G64/C64,0) -> 0
C65: =SUM(K30:M30) -> 0 | F65: =E65/$E$40 -> 0 | G65: =E65-C65 -> 0 | H65: =IFERROR(G65/C65,0) -> 0
B66: 일반경비 소계 | C66: =SUM(K31:M31) -> 1448.9587 | D66: =C66/$C$40 -> 0.055094112 | E66: =SUM(K66:V66) -> 925.68183 | F66: =E66/$E$40 -> 0.054180499 | G66: =E66-C66 -> -523.27687 | H66: =IFERROR(G66/C66,0) -> -0.36113995 | K66: =SUM(K42:K65) -> 466.04003 | L66: =SUM(L42:L65) -> 459.6418 | M66: =SUM(M42:M65) -> 0 | N66: =SUM(N42:N65) -> 0 | O66: =SUM(O42:O65) -> 0 | P66: =SUM(P42:P65) -> 0 | Q66: =SUM(Q42:Q65) -> 0 | R66: =SUM(R42:R65) -> 0 | ... V66: =SUM(V42:V65) -> 0
A67: 원가절감 예상효과 | C67: =SUM(K32:M32) -> -3.682183 | D67: =C67/$C$40 -> -0.00014000854
A68: 경비 합계 | C68: =SUM(K33:M33) -> 2208.3049 | D68: =C68/$C$40 -> 0.083966918 | E68: =SUM(K68:V68) -> 1402.6996 | F68: =E68/$E$40 -> 0.082100523 | G68: =E68-C68 -> -805.60534 | H68: =IFERROR(G68/C68,0) -> -0.36480712 | K68: =K41+K66 -> 704.5489 | L68: =L41+L66 -> 698.15066 | M68: =M41+M66 -> 0 | N68: =N41+N66 -> 0 | O68: =O41+O66 -> 0 | P68: =P41+P66 -> 0 | Q68: =Q41+Q66 -> 0 | R68: =R41+R66 -> 0 | ... V68: =V41+V66 -> 0
C69: ='경영실적 PT'!AG13 -> 2208.3049 | E69: ='경영실적 PT'!AL13 -> 1402.6996 | J69: CHECK→ | K69: ='월계획 '!H124/1000 -> 704.5489 | L69: ='월계획 '!I124/1000 -> 698.15066 | M69: ='월계획 '!J124/1000 -> 0 | N69: ='월계획 '!K124/1000 -> 0 | O69: ='월계획 '!L122/1000 -> 0 | P69: ='월계획 '!M122/1000 -> 0 | Q69: ='월계획 '!N122/1000 -> 0 | R69: ='월계획 '!O122/1000 -> 0 | S69: ='월계획 '!P122/1000 -> 0 | T69: ='월계획 '!Q122/1000 -> 0 | U69: ='월계획 '!R122/1000 -> 0 | V69: ='월계획 '!S122/1000 -> 0
J70: 경비 비교 | K70: =K68-K69 -> 0 | L70: =L68-L69 -> 0 | M70: =M68-M69 -> 0 | N70: =N68-N69 -> 0 | O70: =O68-O69 -> 0 | P70: =P68-P69 -> 0 | Q70: =Q68-Q69 -> 0 | R70: =R68-R69 -> 0 | ... V70: =V68-V69 -> 0

Sheet 성과지표▶

Sheet 보고서_제조_SAP미적용
A1: ○ 성과지표 실적보고
F2: ▽ 월지표 링크 | I2: ▽ 월지표 링크 | L2: ▽ 평가수식 임의변경 금지(오류 있으면 경영관리팀 문의) | W2: 월 | Y2: 누계
A3: 관리부문 | B3: 성과지표 | C3: 배점 | D3: 단위 | E3: 2024년 목표 | F3: 당월 성과지표 실적 | I3: 누계 성과지표 실적 | L3: 누계 실적평가 | N3: 미달성 사유 | O3: 달성/평가 | P3: 평가범위 | U3: 그래프 data
F4: 목표 | G4: 실적 | H4: 달성율 | I4: 목표 | J4: 실적 | K4: 달성율 | L4: 평가율 | M4: 평가점수 | O4: 수식표현 | P4: 최소범위 | Q4: 최대범위 | U4: 항목 | V4: 연간목표 | W4: 계획 | X4: 실적 | Y4: 계획 | Z4: 실적
A5: 경영관리 | B5: 매출액 | D5: 백만원 | E5: =(월지표!C55)/1000 -> 104614.07 | F5: =(월지표!D55)/1000 -> 9209.4917 | G5: =(월지표!D20)/1000 -> 0 | H5: =IF(G5<0,0%,G5/F5) -> 0 | I5: =(월지표!F55)/1000 -> 26299.702 | J5: =(월지표!F20)/1000 -> 17085.148 | K5: =IF(J5<0,0%,IF(O5="반대",I5/J5,J5/I5)) -> 0.64963276 | O5: 정상 | U5: 매출액
B6: 경상이익 | C6: 6 | D6: 백만원 | E6: =(월지표!C56)/1000 -> 5611.7573 | F6: =(월지표!D56)/1000 -> 599.79088 | G6: =(월지표!D21)/1000 -> 0 | H6: =IF(G6<0,0%,G6/F6) -> 0 | I6: =(월지표!F56)/1000 -> 1639.6469 | J6: =(월지표!F21)/1000 -> 946.95985 | K6: =IF(J6<0,0%,IF(O6="반대",I6/J6,J6/I6)) -> 0.57753887 | L6: =IF(J6<0,0,IF(K6<P6,0%,IF(K6>Q6,100%,(K6-P6)/(Q6-P6)))) -> 0.57753887 | M6: =C6*L6 -> 3.4652332 | O6: 정상 | P6: 0 | Q6: 1 | R6: 적자는 0점 | U6: 경상이익
B7: 적정재고 | C7: 8 | D7: 회전율/백만원 | E7: =(월지표!C55/월지표!C57)/10000 -> 2980.0104 | F7: =(월지표!D57)/1000 -> 0 | G7: =(월지표!D22)/1000 -> 3187.8842 | H7: =IF(G7<=0,100%,F7/G7) -> 0 | I7: =(월지표!F57)/1000 -> 1622.2776 | J7: =(월지표!F22)/1000 -> 3192.385 | K7: =IF(J7<0,0%,IF(O7="반대",I7/J7,J7/I7)) -> 0.50817102 | L7: =IF(K7<P7,0%,IF(K7>Q7,100%,(K7-P7)/(Q7-P7))) -> 0 | M7: =C7*L7 -> 0 | O7: 반대 | P7: 0.8 | Q7: 1 | R7: ▷년 매출계획/목표 재고회전수 | U7: 적정재고
B8: 인당매출 | D8: 백만원 | E8: =월지표!C58/1000 -> 179.64638 | F8: =월지표!D58/1000 -> 16.016507 | G8: =월지표!D23/1000 -> #DIV/0! | H8: =IF(G8<0,0%,G8/F8) -> #DIV/0! | I8: =월지표!F58/1000 -> 45.606419 | J8: =월지표!F23/1000 -> 30.78405 | K8: =IF(J8<0,0%,IF(O8="반대",I8/J8,J8/I8)) -> 0.6749938 | O8: 정상
A9: 표준관리 | B9: 재료비율 | C9: 8 | D9: 백만원 | E9: =월지표!C59 -> 0 | F9: =(월지표!D59)/1000 -> 0 | G9: =(월지표!D24)/1000 -> 0 | H9: =IF((F9-G9)>0,1-(F9-G9)/F9,1+(F9-G9)/F9) -> #DIV/0! | I9: =(월지표!$F$5)/1000 -> 13388.862 | J9: =(월지표!$F$6)/1000 -> 13919.821 | K9: =IF(J9<0,0%,IF(O9="반대",I9/J9,J9/I9)) -> 1.0396568 | L9: =IF(K9<P9,0%,IF(K9>Q9,0%,IF(K9<1,1-(1-K9)/(1-P9),1-(K9-1)/(1-P9)))) -> 0 | M9: =C9*L9 -> 0 | O9: 일치성 | P9: 0.98 | Q9: 1.02 | R9: 100%+/-2% | U9: 재료비율
A10: 인력관리 | B10: 직접인원 | D10: 명 | E10: =월지표!C60 -> 467.25 | F10: =월지표!D60 -> 461 | G10: =월지표!D25 -> 0 | H10: =IF(G10<=0,100%,F10/G10) -> 1 | I10: =월지표!F60 -> 462.66667 | J10: =월지표!F25 -> 436 | K10: =IF(J10<0,0%,IF(O10="반대",I10/J10,J10/I10)) -> 1.0611621 | O10: 반대 | U10: 직접인원 차이 | X10: =G10-F10 -> -461 | Z10: =J10-I10 -> -26.666667
B11: 간접인원 | C11: 9 | D11: 명 | E11: =월지표!C61 -> 93 | F11: =월지표!D61 -> 93 | G11: =월지표!D26 -> 0 | H11: =IF(G11<=0,100%,F11/G11) -> 1 | I11: =월지표!F61 -> 93 | J11: =월지표!F26 -> 98 | K11: =IF(J11<0,0%,IF(O11="반대",I11/J11,J11/I11)) -> 0.94897959 | L11: =IF(K11<P11,0%,IF(K11>Q11,100%,(K11-P11)/(Q11-P11))) -> 0.74489796 | M11: =C11*L11 -> 6.7040816 | O11: 반대 | P11: 0.8 | Q11: 1 | U11: 간접인원 차이 | X11: =G11-F11 -> -93 | Z11: =J11-I11 -> 5
B12: 간접제외원 | D12: 명 | E12: =월지표!C62 -> 21 | F12: =월지표!D62 -> 21 | G12: =월지표!D27 -> 0 | H12: =IF(G12<=0,100%,F12/G12) -> 1 | I12: =월지표!F62 -> 21 | J12: =월지표!F27 -> 21 | K12: =IF(J12<0,0%,IF(O12="반대",I12/J12,J12/I12)) -> 1 | O12: 반대 | U12: 간접제외원
B13: 간접비율 | D13: 명 | E13: =월지표!C63*100 -> 19.903692 | F13: =월지표!D63*100 -> 20.173536 | G13: =월지표!D28*100 -> #DIV/0! | H13: =IF(G13<=0,100%,F13/G13) -> #DIV/0! | I13: =월지표!F63*100 -> 20.100865 | J13: =월지표!F28*100 -> 22.477064 | K13: =IF(J13<0,0%,IF(O13="반대",I13/J13,J13/I13)) -> 0.89428336 | O13: 반대 | U13: 간접비율
B14: 인원합계 | D14: 명 | E14: =월지표!C64 -> 582.33333 | F14: =월지표!D64 -> 575 | G14: =월지표!D29 -> 0 | H14: =IF(G14<=0,100%,F14/G14) -> 1 | I14: =월지표!F64 -> 576.66667 | J14: =월지표!F29 -> 555 | K14: =IF(J14<0,0%,IF(O14="반대",I14/J14,J14/I14)) -> 1.039039 | O14: 반대 | U14: 인원합계 차이 | X14: =G14-F14 -> -575 | Z14: =J14-I14 -> -21.666667
A15: 생산관리 | B15: 생산효율 | C15: 9 | D15: % | E15: =월지표!C65*100 -> 100 | F15: =월지표!D65*100 -> 100 | G15: =월지표!D30*100 -> #DIV/0! | H15: =IF(G15<0,0%,G15/F15) -> #DIV/0! | I15: =월지표!F65*100 -> 100 | J15: =월지표!F30*100 -> #DIV/0! | K15: =IF(J15<0,0%,IF(O15="반대",I15/J15,J15/I15)) -> #DIV/0! | L15: =IF(K15<P15,0%,IF(K15>Q15,100%,(K15-P15)/(Q15-P15))) -> #DIV/0! | M15: =C15*L15 -> #DIV/0! | O15: 정상 | P15: 0.9 | Q15: 1 | U15: 생산효율 | V15: =E15*0.01 -> 1 | W15: =F15*0.01 -> 1 | X15: =G15*0.01 -> #DIV/0! | Y15: =I15*0.01 -> 1 | Z15: =J15*0.01 -> #DIV/0!
B16: 공정개선 | D16: HR | E16: =월지표!C66 -> 89123.296 | F16: =월지표!D66 -> 7426.9413 | G16: =월지표!D31 -> 0 | H16: =IF(G16<0,0%,G16/F16) -> 0 | I16: =월지표!F66 -> 22280.824 | J16: =월지표!F31 -> 0 | K16: =IF(J16<0,0%,IF(O16="반대",I16/J16,J16/I16)) -> 0 | L16: =IF(K16<P16,0%,IF(K16>Q16,100%,(K16-P16)/(Q16-P16))) -> 0 | O16: 정상 | P16: 0 | Q16: 0.1
B17: 설비가동율 | D17: % | E17: =월지표!C67*100 -> 90 | F17: =월지표!D67*100 -> 90 | G17: =월지표!D32 -> 0 | H17: =IF(G17<0,0%,G17/F17) -> 0 | I17: =월지표!F67*100 -> 90 | J17: =월지표!F32 -> 0 | K17: =IF(J17<0,0%,IF(O17="반대",I17/J17,J17/I17)) -> 0 | O17: 정상 | P17: 0 | Q17: 0.9
A18: 예산관리 | B18: 일반경비율 | C18: 7 | D18: % | E18: =월지표!C68*100 -> 5.512952 | F18: =월지표!D68*100 -> 5.4074608 | G18: =월지표!D33*100 -> #DIV/0! | H18: =IF(G18<=0,100%,F18/G18) -> #DIV/0! | I18: =월지표!F68*100 -> 5.4954103 | J18: =월지표!F33*100 -> 5.4180499 | K18: =IF(J18<0,0%,IF(O18="반대",I18/J18,J18/I18)) -> 1.0142783 | L18: =IF(K18<P18,0%,IF(K18>Q18,100%,(K18-P18)/(Q18-P18))) -> 1 | M18: =C18*L18 -> 7 | O18: 반대 | P18: 0.9 | Q18: 1 | U18: 일반경비율
A19: 품질관리 | B19: 고객불량율 | C19: 4 | D19: PPM | E19: =월지표!C77 -> 0 | F19: =월지표!D77 -> 16.124793 | G19: =월지표!D42 -> 22.257154 | H19: =IF(G19<=0,100%,F19/G19) -> 0.72447687 | I19: =월지표!F77 -> 16.124793 | J19: =월지표!F42 -> 29.416911 | K19: =IF(J19<0,0%,IF(O19="반대",I19/J19,J19/I19)) -> 0.54814704 | L19: =IF(J19>P19,0%,IF(J19<Q19,100%,(P19-J19)/(P19-Q19))) -> 0.85291544 | M19: =C19*L19 -> 3.4116618 | O19: 반대 | P19: 200 | Q19: 0 | R19: 고객 평가목표 변경 | U19: 고객불량율 | V19: =E19 -> 0 | W19: =F19 -> 16.124793 | X19: =G19 -> 22.257154 | Y19: =I19 -> 16.124793 | Z19: =J19 -> 29.416911
B20: 공정불량율 | C20: 4 | D20: PPM | E20: =월지표!C78 -> 50 | F20: =월지표!D78 -> 50 | G20: =월지표!D43 -> 140.76445 | H20: =IF(G20<=0,100%,F20/G20) -> 0.35520331 | I20: =월지표!F78 -> 50 | J20: =월지표!F43 -> 128.85912 | K20: =IF(J20<0,0%,IF(O20="반대",I20/J20,J20/I20)) -> 0.38802066 | L20: =IF(J20>P20,0%,IF(J20<Q20,100%,(P20-J20)/(P20-Q20))) -> 0.47427255 | M20: =C20*L20 -> 1.8970902 | O20: 반대 | P20: 200 | Q20: 50 | U20: 공정불량율 | V20: =E20 -> 50 | W20: =F20 -> 50 | X20: =G20 -> 140.76445 | Y20: =I20 -> 50 | Z20: =J20 -> 128.85912
B21: 입고불량율 | D21: PPM | E21: =월지표!C79 -> 50 | F21: =월지표!D79 -> 50 | G21: =월지표!D44 -> 282.31428 | H21: =IFERROR(IF(G21<=0,100%,F21/G21),0) -> 0.17710759 | I21: =월지표!F79 -> 50 | J21: =월지표!F44 -> 253.56273 | K21: =IF(J21<0,0%,IF(O21="반대",I21/J21,J21/I21)) -> 0.19718986 | O21: 반대 | P21: 200 | Q21: 50
B22: 고객클레임 | C22: 6 | D22: 백만원 | E22: =(월지표!C80+월지표!C81)/1000 -> 10.461407 | F22: =(월지표!D80+월지표!D81)/1000 -> 0.92094917 | G22: =(월지표!D45+월지표!D46)/1000 -> 1.881 | H22: =IF(G22<=0,100%,F22/G22) -> 0.48960615 | I22: =(월지표!F80+월지표!F81)/1000 -> 2.6299702 | J22: =(월지표!F45+월지표!F46)/1000 -> 5.791 | K22: =IFERROR(IF(J22<0,0%,IF(O22="반대",I22/J22,J22/I22)),100%) -> 0.45414785 | L22: =IF(K22<P22,0%,IF(K22>Q22,100%,(K22-P22)/(Q22-P22))) -> 0 | M22: =C22*L22 -> 0 | O22: 반대 | P22: 0.5 | Q22: 1 | R22: 고객클레임 & 고객불량율 상관관계 | U22: 고객클레임 | V22: =E22 -> 10.461407 | W22: =F22 -> 0.92094917 | X22: =G22 -> 1.881 | Y22: =I22 -> 2.6299702 | Z22: =J22 -> 5.791
B23: 폐기비용 | C23: 5 | D23: 백만원 | E23: =(월지표!C82)/1000 -> 0 | F23: =(월지표!D82)/1000 -> 0 | G23: =(월지표!D47)/1000 -> 0 | H23: =IF(G23<=0,100%,F23/G23) -> 1 | I23: =(월지표!F82)/1000 -> 0 | J23: =(월지표!F47)/1000 -> 0 | K23: =IFERROR(IF(J23<0,0%,IF(O23="반대",I23/J23,J23/I23)),100%) -> 1 | L23: =IF(K23<P23,0%,IF(K23>Q23,100%,(K23-P23)/(Q23-P23))) -> 1 | M23: =C23*L23 -> 5 | O23: 반대 | P23: 1 | Q23: 1 | U23: 폐기원가
A24: 원가개선 | B24: 원가절감 | C24: 20 | D24: 백만원 | E24: =(월지표!C83)/1000 -> 1569.2111 | F24: =(월지표!D83)/1000 -> 156.92111 | G24: =(월지표!D48)/1000 -> 0 | H24: =IFERROR(IF(G24<0,0%,G24/F24),"") -> 0 | I24: =(월지표!F83)/1000 -> 941.52665 | J24: =(월지표!F48)/1000 -> 347.545 | K24: =IF(J24<0,0%,IF(O24="반대",I24/J24,J24/I24)) -> 0.36912922 | L24: =IF(K24<P24,0%,IF(K24>Q24,100%,(K24-P24)/(Q24-P24))) -> 0.36912922 | M24: =C24*L24 -> 7.3825844 | O24: 정상 | P24: 0 | Q24: 1 | U24: 원가절감
B25: 조기달성 | C25: 5 | D25: 백만원 | E25: =E24 -> 1569.2111 | F25: =월지표!D83/1000 -> 156.92111 | G25: =월지표!D48/1000 -> 0 | H25: =IF(G25<0,0%,G25/F25) -> 0 | I25: =월지표!F83/1000 -> 941.52665 | J25: =월지표!F48/1000 -> 347.545 | K25: =IF(J25<0,0%,IF(O25="반대",I25/J25,J25/I25)) -> 0.36912922 | L25: =IF(K25<P25,0%,IF(K25>Q25,100%,(K25-P25)/(Q25-P25))) -> 0 | M25: =C25*L25 -> 0 | O25: 정상 | P25: 1 | Q25: 1
B26: 개선제안 | C26: 2 | D26: 건 | E26: =월지표!C84 -> 558 | F26: =월지표!D84 -> 46.5 | G26: =월지표!D49 -> 178 | H26: =IF(G26<0,0%,G26/F26) -> 3.827957 | I26: =월지표!F84 -> 232.5 | J26: =월지표!F49 -> 322 | K26: =IF(J26<0,0%,IF(O26="반대",I26/J26,J26/I26)) -> 1.3849462 | L26: =IF(K26<P26,0%,IF(K26>Q26,100%,(K26-P26)/(Q26-P26))) -> 1 | M26: =C26*L26 -> 2 | O26: 정상 | P26: 0 | Q26: 1 | U26: 개선제안
A27: 사업실적 | B27: 적기보고 | C27: 7 | D27: 일 | E27: 15 | F27: 15 | G27: =월지표!D50 -> 15 | H27: =IF(G27>=19,0%,IF(G27="",0%,IF(1-(G27-F27)/F27>100%,100%,1-(G27-F27)/F27))) -> 1 | I27: 15 | J27: =월지표!F50 -> 15 | K27: =IF(J27>=19,0%,IF(J27="",0%,IF(1-(J27-I27)/I27>100%,100%,1-(J27-I27)/I27))) -> 1 | L27: =K27 -> 1 | M27: =C27*L27 -> 7 | O27: 정상 | P27: 15 | Q27: 18 | U27: 적기보고
B28: 신차평가 | D28: 점 | P28: 0 | Q28: 1 | R28: 신차개발 보고회 점수 반영 | U28: 사업구조
A29: 합 계 | C29: =SUM(C5:C28) -> 100 | F29: =C29 -> 100 | G29: =M29 -> #DIV/0! | I29: =C29 -> 100 | J29: =M29 -> #DIV/0! | M29: =SUM(M5:M28) -> #DIV/0! | P29: ※SAP 사업장 16~23행 숨기기 취소 | U29: 성과지표 점수 | V29: 100 | W29: 100 | X29: =M29 -> #DIV/0! | Y29: 100 | Z29: =M29 -> #DIV/0!

Sheet 성과지표 분석 PT 1
B1: ○ 2025년 만누르 실적분석
B3: 구 분 | D3: 계획 및 실적 | F3: 실적 세부내용 | K3: 미달성 원인분석 및 개선계획
F4: 구 분 | H4: 당 월 | I4: 누 계
B6: 생산 효율 | F6: 표준시간 | H6: =생산효율!L6 -> 0 | I6: =생산효율!V6 -> 294837.12 | K6: • 원인분석: - 연휴 이후 고정인원 이탈 및 지각증가로 인한 생산성 저하 • 개선계획: - 연휴 마지막날 생산계획 수립 및 출근률 확인 및 대책 수립을 통한 연휴 이후 인원결근 예방
F7: 투입시간 | H7: =생산효율!L8 -> 0 | I7: =생산효율!V8 -> 326345.19
F8: 인정비가동 | H8: =생산효율!L21 -> 0 | I8: =생산효율!V21 -> 15958.449
F9: 개선비가동 | H9: =생산효율!L39 -> 0 | I9: =생산효율!V39 -> 8176.14
B11: 적정 재고 | F11: 매출액 | H11: ='경영실적 PT'!W7 -> 0 | I11: ='경영실적 PT'!AL7 -> 17085.148 | K11: 구 분 | M11: 당월 표준재고 | O11: 당월 현재고 | Q11: 차이
F12: 제(상)품 재고 | H12: =H13+H14 -> 0 | M12: 폼목수 | N12: 금액 | O12: 폼목수 | P12: 금액 | Q12: 폼목수 | R12: 금액
F13: ① 위탁재고 | K13: 제(상)품 | Q13: =N13-P13 -> 0 | R13: =N13-P13 -> 0
F14: ② 사내재고 | H14: =P13 -> 0 | K14: 재공품 | Q14: =N14-P14 -> 0 | R14: =N14-P14 -> 0
F15: 재공품 재고 | K15: 원재료 | L15: KD | Q15: =N15-P15 -> 0 | R15: =N15-P15 -> 0
F16: 원재료 재고 | H16: =P15+P16 -> 0 | L16: LP | Q16: =N16-P16 -> 0 | R16: =N16-P16 -> 0
F17: 합 계 | H17: =H12+H15+H16 -> 0 | K17: 계 | M17: {=SUn(N13:N16)} -> #NAME? | N17: {=SUn(N13:N16)} -> #NAME? | O17: {=SUn(P13:P16)} -> #NAME? | P17: {=SUn(P13:P16)} -> #NAME? | Q17: {=SUn(Q13:Q16)} -> #NAME? | R17: {=SUn(R13:R16)} -> #NAME?
F18: 재고율 (매출對) | H18: =H17/H11 -> #DIV/0! | K18: 원인분석 | M18: ○ ○ ○
I21: =H17-'재무상태표(BS)'!I28/1000000 -> -3187.8842
B22: 구 분 | D22: 계획 및 실적 | F22: 실적 세부내용 | K22: 미달성 원인분석 및 개선계획
F23: 구 분 | H23: 당 월 | I23: 누 계
B25: 항공 물류 | F25: 발생 금액 | G25: 고객 귀책 | H25: =항공물류!H4 -> 0 | I25: =항공물류!P4 -> 0
G26: 법인 귀책 | H26: =항공물류!H5 -> 0 | I26: =항공물류!P5 -> 0
G27: 계 | H27: {=SUn(H25:H26)} -> #NAME? | I27: {=SUn(I25:I26)} -> #NAME?
F28: 회수금액 | H28: =항공물류!H11 -> 0 | I28: =항공물류!P11 -> 0
F29: 미회수금액 | H29: =H25-H28 -> 0 | I29: =I25-I28 -> 0
B31: 불용 재고 | F31: 차종단산 | H31: =불용재고!H8 -> 0 | I31: =불용재고!P8 -> 0
F32: Hp변경 | H32: =불용재고!H13 -> 0 | I32: =불용재고!P13 -> 0
F33: 발주오류 | H33: =불용재고!H18 -> 0 | I33: =불용재고!P18 -> 0
F34: 사양삭제 | H34: =불용재고!H23 -> 0 | I34: =불용재고!P23 -> 0
B36: 실패 비용 | F36: 실패 비용 | G36: 3자검사 | K36: 1. 용접 불량 공정개선 (티징, HAS, 등 작업조건 수시점검) 2. 지그 클램프 점검 및 작동상태 점검 3. 신규 작업자 투입시 교육 및 라인리더 참관 점검
G37: 리워크 비용
G38: 폐기비용 | H38: ='클레임&폐기비'!F20 -> 3.653 | I38: ='클레임&폐기비'!O20 -> 17.489
G39: 계 | H39: =H36+H37+H38 -> 3.653 | I39: =I36+I37+I38 -> 17.489
B43: 구 분 | D43: 계획 및 실적 | F43: 실적 세부내용 | K43: 미달성 원인분석 및 개선계획
F44: 구 분 | H44: 당 월 | I44: 누 계
B46: 고객 불량율 | F46: 납품수량(HA) | H46: =불량율!H12 -> 313736 | I46: =불량율!Q12 -> 1419438 | K46: 1. 기초 품질 문제 관리 └ 라인 리더 및 작업자 자발적 문제 참여 유도 └ 일일 품질 미팅 활동 강화 2..야간조 관리 강화 └ 야간조 품질 엔지니어급 상주 예정 └ 생산팀 야간조 인계 교육 방법 강화 ▶ 누락방지 센서추가로 누락방지 ▶ pdi 검사강화로 고객 불량 감소
F47: 불량수량(HA) | H47: =불량율!H13 -> 7 | I47: =불량율!Q13 -> 39
F48: 고객불량(PPn) | H48: =불량율!H14 -> 22.311753 | I48: =불량율!Q14 -> 27.475663
B50: 공정 불량율 | F50: 생산수량(HA) | H50: =불량율!H15 -> 3362136 | I50: 19575566 | K50: 1) ALL HRT & RR BAdK -WHLD SHARP HDHH & WHLD BURR – (QTY : 100+ HA)_ In hpusH 1) linH audit 및 Qd공정점검 (1회/주) 2) 클램프 및 지그BLpdK 점검 (pHd) 3)로봇 프로그램, 팁 점검, 노즐 청소등 점검
F51: 불량 수량 (HA) | G51: 리워크 수량 | H51: =불량율!H16 -> 459 | I51: =불량율!Q18 -> 1615
G52: 폐기 수량 | H52: 0 | I52: =불량율!Q17 -> 0
G53: 계 | H53: =불량율!H18 -> 459 | I53: =I51+I52 -> 1615
F54: 공정불량(PPn) | H54: =불량율!H19 -> 136.52035 | I54: =불량율!Q19 -> 131.29612
B56: 고객 클레임 (필드+고객) | F56: 필드클레임 | H56: ='클레임&폐기비'!F4 -> 0 | I56: ='클레임&폐기비'!P4 -> 0 | K56: 1. 고객사 클래임 : PS7i 양산 초기 롯뜨 문제 발생 └ 대책 완료 및 개선품 투입 완료 ( 문제 발생시 즉각 고객 대응) 2. 협력사 품질 확동 강화 └ 품질 비용 발생 관련 협력사 활동 여부에 따라 가감 프로세스 정립 예정 ▶ 재발방지위해 발생건별 교육 실시 ▶ 고질 문제 개선 클래임 감소
F57: 고객클레임 | H57: ='클레임&폐기비'!F6 -> 1.807 | I57: ='클레임&폐기비'!O6 -> 7.598
F58: 이의제기 (확정액)
F59: 협력사클레임 | H59: ='클레임&폐기비'!F10 -> 2.249 | I59: ='클레임&폐기비'!O10 -> 9.66

Sheet 성과지표 분석 PT 2
B1: ○ 2024년 만누르 실적분석
B3: 구 분 | D3: 계획 및 실적 | F3: 미달성 원인분석 및 개선계획
B5: 원 가 절 감 | F5: 1. 개발, 자재, 영업 2. 기술, 공무 - 결제 진행 중 150 백만원 3. 경영지원 - 고객사 선수금 수취 후 차입금 상환에 따른 이자비용 220 백만 (진행 중)
B7: 성 과 지 표 점 수 | F7: 1. 적정 재고 유지를 통한 목표 달성 2. 생산성 달성 (1) 고정인원 이탈 방지 (인원 안정화) (2) 신규 직원 교육체계 확립 3. 원가절감 조기 달성
B11: 구 분 | D11: 계획 및 실적 | F11: 미달성 원인분석 및 개선계획
B13: 종 합 인 원 | F13: ○ 계획 578명 (3.8%), 실적 553명 (3.8%) └ 직접직 0.0% ↑, 간접직 0.0%
B15: 직접직 인 원 | F15: ○ 계획 467명 (2.5%), 실적 446명 (2.5%) └ 추가 연장근무 (휴일 특근) ↑
B17: 간접직 인 원 | F17: ○ 간접직 총원 : 97명 ○ 제외인원 : 21명 (상주원 13명, 경비/청소 8명) ○ 간접직 인원 : 118명
B19: ※ 제외인원 : 고객사 노무비 회수 가능인원 限
B20: ※ 간접직 인원 : 경비, 청소, 기타 인원 포함

Sheet 월지표
A1: 1. 특별항목 월지표실적 누적관리 | E1: ▽ 컬러별 범위 확인 | F1: 기간수정 | G1: (금액단위:천원) | I1: 엑셀 자료는 금액단위 천원, PT 보고서는 금액단위 백만원 | U1: 2개년도 관리
A2: 관리부문 | B2: 성과지표 | E2: 누적 집계방법 | F2: 월누계 | G2: 매출, 이익지표 : 1월~12월 | I2: 당해 1월 | J2: 당해 2월 | K2: 당해 3월 | L2: 당해 4월 | M2: 당해 5월 | N2: 당해 6월 | O2: 당해 7월 | P2: 당해 8월 | Q2: 당해 9월 | R2: 당해 10월 | S2: 23년 11월 | T2: 23년 12월 | U2: 당해 1월 | V2: 당해 2월 | W2: 당해 3월 | X2: 당해 4월 | Y2: 당해 5월 | Z2: 당해 6월 | AA2: 당해 7월 | AB2: 당해 8월 | AC2: 당해 9월 | AD2: 당해 10월 | AE2: 24년 11월 | AF2: 24년 12월 | AG2: 비 고
G3: 22년 11월 | H3: 22년 12월 | S3: 타 지표 : 전년11월~당해10월 | AE3: 타 지표 : 전년11월~당해10월
A4: ▶ 1. 표준재료비율 보고 _ 표준재료비 분석보고서 금액 누적관리 | G4: 월별 관리
B5: 월표준재료비 | E5: 당해 1월부터 합산 | F5: =SUM($U5:W5) -> 13388862 | G5: 5289611.6 | H5: 5412336.6 | I5: 5083629.7 | J5: 5886481.9 | K5: 6525851.1 | L5: 6432337.7 | M5: 5286854.4 | N5: 6929326.6 | O5: 7128318.8 | P5: 7146329.8 | Q5: 7286711.3 | R5: 7514841 | S5: 7019551.7 | T5: 7002821.8 | U5: 6495587.6 | V5: 6893274.2
B6: 월실적재료비 | E6: 당해 1월부터 합산 | F6: =SUM($U6:W6) -> 13919821 | G6: 5494038.5 | H6: 5945696.1 | I6: 5114493.7 | J6: 6011002.4 | K6: 6528654.9 | L6: 6617032.8 | M6: 5514531.4 | N6: 7028115.9 | O6: 7099188.4 | P6: 7205634.2 | Q6: 7474254.8 | R6: 7608794.9 | S6: 7176665.6 | T6: 7952447.2 | U6: ='월계획 '!H118 -> 6756010.2 | V6: ='월계획 '!I118 -> 7163810.9 | W6: ='월계획 '!J118 -> 0 | X6: ='월계획 '!K118 -> 0 | Y6: ='월계획 '!L118 -> 0 | Z6: ='월계획 '!M118 -> 0 | AA6: ='월계획 '!N118 -> 0 | AB6: ='월계획 '!O118 -> 0 | ... AF6: ='월계획 '!S118 -> 0
A7: ▶ 2. 일반경비율 보고 _ 경영실적보고서 금액 누적관리 | G7: 월별 관리 | I7: 월별 관리 | U7: 월별 관리
B8: 일반경비예산 | C8: =SUM($I8:T8) -> 4951101.2 | E8: 당해 1월부터 합산 | F8: =SUM($U8:W8) -> 1445276.5 | G8: 340575.06 | H8: 408270 | I8: 416634.28 | J8: 388237.47 | K8: 446689.02 | L8: 403630.12 | M8: 350210.77 | N8: 411731.06 | O8: 419588.3 | P8: 421381.4 | Q8: 393563.83 | R8: 450877.21 | S8: 426024.22 | T8: 422533.49 | U8: ='월계획 '!H94 -> 470596.56 | V8: ='월계획 '!I94 -> 476680.31 | W8: ='월계획 '!J94 -> 497999.65 | X8: ='월계획 '!K94 -> 469829.34 | Y8: ='월계획 '!L94 -> 420766.6 | Z8: ='월계획 '!M94 -> 475061.25 | AA8: ='월계획 '!N94 -> 502922.74 | AB8: ='월계획 '!O94 -> 482879.54 | ... AF8: ='월계획 '!S94 -> 484409.11
B9: 계획경비율 | C9: =C8/C55 -> 0.047327296 | E9: 누적비율 | F9: =F8/F55 -> 0.054954103 | G9: 0.072956257 | H9: 0.080949371 | I9: 0.079066807 | J9: 0.064615529 | K9: 0.061152305 | L9: 0.062522023 | M9: 0.070547585 | N9: 0.061291208 | O9: 0.062302606 | P9: 0.065261868 | Q9: 0.058361691 | R9: 0.078526468 | S9: 0.063210788 | T9: 0.060458753 | U9: =U8/U55 -> 0.057385113 | V9: =V8/V55 -> 0.053622626 | W9: =W8/W55 -> 0.054074608 | X9: =X8/X55 -> 0.054990437 | Y9: =Y8/Y55 -> 0.058553426 | Z9: =Z8/Z55 -> 0.053441891 | AA9: =AA8/AA55 -> 0.052366098 | AB9: =AB8/AB55 -> 0.052206908 | ... AF9: =AF8/AF55 -> 0.054644418
B10: 일반경비실적 | E10: 당해 1월부터 합산 | F10: =SUM($U10:W10) -> 925681.83 | G10: 446005.07 | H10: 699179.39 | I10: 437474.95 | J10: 493886.5 | K10: 594834.79 | L10: 463296.17 | M10: 358957.81 | N10: 393086.61 | O10: 446635.84 | P10: 462168.5 | Q10: 468711.8 | R10: 519334.51 | S10: 537197.05 | T10: 538388.4 | U10: ='월계획 '!H126 -> 466040.03 | V10: ='월계획 '!I126 -> 459641.8 | W10: ='월계획 '!J126 -> 0 | X10: ='월계획 '!K126 -> 0 | Y10: ='월계획 '!L126 -> 0 | Z10: ='월계획 '!M126 -> 0 | AA10: ='월계획 '!N126 -> 0 | AB10: ='월계획 '!O126 -> 0 | ... AF10: ='월계획 '!S126 -> 0
B11: 실적경비율 | E11: 누적비율 | F11: =F10/F20 -> 0.054180499 | G11: 0.065315397 | H11: 0.094963934 | I11: 0.066807248 | J11: 0.066619971 | K11: 0.061327915 | L11: 0.056375727 | M11: 0.052955563 | N11: 0.051788974 | O11: 0.054167403 | P11: 0.049943226 | Q11: 0.051089486 | R11: 0.057145275 | S11: 0.060331222 | T11: 0.056905189 | U11: =U10/U20 -> 0.057101887 | V11: =V10/V20 -> 0.051508587 | W11: =W10/W20 -> #DIV/0! | X11: =X10/X20 -> #DIV/0! | Y11: =Y10/Y20 -> #DIV/0! | Z11: =Z10/Z20 -> #DIV/0! | AA11: =AA10/AA20 -> #DIV/0! | AB11: =AB10/AB20 -> #DIV/0! | ... AF11: =AF10/AF20 -> #DIV/0!
A12: ▶ 3. 폐기금액(불량, 스크랩) _ 구분 보고(원가, 중량, 판매가) | G12: 월별 관리 | I12: 월별 관리 | U12: 월별 관리
B13: 폐기원가(천원) | E13: 당해 1월부터 합산 | F13: =SUM($U13:W13) -> 0
B14: 매각(판매)량(Kg) | E14: 당해 1월부터 합산 | F14: =SUM($U14:W14) -> 0
B15: 매각금액(천원) | E15: 당해 1월부터 합산 | F15: =SUM($U15:W15) -> 0
A17: 2. 월별 성과지표 실적 | D17: 기간수정, 링크 | E17: ▽ 컬러별 범위 확인 | F17: 기간수정
A18: 관리부문 | B18: 성과지표 | D18: 당월(해당월) | E18: 누적 집계방법 | F18: 월누계 | G18: 매출, 이익지표 : 1월~12월 | I18: 당해 1월 | J18: 당해 2월 | K18: 당해 3월 | L18: 당해 4월 | M18: 당해 5월 | N18: 당해 6월 | O18: 당해 7월 | P18: 당해 8월 | Q18: 당해 9월 | R18: 당해 10월 | S18: 23년 11월 | T18: 23년 12월 | U18: 당해 1월 | V18: 당해 2월 | W18: 당해 3월 | X18: 당해 4월 | Y18: 당해 5월 | Z18: 당해 6월 | AA18: 당해 7월 | AB18: 당해 8월 | AC18: 당해 9월 | AD18: 당해 10월 | AE18: 24년 11월 | AF18: 24년 12월 | AG18: 비 고
G19: 22년 11월 | H19: 22년 12월 | S19: 타 지표 : 전년11월~당해10월 | AE19: 타 지표 : 전년11월~당해10월
A20: 경영관리 | B20: 매출액 | D20: =W20 -> 0 | E20: 당해 1월부터 합산 | F20: =SUM(U20:W20) -> 17085148 | G20: 6828482.8 | H20: 7362578.2 | I20: 6548315.7 | J20: 7413490.3 | K20: 9699250.2 | L20: 8218007.9 | M20: 6778472.2 | N20: 7590160.3 | O20: 8245472.7 | P20: 9253877.5 | Q20: 9174329.9 | R20: 9087969.5 | S20: 8904130.1 | T20: 9461147.8 | U20: ='월계획 '!H112 -> 8161552.3 | V20: ='월계획 '!I112 -> 8923595.5 | W20: ='월계획 '!J112 -> 0 | X20: ='월계획 '!K112 -> 0 | Y20: ='월계획 '!L112 -> 0 | Z20: ='월계획 '!M112 -> 0 | AA20: ='월계획 '!N112 -> 0 | AB20: ='월계획 '!O112 -> 0 | ... AF20: ='월계획 '!S112 -> 0 | AG20: 월별 실적 | AH20: 경영실적
B21: 경상이익 | D21: =W21 -> 0 | E21: 당해 1월부터 합산 | F21: =SUM(U21:W21) -> 946959.85 | G21: 68507.506 | H21: -624264.82 | I21: 44236.931 | J21: -143426.94 | K21: 1601341.8 | L21: 453014.04 | M21: 312301.55 | N21: -506241.2 | O21: -162045.35 | P21: 888282.81 | Q21: 474246.95 | R21: 281327.02 | S21: 321368.3 | T21: 57321.016 | U21: ='월계획 '!H139 -> 311460.03 | V21: ='월계획 '!I139 -> 635499.82 | W21: ='월계획 '!J139 -> 0 | X21: ='월계획 '!K139 -> 0 | Y21: ='월계획 '!L139 -> 0 | Z21: ='월계획 '!M139 -> 0 | AA21: ='월계획 '!N139 -> 0 | AB21: ='월계획 '!O139 -> 0 | ... AF21: ='월계획 '!S139 -> 0 | AG21: 월별 실적 | AH21: 경영실적
B22: 적정재고 | D22: =W22 -> 3187884.2 | E22: 당해 1월부터 평균 | F22: =AVERAGE(U22:W22) -> 3192385 | G22: 2622652 | H22: 2622652 | I22: 2800011.9 | J22: 3184005.4 | K22: 2739895.7 | L22: 3177664.2 | M22: 3863260.8 | N22: 3930551.9 | O22: 3546065.7 | P22: 3600736.1 | Q22: 3983941.8 | R22: 3634341.8 | S22: 3480993.7 | T22: 3224321.7 | U22: 3201386.6 | V22: 3187884.2 | W22: ='재무상태표(BS)'!I28/1000 -> 3187884.2 | AG22: 월말 재고 | AH22: 경영실적
B23: 인당매출 | D23: =W23 -> #DIV/0! | E23: 수식 | F23: =F20/F29 -> 30784.05 | G23: 12787.421 | H23: 14158.804 | I23: 12194.256 | J23: 13405.95 | K23: 16608.305 | L23: 13696.68 | M23: 11788.647 | N23: 12504.383 | O23: 13788.416 | P23: 15982.517 | Q23: 15629.182 | R23: 15534.991 | S23: 15731.679 | T23: 16397.137 | U23: =U20/U29 -> 14652.697 | V23: =V20/V29 -> 16136.701 | W23: =W20/W29 -> #DIV/0! | X23: =X20/X29 -> #DIV/0! | Y23: =Y20/Y29 -> #DIV/0! | Z23: =Z20/Z29 -> #DIV/0! | AA23: =AA20/AA29 -> #DIV/0! | AB23: =AB20/AB29 -> #DIV/0! | ... AF23: =AF20/AF29 -> #DIV/0! | AG23: 수식 확인
A24: 표준관리 | B24: 재료비율 | D24: =W24 -> 0 | E24: 고정 링크 | F24: =F6 -> 13919821 | G24: 5494038.5 | H24: 5945696.1 | I24: 5114493.7 | J24: 6011002.4 | K24: 6528654.9 | L24: 6617032.8 | M24: 5514531.4 | N24: 7028115.9 | O24: 7099188.4 | P24: 7205634.2 | Q24: 7474254.8 | R24: 7608794.9 | S24: 7176665.6 | T24: 7952447.2 | U24: =U6 -> 6756010.2 | V24: =V6 -> 7163810.9 | W24: =W6 -> 0 | X24: =X6 -> 0 | Y24: =Y6 -> 0 | Z24: =Z6 -> 0 | AA24: =AA6 -> 0 | AB24: =AB6 -> 0 | ... AF24: =AF6 -> 0 | AG24: 링크 확인
A25: 인력관리 | B25: 직접인원 | D25: =W25 -> 0 | E25: 당해 1월부터 평균 | F25: =AVERAGE(U25:W25) -> 436 | G25: 416 | H25: 401 | I25: 409 | J25: 426 | K25: 440 | L25: 475 | M25: 453 | N25: 485 | O25: 479 | P25: 469 | Q25: 476 | R25: 471 | S25: 452 | T25: 458 | U25: 439 | V25: 433 | AG25: 월별 실적 | AH25: 인원실적
B26: 간접인원 | D26: =W26 -> 0 | E26: 당해 1월부터 평균 | F26: =AVERAGE(U26:W26) -> 98 | G26: 96 | H26: 96 | I26: 105 | J26: 104 | K26: 120 | L26: 102 | M26: 101 | N26: 101 | O26: 98 | P26: 89 | Q26: 90 | R26: 93 | S26: 93 | T26: 98 | U26: =118-21 -> 97 | V26: =120-21 -> 99 | AG26: 월별 실적 | AH26: 인원실적
B27: 간접제외원 | D27: =W27 -> 0 | E27: 당해 1월부터 평균 | F27: =AVERAGE(U27:W27) -> 21 | G27: 22 | H27: 23 | I27: 23 | J27: 23 | K27: 24 | L27: 23 | M27: 21 | N27: 21 | O27: 21 | P27: 21 | Q27: 21 | R27: 21 | S27: 21 | T27: 21 | U27: 21 | V27: 21 | AG27: 월별 실적 | AH27: ◀ 제외 인정인원 구분
B28: 간접비율 | D28: =W28 -> #DIV/0! | E28: 수식 | F28: =F26/F25 -> 0.22477064 | G28: 0.23076923 | H28: 0.2394015 | I28: 0.25672372 | J28: 0.24413146 | K28: 0.27272727 | L28: 0.21473684 | M28: 0.22295806 | N28: 0.20824742 | O28: 0.2045929 | P28: 0.18976546 | Q28: 0.18907563 | R28: 0.19745223 | S28: 0.20575221 | T28: 0.2139738 | U28: =U26/U25 -> 0.22095672 | V28: =V26/V25 -> 0.22863741 | W28: =W26/W25 -> #DIV/0! | X28: =X26/X25 -> #DIV/0! | Y28: =Y26/Y25 -> #DIV/0! | Z28: =Z26/Z25 -> #DIV/0! | AA28: =AA26/AA25 -> #DIV/0! | AB28: =AB26/AB25 -> #DIV/0! | ... AF28: =AF26/AF25 -> #DIV/0! | AG28: 수식 확인
B29: 인원합계 | D29: =W29 -> 0 | E29: 수식 | F29: =F25+F26+F27 -> 555 | G29: 534 | H29: 520 | I29: 537 | J29: 553 | K29: 584 | L29: 600 | M29: 575 | N29: 607 | O29: 598 | P29: 579 | Q29: 587 | R29: 585 | S29: 566 | T29: 577 | U29: =U25+U26+U27 -> 557 | V29: =V25+V26+V27 -> 553 | W29: =W25+W26+W27 -> 0 | X29: =X25+X26+X27 -> 0 | Y29: =Y25+Y26+Y27 -> 0 | Z29: =Z25+Z26+Z27 -> 0 | AA29: =AA25+AA26+AA27 -> 0 | AB29: =AB25+AB26+AB27 -> 0 | ... AF29: =AF25+AF26+AF27 -> 0 | AG29: 수식 확인
A30: 생산관리 | B30: 생산효율 | D30: =W30 -> #DIV/0! | E30: 당해 1월부터 평균 | F30: =AVERAGE(U30:W30) -> #DIV/0! | G30: 0.96150711 | H30: 0.97430838 | I30: 0.96355811 | J30: 0.97340309 | K30: 0.9585304 | L30: 0.91528753 | M30: 0.95913571 | N30: 0.93526904 | O30: 0.96060099 | P30: 0.97456735 | Q30: 0.95693698 | R30: 0.96772039 | S30: 0.9728905 | T30: 0.91657403 | U30: =생산효율!J43 -> 0.94852745 | V30: =생산효율!K43 -> 0.96353905 | W30: =생산효율!L43 -> #DIV/0! | X30: =생산효율!M43 -> #DIV/0! | Y30: =생산효율!N43 -> #DIV/0! | Z30: =생산효율!O43 -> #DIV/0! | AA30: =생산효율!P43 -> #DIV/0! | AB30: =생산효율!Q43 -> #DIV/0! | ... AF30: =생산효율!U43 -> #DIV/0! | AG30: 월별 실적 | AH30: 생산성실적
B31: 공정개선 | D31: =W31 -> 0 | E31: 당해 1월부터 합산 | F31: =SUM($U31:W31) -> 0 | AG31: 월별 실적 | AH31: 회사 기준
B32: 설비가동율 | D32: =W32 -> 0 | E32: 당해 1월부터 평균 | F32: =AVERAGE(U32:W32) -> 0 | H32: 0 | I32: 0 | J32: 0 | K32: 0 | L32: 0 | M32: 0 | N32: 0 | O32: 0 | P32: 0 | Q32: 0 | R32: 0 | S32: 0 | T32: 0 | U32: 0 | V32: 0 | AG32: 월별 실적 | AH32: 생산성실적
A33: 예산관리 | B33: 일반경비율 | D33: =W33 -> #DIV/0! | E33: 고정 링크 | F33: =F11 -> 0.054180499 | G33: 0.065315397 | H33: 0.094963934 | I33: 0.066807248 | J33: 0.066619971 | K33: 0.061327915 | L33: 0.056375727 | M33: 0.052955563 | N33: 0.051788974 | O33: 0.054167403 | P33: 0.049943226 | Q33: 0.051089486 | R33: 0.057145275 | S33: 0.060331222 | T33: 0.056905189 | U33: =U11 -> 0.057101887 | V33: =V11 -> 0.051508587 | W33: =W11 -> #DIV/0! | X33: =X11 -> #DIV/0! | Y33: =Y11 -> #DIV/0! | Z33: =Z11 -> #DIV/0! | AA33: =AA11 -> #DIV/0! | AB33: =AB11 -> #DIV/0! | ... AF33: =AF11 -> #DIV/0! | AG33: 월별 실적 | AH33: 경영실적
A34: SAP관리 | B34: 원재료재고조정 | E34: 당해 1월부터 합산 | AG34: 월별 실적
B35: 제품재고조정 | E35: 당해 1월부터 합산 | AG35: 월별 실적
B36: 생산실적 지연등록 | E36: 당해 1월부터 합산 | AG36: 월별 실적
B37: Backlog 지연처리 | E37: 당해 1월부터 합산 | L37: =IF(L36="","",IF(1-(L36-18)/18>100%,100%,1-(L36-18)/18)) | AG37: 월별 실적
B38: 납품문서 지연처리 | E38: 당해 1월부터 합산 | AG38: 월별 실적
B39: 수요계획 시간준수 | E39: 당해 1월부터 합산 | AG39: 월별 실적
B40: 생산계획 시간준수 | E40: 당해 1월부터 합산 | AG40: 월별 실적
B41: 자동발주실행 | E41: 당해 1월부터 합산 | AG41: 월별 실적
A42: 품질관리 | B42: 고객불량율 | D42: =W42 -> 22.257154 | E42: 당해 1월부터 평균 | F42: =AVERAGE(U42:W42) -> 29.416911 | G42: 36.173779 | H42: 23.41392 | I42: 22 | J42: 42 | K42: 25.23955 | L42: 38.246768 | M42: 25.709337 | N42: 29.545152 | O42: 38.061019 | P42: 44.034393 | Q42: 22 | R42: 38 | S42: 25 | T42: 27.462217 | U42: =불량율!E4 -> 41.575226 | V42: =불량율!F4 -> 24.418355 | W42: =불량율!G4 -> 22.257154 | X42: =불량율!H4 -> 22.311753 | Y42: =불량율!I4 -> #DIV/0! | Z42: =불량율!J4 -> #DIV/0! | AA42: =불량율!K4 -> #DIV/0! | AB42: =불량율!L4 -> #DIV/0! | ... AF42: =불량율!P4 -> #DIV/0! | AG42: 월별 실적 | AH42: ◀ 고객사 클레임과 고객불량율 상관관계 필 확인
B43: 공정불량율 | D43: =W43 -> 140.76445 | E43: 당해 1월부터 평균 | F43: =AVERAGE(U43:W43) -> 128.85912 | G43: 913.42888 | H43: 866.90434 | I43: 1107.915 | J43: 1040.2198 | K43: 693.56787 | L43: 755.88369 | M43: 941.37792 | N43: 612.37053 | O43: 563.19812 | P43: 507.3954 | Q43: 334 | R43: 383 | S43: 316.89885 | T43: 353.04566 | U43: =불량율!E6 -> 107.60462 | V43: =불량율!F6 -> 138.20828 | W43: =불량율!G6 -> 140.76445 | X43: =불량율!H6 -> 136.52035 | Y43: =불량율!I6 -> #DIV/0! | Z43: =불량율!J6 -> #DIV/0! | AA43: =불량율!K6 -> #DIV/0! | AB43: =불량율!L6 -> #DIV/0! | ... AF43: =불량율!P6 -> #DIV/0! | AG43: 월별 실적
B44: 입고불량율 | D44: =W44 -> 282.31428 | E44: 당해 1월부터 평균 | F44: =AVERAGE(U44:W44) -> 253.56273 | G44: 252.89931 | H44: 253.24601 | I44: 235.11764 | J44: 298.83505 | K44: 647.09344 | L44: 313.01894 | M44: 408.53689 | N44: 399.97323 | O44: 456 | P44: 586.14709 | Q44: 440 | R44: 594 | S44: 783.61342 | T44: 802.20671 | U44: =불량율!E8 -> 242.873 | V44: =불량율!F8 -> 235.50092 | W44: =불량율!G8 -> 282.31428 | X44: =불량율!H8 -> 267.68584 | Y44: =불량율!I8 -> #DIV/0! | Z44: =불량율!J8 -> #DIV/0! | AA44: =불량율!K8 -> #DIV/0! | AB44: =불량율!L8 -> #DIV/0! | ... AF44: =불량율!P8 -> #DIV/0! | AG44: 월별 실적
B45: 필드클레임 | D45: =W45 -> 0 | E45: 당해 1월부터 합산 | F45: =SUM($U45:W45) -> 0 | G45: 0 | H45: 0 | I45: 0 | J45: 0 | K45: 0 | L45: 0 | M45: 0 | N45: 0 | O45: 0 | P45: 0 | Q45: 0 | R45: 0 | S45: 0 | T45: 0 | U45: ='클레임&폐기비'!C4*1000 -> 0 | V45: ='클레임&폐기비'!D4*1000 -> 0 | W45: ='클레임&폐기비'!E4*1000 -> 0 | X45: ='클레임&폐기비'!F4*1000 -> 0 | Y45: ='클레임&폐기비'!G4*1000 -> 0 | Z45: ='클레임&폐기비'!H4*1000 -> 0 | AA45: ='클레임&폐기비'!I4*1000 -> 0 | AB45: ='클레임&폐기비'!J4*1000 -> 0 | ... AF45: ='클레임&폐기비'!N4*1000 -> 0 | AG45: 월별 실적 | AH45: ◀ 고객사 클레임과 고객불량율 상관관계 필 확인
B46: 기타클레임 | D46: =W46 -> 1881 | E46: 당해 1월부터 합산 | F46: =SUM($U46:W46) -> 5791 | G46: 0 | H46: 0 | I46: 215.89808 | J46: 0 | K46: 238.63536 | L46: 1487.7346 | M46: 0 | N46: 3114.6259 | O46: 9882.5861 | P46: 490.9648 | Q46: 2.368 | R46: 7664.528 | S46: 0 | T46: 0 | U46: ='클레임&폐기비'!C5*1000 -> 2030 | V46: ='클레임&폐기비'!D5*1000 -> 1880 | W46: ='클레임&폐기비'!E5*1000 -> 1881 | X46: ='클레임&폐기비'!F5*1000 -> 1807 | Y46: ='클레임&폐기비'!G5*1000 -> 0 | Z46: ='클레임&폐기비'!H5*1000 -> 0 | AA46: ='클레임&폐기비'!I5*1000 -> 0 | AB46: ='클레임&폐기비'!J5*1000 -> 0 | ... AF46: ='클레임&폐기비'!N5*1000 -> 0 | AG46: 월별 실적
B47: 폐기원가 | D47: =W47 -> 0 | E47: 당해 1월부터 합산 | F47: =SUM($U47:W47) -> 0 | G47: 0 | H47: 0 | I47: 0 | J47: 0 | K47: 0 | L47: 0 | M47: 0 | N47: 0 | O47: 0 | P47: 0 | Q47: 0 | R47: 0 | S47: 0 | T47: 0 | U47: =U13 -> 0 | V47: =V13 -> 0 | W47: =W13 -> 0 | X47: =X13 -> 0 | Y47: =Y13 -> 0 | Z47: =Z13 -> 0 | AA47: =AA13 -> 0 | AB47: =AB13 -> 0 | ... AF47: =AF13 -> 0 | AG47: 링크 확인
A48: 원가개선 | B48: 원가절감 | D48: =W48 -> 0 | E48: 전년 11월부터 합산 | F48: =SUM($S48:W48) -> 347545 | I48: 264896 | J48: 31570 | K48: 352035 | L48: 9088 | M48: 0 | N48: 0 | O48: 0 | P48: 0 | Q48: 0 | R48: 0 | S48: 0 | T48: 0 | U48: =원가절감!L72*1000 -> 316102 | V48: =원가절감!M72*1000 -> 31443 | W48: =원가절감!N72*1000 -> 0 | X48: =원가절감!O72*1000 -> 0 | Y48: =원가절감!P72*1000 -> 0 | Z48: =원가절감!Q72*1000 -> 0 | AA48: =원가절감!R72*1000 -> 0 | AB48: =원가절감!S72*1000 -> 0 | ... AE48: =원가절감!V72*1000 -> 0 | AF48: 0 | AG48: 월별 실적
B49: 개선제안 | D49: =W49 -> 178 | E49: 전년 11월부터 합산 | F49: =SUM($S49:W49) -> 322 | I49: 0 | J49: 0 | K49: 0 | L49: 0 | M49: 100 | N49: 40 | O49: 131 | P49: 132 | Q49: 39 | R49: 5 | S49: 0 | T49: 54 | U49: 4 | V49: 86 | W49: =268-90 -> 178 | AG49: 월별 실적
A50: 사업실적 | B50: 적기보고 | D50: =W50 -> 15 | E50: 당해 1월부터 평균 | F50: =AVERAGE(U50:W50) -> 15 | G50: 15 | H50: 15 | I50: 15 | J50: 15 | K50: 15 | L50: 15 | M50: 15 | N50: 15 | O50: 15 | P50: 15 | Q50: 15 | R50: 15 | S50: 15 | T50: 15 | U50: 15 | V50: 15 | W50: 15 | AG50: 제출 일수
A52: 3. 2024年 월별 성과지표 목표 | D52: 기간수정, 링크 | E52: ▽ 컬러별 범위 확인 | F52: 기간수정 | H52: ▼ 메모 필수 확인 | J52: ▼ 메모 필수 확인 | V52: ▼ 메모 필수 확인
A53: 관리부문 | B53: 성과지표 | C53: 2024년 목표 | D53: 당월(해당월) | E53: 누적 집계방법 | F53: 월누계 | G53: 매출, 이익지표 : 1월~12월 | I53: 당해 1월 | J53: 당해 2월 | K53: 당해 3월 | L53: 당해 4월 | M53: 당해 5월 | N53: 당해 6월 | O53: 당해 7월 | P53: 당해 8월 | Q53: 당해 9월 | R53: 당해 10월 | S53: 23년 11월 | T53: 23년 12월 | U53: 당해 1월 | V53: 당해 2월 | W53: 당해 3월 | X53: 당해 4월 | Y53: 당해 5월 | Z53: 당해 6월 | AA53: 당해 7월 | AB53: 당해 8월 | AC53: 당해 9월 | AD53: 당해 10월 | AE53: 24년 11월 | AF53: 24년 12월 | AG53: 비 고
G54: 22년 11월 | H54: 22년 12월 | S54: 타 지표 : 전년11월~당해10월 | AE54: 타 지표 : 전년11월~당해10월
A55: 경영관리 | B55: 매출액 | C55: 1.0461407e+08 | D55: =W55 -> 9209491.7 | E55: 당해 1월부터 합산 | F55: =SUM(U55:W55) -> 26299702 | G55: 4668209.1 | H55: 5043522.8 | I55: 5269395.5 | J55: 6008423.6 | K55: 7304532.8 | L55: 6455807.1 | M55: 4964178 | N55: 6717620.3 | O55: 6734683 | P55: 6456778.1 | Q55: 6743530.3 | R55: 5741722.8 | S55: 6739739.1 | T55: 6988789.3 | U55: ='월계획 '!H80 -> 8200673.2 | V55: ='월계획 '!I80 -> 8889536.9 | W55: ='월계획 '!J80 -> 9209491.7 | X55: ='월계획 '!K80 -> 8543837.1 | Y55: ='월계획 '!L80 -> 7186028.8 | Z55: ='월계획 '!M80 -> 8889304.6 | AA55: ='월계획 '!N80 -> 9603975.8 | AB55: ='월계획 '!O80 -> 9249341.9 | ... AF55: ='월계획 '!S80 -> 8864750.1 | AG55: 년간 계획 | AH55: 경영계획
B56: 경상이익 | C56: 5611757.3 | D56: =W56 -> 599790.88 | E56: 당해 1월부터 합산 | F56: =SUM(U56:W56) -> 1639646.9 | G56: 163339.1 | H56: 212743.64 | I56: 121634.82 | J56: 346729.64 | K56: 557748.38 | L56: 467993.62 | M56: 203062.3 | N56: 511363.65 | O56: 512308.68 | P56: 443027.32 | Q56: 547002.14 | R56: 257307.17 | S56: 303118.43 | T56: 449523.13 | U56: ='월계획 '!H107 -> 461711.84 | V56: ='월계획 '!I107 -> 578144.23 | W56: ='월계획 '!J107 -> 599790.88 | X56: ='월계획 '!K107 -> 510061.65 | Y56: ='월계획 '!L107 -> 294465.41 | Z56: ='월계획 '!M107 -> 544949.56 | AA56: ='월계획 '!N107 -> 583655.08 | AB56: ='월계획 '!O107 -> 552421.77 | ... AF56: ='월계획 '!S107 -> 377257.17 | AG56: 년간 계획 | AH56: 경영계획
B57: 적정재고 | C57: 3.5105271 | D57: =W57 -> 0 | E57: 당해 1월부터 평균 | F57: =AVERAGE(U57:W57) -> 1622277.6 | G57: 1950995.1 | H57: 2103593.8 | I57: 2322097.8 | J57: 2628897.3 | K57: 3439450.4 | L57: 2914187.2 | M57: 2403713.6 | N57: 2691546.2 | O57: 2923926.5 | P57: 3281516.9 | Q57: 3253308.5 | R57: 3222684.2 | S57: 3157493 | T57: 3355017 | U57: =U20/$C$57 -> 2324879.5 | V57: =V20/$C$57 -> 2541953.2 | W57: =W20/$C$57 -> 0 | X57: =X20/$C$57 -> 0 | Y57: =Y20/$C$57 -> 0 | Z57: =Z20/$C$57 -> 0 | AA57: =AA20/$C$57 -> 0 | AB57: =AB20/$C$57 -> 0 | ... AF57: =AF20/$C$57 -> 0 | AG57: 수식 확인 | AH57: 실적 대비
B58: 인당매출 | C58: 179646.38 | D58: =W58 -> 16016.507 | E58: 수식 | F58: =F55/F64 -> 45606.419 | G58: 8411.1875 | H58: 8756.1159 | I58: 9448.6822 | J58: 10789.996 | K58: 12764.136 | L58: 11642.227 | M58: 8860.0307 | N58: 12103.094 | O58: 12106.923 | P58: 11641.725 | Q58: 12108.016 | R58: 10260.677 | S58: 12112.912 | T58: 12567.367 | U58: =U55/U64 -> 14188.016 | V58: =V55/V64 -> 15406.476 | W58: =W55/W64 -> 16016.507 | X58: =X55/X64 -> 14807.343 | Y58: =Y55/Y64 -> 12368.38 | Z58: =Z55/Z64 -> 15406.074 | AA58: =AA55/AA64 -> 16644.672 | AB58: =AB55/AB64 -> 16030.055 | ... AF58: =AF55/AF64 -> 15231.529 | AG58: 수식 확인
A59: 표준관리 | B59: 재료비율 | D59: =W59 -> 0 | E59: 고정 링크 | F59: =$F$5 -> 13388862 | G59: 5289611.6 | H59: 5412336.6 | I59: 5083629.7 | J59: 5886481.9 | K59: 6525851.1 | L59: 6432337.7 | M59: 5286854.4 | N59: 6929326.6 | O59: 7128318.8 | P59: 7146329.8 | Q59: 7286711.3 | R59: 7514841 | S59: 7019551.7 | T59: 7002821.8 | U59: =U5 -> 6495587.6 | V59: =V5 -> 6893274.2 | W59: =W5 -> 0 | X59: =X5 -> 0 | Y59: =Y5 -> 0 | Z59: =Z5 -> 0 | AA59: =AA5 -> 0 | AB59: =AB5 -> 0 | ... AF59: =AF5 -> 0 | AG59: 링크 확인 | AH59: 실적 대비
A60: 인력관리 | B60: 당월 표준인원 | C60: 467.25 | D60: =W60 -> 461 | E60: 당해 1월부터 평균 | F60: =AVERAGE(U60:W60) -> 462.66667 | G60: 374 | H60: 395 | I60: 437.68576 | J60: 436.85135 | K60: 452.27007 | L60: 434.51651 | M60: 440.28903 | N60: 435.03333 | O60: 436.26711 | P60: 434.62381 | Q60: 436.94758 | R60: 439.58519 | S60: 471 | T60: 471 | U60: 464 | V60: 463 | W60: 461 | X60: 463 | Y60: 467 | Z60: 463 | AA60: 463 | AB60: 463 | AC60: 477 | AD60: 494 | AE60: 461 | AF60: 468 | AG60: 년간 계획 | AH60: 인원계획
B61: 간접인원 | C61: 93 | D61: =W61 -> 93 | E61: 당해 1월부터 평균 | F61: =AVERAGE(U61:W61) -> 93 | G61: 160 | H61: 160 | I61: 95 | J61: 95 | K61: 95 | L61: 95 | M61: 95 | N61: 95 | O61: 95 | P61: 95 | Q61: 95 | R61: 95 | S61: 93 | T61: 93 | U61: 93 | V61: 93 | W61: 93 | X61: 93 | Y61: 93 | Z61: 93 | AA61: 93 | AB61: 93 | AC61: 93 | AD61: 93 | AE61: 93 | AF61: 93 | AG61: 회사 지침 | AH61: ◀ 공장 규모별 기준_본사 공지인원
B62: 간접제외원 | C62: 21 | D62: =W62 -> 21 | E62: 당해 1월부터 평균 | F62: =AVERAGE(U62:W62) -> 21 | G62: 21 | H62: 21 | I62: 25 | J62: 25 | K62: 25 | L62: 25 | M62: 25 | N62: 25 | O62: 25 | P62: 25 | Q62: 25 | R62: 25 | S62: 21 | T62: 21 | U62: 21 | V62: 21 | W62: 21 | X62: 21 | Y62: 21 | Z62: 21 | AA62: 21 | AB62: 21 | AC62: 21 | AD62: 21 | AE62: 21 | AF62: 21 | AG62: 년간 계획 | AH62: ◀ 제외 인정인원 구분
B63: 간접비율 | C63: 0.19903692 | D63: =W63 -> 0.20173536 | E63: 수식 | F63: =F61/F60 -> 0.20100865 | G63: 0.42780749 | H63: 0.40506329 | I63: 0.2170507 | J63: 0.21746528 | K63: 0.21005148 | L63: 0.21863381 | M63: 0.21576735 | N63: 0.21837407 | O63: 0.2177565 | P63: 0.21857983 | Q63: 0.21741739 | R63: 0.21611283 | S63: 0.21768545 | T63: 0.21783689 | U63: =U61/U60 -> 0.20043103 | V63: =V61/V60 -> 0.20086393 | W63: =W61/W60 -> 0.20173536 | X63: =X61/X60 -> 0.20086393 | Y63: =Y61/Y60 -> 0.19914347 | Z63: =Z61/Z60 -> 0.20086393 | AA63: =AA61/AA60 -> 0.20086393 | AB63: =AB61/AB60 -> 0.20086393 | ... AF63: =AF61/AF60 -> 0.19871795 | AG63: 수식 확인
B64: 인원합계 | C64: 582.33333 | D64: =W64 -> 575 | E64: 수식 | F64: =F60+F61+F62 -> 576.66667 | G64: 555 | H64: 576 | I64: 557.68576 | J64: 556.85135 | K64: 572.27007 | L64: 554.51651 | M64: 560.28903 | N64: 555.03333 | O64: 556.26711 | P64: 554.62381 | Q64: 556.94758 | R64: 559.58519 | S64: 556.4095 | T64: 556.10611 | U64: =U60+U61+U62 -> 578 | V64: =V60+V61+V62 -> 577 | W64: =W60+W61+W62 -> 575 | X64: =X60+X61+X62 -> 577 | Y64: =Y60+Y61+Y62 -> 581 | Z64: =Z60+Z61+Z62 -> 577 | AA64: =AA60+AA61+AA62 -> 577 | AB64: =AB60+AB61+AB62 -> 577 | ... AF64: =AF60+AF61+AF62 -> 582 | AG64: 수식 확인
A65: 생산관리 | B65: 생산효율 | C65: 1 | D65: =W65 -> 1 | E65: 당해 1월부터 평균 | F65: =AVERAGE(U65:W65) -> 1 | G65: 1 | H65: 1 | I65: 1 | J65: 1 | K65: 1 | L65: 1 | M65: 1 | N65: 1 | O65: 1 | P65: 1 | Q65: 1 | R65: 1 | S65: 1 | T65: 1 | U65: 1 | V65: 1 | W65: 1 | X65: 1 | Y65: 1 | Z65: 1 | AA65: 1 | AB65: 1 | AC65: 1 | AD65: 1 | AE65: 1 | AF65: 1 | AG65: 년간 계획 | AH65: 생산성계획
B66: 공정개선 | C66: 89123.296 | D66: =W66 -> 7426.9413 | E66: 당해 1월부터 합산 | F66: =SUM($U66:W66) -> 22280.824 | I66: 64322.778 | J66: 64322.778 | K66: 64322.778 | L66: 64322.778 | M66: 64322.778 | N66: 64322.778 | O66: 64322.778 | P66: 64322.778 | Q66: 64322.778 | R66: 64322.778 | S66: 7426.9413 | T66: 7426.9413 | U66: 7426.9413 | V66: 7426.9413 | W66: 7426.9413 | X66: 7426.9413 | Y66: 7426.9413 | Z66: 7426.9413 | AA66: 7426.9413 | AB66: 7426.9413 | AC66: 7426.9413 | AD66: 7426.9413 | AE66: 7426.9413 | AF66: 7426.9413 | AG66: 년간 계획 | AH66: 회사 기준
B67: 설비가동율 | C67: 0.9 | D67: =W67 -> 0.9 | E67: 당해 1월부터 평균 | F67: =AVERAGE(U67:W67) -> 0.9 | G67: 1 | H67: 1 | I67: 0.9 | J67: 0.9 | K67: 0.9 | L67: 0.9 | M67: 0.9 | N67: 0.9 | O67: 0.9 | P67: 0.9 | Q67: 0.9 | R67: 0.9 | S67: 0.9 | T67: 0.9 | U67: 0.9 | V67: 0.9 | W67: 0.9 | X67: 0.9 | Y67: 0.9 | Z67: 0.9 | AA67: 0.9 | AB67: 0.9 | AC67: 0.9 | AD67: 0.9 | AE67: 0.9 | AF67: 0.9 | AG67: 년간 계획 | AH67: 생산성계획
A68: 예산관리 | B68: 일반경비율 | C68: 0.05512952 | D68: =W68 -> 0.054074608 | E68: 고정 링크 | F68: =F9 -> 0.054954103 | I68: 0.079066807 | J68: 0.064615529 | K68: 0.061152305 | L68: 0.062522023 | M68: 0.070547585 | N68: 0.061291208 | O68: 0.062302606 | P68: 0.065261868 | Q68: 0.058361691 | R68: 0.078526468 | S68: 0.063210788 | T68: 0.060458753 | U68: ='월계획 '!H94/'월계획 '!H80 -> 0.057385113 | V68: ='월계획 '!I94/'월계획 '!I80 -> 0.053622626 | W68: ='월계획 '!J94/'월계획 '!J80 -> 0.054074608 | X68: ='월계획 '!K94/'월계획 '!K80 -> 0.054990437 | Y68: ='월계획 '!L94/'월계획 '!L80 -> 0.058553426 | Z68: ='월계획 '!M94/'월계획 '!M80 -> 0.053441891 | AA68: ='월계획 '!N94/'월계획 '!N80 -> 0.052366098 | AB68: ='월계획 '!O94/'월계획 '!O80 -> 0.052206908 | ... AF68: ='월계획 '!S94/'월계획 '!S80 -> 0.054644418 | AG68: 년간 계획 | AH68: 경영계획
A69: SAP관리 | B69: 원재료재고조정 | E69: 당해 1월부터 합산
B70: 제품재고조정 | E70: 당해 1월부터 합산
B71: 생산실적 지연등록 | E71: 당해 1월부터 합산
B72: Backlog 지연처리 | E72: 당해 1월부터 합산
B73: 납품문서 지연처리 | E73: 당해 1월부터 합산
B74: 수요계획 시간준수 | E74: 당해 1월부터 합산
B75: 생산계획 시간준수 | E75: 당해 1월부터 합산
B76: 자동발주실행 | E76: 당해 1월부터 합산
A77: 품질관리 | B77: 고객불량율 | C77: 0 | D77: =W77 -> 16.124793 | E77: 당해 1월부터 평균 | F77: =AVERAGE(U77:W77) -> 16.124793 | G77: 0 | H77: 0 | I77: 0 | J77: 0 | K77: 0 | L77: 0 | M77: 0 | N77: 0 | O77: 0 | P77: 0 | Q77: 0 | R77: 0 | S77: 16.124793 | T77: 16.124793 | U77: 16.124793 | V77: 16.124793 | W77: 16.124793 | X77: 16.124793 | Y77: 16.124793 | Z77: 16.124793 | AA77: 16.124793 | AB77: 16.124793 | AC77: 16.124793 | AD77: 16.124793 | AE77: 16.124793 | AF77: 16.124793 | AG77: 회사 지침 | AH77: 전사 동일 목표
B78: 공정불량율 | C78: 50 | D78: =W78 -> 50 | E78: 당해 1월부터 평균 | F78: =AVERAGE(U78:W78) -> 50 | G78: 50 | H78: 50 | I78: 50 | J78: 50 | K78: 50 | L78: 50 | M78: 50 | N78: 50 | O78: 50 | P78: 50 | Q78: 50 | R78: 50 | S78: 50 | T78: 50 | U78: 50 | V78: 50 | W78: 50 | X78: 50 | Y78: 50 | Z78: 50 | AA78: 50 | AB78: 50 | AC78: 50 | AD78: 50 | AE78: 50 | AF78: 50 | AG78: 회사 지침 | AH78: 전사 동일 목표
B79: 입고불량율 | C79: 50 | D79: =W79 -> 50 | E79: 당해 1월부터 평균 | F79: =AVERAGE(U79:W79) -> 50 | G79: 50 | H79: 50 | I79: 50 | J79: 50 | K79: 50 | L79: 50 | M79: 50 | N79: 50 | O79: 50 | P79: 50 | Q79: 50 | R79: 50 | S79: 50 | T79: 50 | U79: 50 | V79: 50 | W79: 50 | X79: 50 | Y79: 50 | Z79: 50 | AA79: 50 | AB79: 50 | AC79: 50 | AD79: 50 | AE79: 50 | AF79: 50 | AG79: 회사 지침 | AH79: 전사 동일 목표
B80: 필드클레임 | C80: 0 | D80: =W80 -> 0 | E80: 당해 1월부터 합산 | F80: =SUM($U80:W80) -> 0 | G80: 1000 | H80: 1000 | I80: 71.666667 | J80: 71.666667 | K80: 71.666667 | L80: 71.666667 | M80: 71.666667 | N80: 71.666667 | O80: 71.666667 | P80: 71.666667 | Q80: 71.666667 | R80: 71.666667 | S80: 0 | T80: 0 | U80: 0 | V80: 0 | W80: 0 | X80: 0 | Y80: 0 | Z80: 0 | AA80: 0 | AB80: 0 | AC80: 0 | AD80: 0 | AE80: 0 | AF80: 0 | AG80: 전년도 실적 50%개선 | AH80: 클레임 목표
B81: 기타클레임 | C81: 10461.407 | D81: =W81 -> 920.94917 | E81: 당해 1월부터 합산 | F81: =SUM($U81:W81) -> 2629.9702 | G81: 503.81879 | H81: 503.81879 | I81: 526.93955 | J81: 600.84236 | K81: 730.45328 | L81: 645.58071 | M81: 496.4178 | N81: 671.76203 | O81: 673.4683 | P81: 645.67781 | Q81: 674.35303 | R81: 574.17228 | U81: 820.06732 | V81: 888.95369 | W81: 920.94917 | X81: 854.38371 | Y81: 718.60288 | Z81: 888.93046 | AA81: 960.39758 | AB81: 924.93419 | AC81: 853.73465 | AD81: 889.48836 | AE81: 854.49024 | AF81: 886.47501 | AG81: 회사 지침 | AH81: 클레임 목표
B82: 폐기원가 | C82: 0 | D82: =W82 -> 0 | E82: 당해 1월부터 합산 | F82: =SUM($U82:W82) -> 0 | G82: 0 | H82: 0 | S82: 0 | T82: 0 | U82: 0 | V82: 0 | W82: 0 | X82: 0 | Y82: 0 | Z82: 0 | AA82: 0 | AB82: 0 | AC82: 0 | AD82: 0 | AE82: 0 | AF82: 0 | AG82: 목표 zero
A83: 원가개선 | B83: 원가절감 | C83: 1569211.1 | D83: =W83 -> 156921.11 | E83: 전년11월부터 합산 | F83: =SUM($S83:W83) -> 941526.65 | G83: 228482.46 | H83: 228482.46 | I83: 152321.64 | J83: 152321.64 | K83: 152321.64 | L83: 152321.64 | M83: 152321.64 | N83: 152321.64 | O83: 152321.64 | P83: 0 | Q83: 0 | R83: 0 | S83: =$C$83*S85 -> 235381.66 | T83: =$C$83*T85 -> 235381.66 | U83: =$C$83*U85 -> 156921.11 | V83: =$C$83*V85 -> 156921.11 | W83: =$C$83*W85 -> 156921.11 | X83: =$C$83*X85 -> 156921.11 | Y83: =$C$83*Y85 -> 156921.11 | Z83: =$C$83*Z85 -> 156921.11 | ... AD83: =$C$83*AD85 -> 0 | AG83: 회사 지침 | AH83: 매출 규모별 기준
B84: 개선제안 | C84: 558 | D84: =W84 -> 46.5 | E84: 전년11월부터 합산 | F84: =SUM($S84:W84) -> 232.5 | G84: 47.5 | H84: 47.5 | I84: 47.5 | J84: 47.5 | K84: 47.5 | L84: 47.5 | M84: 47.5 | N84: 47.5 | O84: 47.5 | P84: 47.5 | Q84: 47.5 | R84: 47.5 | S84: 46.5 | T84: 46.5 | U84: 46.5 | V84: 46.5 | W84: 46.5 | X84: 46.5 | Y84: 46.5 | Z84: 46.5 | AA84: 46.5 | AB84: 46.5 | AC84: 46.5 | AD84: 46.5 | AE84: 46.5 | AF84: 46.5 | AG84: 회사 지침 | AH84: 공장 규모별 기준
C85: 원가절감 월목표율 | I85: 0.15 | J85: 0.15 | K85: 0.1 | L85: 0.1 | M85: 0.1 | N85: 0.1 | O85: 0.1 | P85: 0.1 | Q85: 0.1 | S85: 0.15 | T85: 0.15 | U85: 0.1 | V85: 0.1 | W85: 0.1 | X85: 0.1 | Y85: 0.1 | Z85: 0.1 | AA85: 0.1 | AE85: 0.15 | AF85: 0.15

Sheet 불량율
A1: 1. 2026년 목표 및 실적 불량율 | Q1: 단위 : PPM
A2: 구 분 | C2: 25.11월 | D2: 12월 | E2: 26.1월 | F2: 2월 | G2: 3월 | H2: 4월 | I2: 5월 | J2: 6월 | K2: 7월 | L2: 8월 | M2: 9월 | N2: 10월 | O2: 11월 | P2: 12월 | Q2: 누적
A3: 고객불량 | B3: 목표 | C3: 0 | D3: 0 | E3: 0 | F3: 0 | G3: 0 | H3: 0 | I3: 0 | J3: 0 | K3: 0 | L3: 0 | M3: 0 | N3: 0 | O3: 0 | P3: 0 | Q3: =AVERAGE(E3:O3) -> 0
B4: 실적 | C4: =C14 -> 13.260606 | D4: =D14 -> 14.05893 | E4: =E14 -> 41.575226 | F4: =F14 -> 24.418355 | G4: =G14 -> 22.257154 | H4: =H14 -> 22.311753 | I4: =I14 -> #DIV/0! | J4: =J14 -> #DIV/0! | ... Q4: =Q14 -> 27.475663
A5: 공정불량 | B5: 목표 | C5: 50 | D5: 50 | E5: 50 | F5: 50 | G5: 50 | H5: 50 | I5: 50 | J5: 50 | K5: 50 | L5: 50 | M5: 50 | N5: 50 | O5: 50 | P5: 50 | Q5: =AVERAGE(E5:O5) -> 50
B6: 실적 | C6: =C19 -> 150.07515 | D6: =D19 -> 148.93428 | E6: =E19 -> 107.60462 | F6: =F19 -> 138.20828 | G6: =G19 -> 140.76445 | H6: =H19 -> 136.52035 | I6: =I19 -> #DIV/0! | J6: =J19 -> #DIV/0! | ... Q6: =Q19 -> 131.29612
A7: 입고불량 | B7: 목표 | C7: 50 | D7: 50 | E7: 50 | F7: 50 | G7: 50 | H7: 50 | I7: 50 | J7: 50 | K7: 50 | L7: 50 | M7: 50 | N7: 50 | O7: 50 | P7: 50 | Q7: =AVERAGE(E7:O7) -> 50
B8: 실적 | C8: =C22 -> 218.252 | D8: =D22 -> 229.76582 | E8: =E22 -> 242.873 | F8: =F22 -> 235.50092 | G8: =G22 -> 282.31428 | H8: =H22 -> 267.68584 | I8: =I22 -> #DIV/0! | J8: =J22 -> #DIV/0! | ... Q8: =Q22 -> 257.41287
A10: ▣ 2026년 실적 불량율
A11: 구 분 | C11: 25.11월 | D11: 12월 | E11: 26.1월 | F11: 2월 | G11: 3월 | H11: 4월 | I11: 5월 | J11: 6월 | K11: 7월 | L11: 8월 | M11: 9월 | N11: 10월 | O11: 11월 | P11: 12월 | Q11: 누적
A12: 고객불량 | B12: 출하수량 | C12: 452468 | D12: 426775 | E12: 336739 | F12: 409528 | G12: 359435 | H12: 313736 | Q12: =SUM(E12:P12) -> 1419438
B13: 불량수량 | C13: 6 | D13: 6 | E13: 14 | F13: 10 | G13: 8 | H13: 7 | Q13: =SUM(E13:P13) -> 39
B14: 불량율(PPM) | C14: =C13/C12*1000000 -> 13.260606 | D14: =D13/D12*1000000 -> 14.05893 | E14: =E13/E12*1000000 -> 41.575226 | F14: =F13/F12*1000000 -> 24.418355 | G14: =G13/G12*1000000 -> 22.257154 | H14: =H13/H12*1000000 -> 22.311753 | I14: =I13/I12*1000000 -> #DIV/0! | J14: =J13/J12*1000000 -> #DIV/0! | ... P14: =P13/P12*1000000 -> #DIV/0! | Q14: =IF(Q12="","",Q13/Q12*1000000) -> 27.475663
A15: 공정불량 | B15: 생산수량 | C15: 2192235 | D15: 2316458 | E15: 2843744 | F15: 3089540 | G15: 3005020 | H15: 3362136 | Q15: =SUM(E15:P15) -> 12300440
B16: 리워크수량 | C16: 329 | D16: 345 | E16: 306 | F16: 427 | G16: 423 | H16: 459 | Q16: =SUM(E16:P16) -> 1615
B17: 폐기수량 | Q17: =SUM(E17:P17) -> 0
B18: 불량수량계 | C18: =C16+C17 -> 329 | D18: =D16+D17 -> 345 | E18: =E16+E17 -> 306 | F18: =F16+F17 -> 427 | G18: =G16+G17 -> 423 | H18: =H16+H17 -> 459 | I18: =I16+I17 -> 0 | J18: =J16+J17 -> 0 | ... P18: =P16+P17 -> 0 | Q18: =SUM(E18:P18) -> 1615
B19: 불량율(PPM) | C19: =C18/C15*1000000 -> 150.07515 | D19: =D18/D15*1000000 -> 148.93428 | E19: =E18/E15*1000000 -> 107.60462 | F19: =F18/F15*1000000 -> 138.20828 | G19: =G18/G15*1000000 -> 140.76445 | H19: =H18/H15*1000000 -> 136.52035 | I19: =I18/I15*1000000 -> #DIV/0! | J19: =J18/J15*1000000 -> #DIV/0! | ... P19: =P18/P15*1000000 -> #DIV/0! | Q19: =IF(Q15="","",Q18/Q15*1000000) -> 131.29612
A20: 입고불량 | B20: 입고수량 | C20: 2707879 | D20: 2654877 | E20: 2787465 | F20: 3027589 | G20: 2964781 | H20: 3216457 | Q20: =SUM(E20:P20) -> 11996292
B21: 불량수량 | C21: 591 | D21: 610 | E21: 677 | F21: 713 | G21: 837 | H21: 861 | Q21: =SUM(E21:P21) -> 3088
B22: 불량율(PPM) | C22: =C21/C20*1000000 -> 218.252 | D22: =D21/D20*1000000 -> 229.76582 | E22: =E21/E20*1000000 -> 242.873 | F22: =F21/F20*1000000 -> 235.50092 | G22: =G21/G20*1000000 -> 282.31428 | H22: =H21/H20*1000000 -> 267.68584 | I22: =I21/I20*1000000 -> #DIV/0! | J22: =J21/J20*1000000 -> #DIV/0! | ... P22: =P21/P20*1000000 -> #DIV/0! | Q22: =IF(Q20="","",Q21/Q20*1000000) -> 257.41287
A24: ▣ 2026년 실적 불량율 - 고객사별 세부자료 별도 작성
A25: 고객구분 | C25: 25.11월 | D25: 12월 | E25: 26.1월 | F25: 2월 | G25: 3월 | H25: 4월 | I25: 5월 | J25: 6월 | K25: 7월 | L25: 8월 | M25: 9월 | N25: 10월 | O25: 11월 | P25: 12월 | Q25: 누적
A26: HTL | B26: delivery | C26: 236789 | D26: 229383 | E26: 197847 | F26: 221795 | G26: 225695 | H26: 211459 | Q26: =SUM(E26:P26) -> 856796
B27: Defect | C27: 0 | D27: 2 | E27: 1 | F27: 3 | G27: 3 | H27: 4 | Q27: =SUM(E27:P27) -> 11
B28: 불량율(PPM) | C28: =IF(C26="","",C27/C26*1000000) -> 0 | D28: =IF(D26="","",D27/D26*1000000) -> 8.719042 | E28: =IF(E26="","",E27/E26*1000000) -> 5.0544107 | F28: =IF(F26="","",F27/F26*1000000) -> 13.526004 | G28: =IF(G26="","",G27/G26*1000000) -> 13.292275 | H28: =IF(H26="","",H27/H26*1000000) -> 18.916197 | I28: =IF(I26="","",I27/I26*1000000) | J28: =IF(J26="","",J27/J26*1000000) | ... P28: =IF(P26="","",P27/P26*1000000) | Q28: =Q27/Q26*1000000 -> 12.838529
A29: MOBIS | B29: delivery | C29: 70651 | D29: 72189 | E29: 58183 | F29: 63026 | G29: 69809 | H29: 72896 | Q29: =SUM(E29:P29) -> 263914
B30: Defect | C30: 6 | D30: 4 | E30: 3 | F30: 7 | G30: 5 | H30: 3 | Q30: =SUM(E30:P30) -> 18
B31: 불량율(PPM) | C31: =IF(C29="","",C30/C29*1000000) -> 84.924488 | D31: =D30/D29*1000000 -> 55.410104 | E31: =IF(E29="","",E30/E29*1000000) -> 51.561453 | F31: =IF(F29="","",F30/F29*1000000) -> 111.06527 | G31: =IF(G29="","",G30/G29*1000000) -> 71.624003 | H31: =IF(H29="","",H30/H29*1000000) -> 41.154522 | I31: =IF(I29="","",I30/I29*1000000) | J31: =IF(J29="","",J30/J29*1000000) | K31: =IF(K29="","",K30/K29*1000000) | L31: =IF(L29="","",L30/L29*1000000) | ... P31: =IF(P29="","",P30/P29*1000000) | Q31: =Q30/Q29*1000000 -> 68.204036
A32: LEAR | B32: delivery | C32: 145028 | D32: 125203 | E32: 80709 | F32: 124707 | G32: 63931 | H32: 29381 | Q32: =SUM(E32:P32) -> 298728
B33: Defect | C33: 0 | D33: 0 | E33: 10 | F33: 0 | G33: 0 | H33: 0 | Q33: =SUM(E33:P33) -> 10
B34: 불량율(PPM) | C34: =IF(C32="","",C33/C32*1000000) -> 0 | D34: =D33/D32*1000000 -> 0 | E34: =IF(E32="","",E33/E32*1000000) -> 123.90192 | F34: =IF(F32="","",F33/F32*1000000) -> 0 | G34: =IF(G32="","",G33/G32*1000000) -> 0 | H34: =IF(H32="","",H33/H32*1000000) -> 0 | I34: =IF(I32="","",I33/I32*1000000) | J34: =IF(J32="","",J33/J32*1000000) | K34: =IF(K32="","",K33/K32*1000000) | L34: =IF(L32="","",L33/L32*1000000) | M34: 0 | N34: 0 | O34: 0 | P34: 0 | Q34: =Q33/Q32*1000000 -> 33.475268
A35: TOTAL | B35: 출하수량 | C35: =SUM(C26,C29,C32) -> 452468 | D35: =SUM(D26,D29,D32) -> 426775 | E35: =SUM(E26,E29,E32) -> 336739 | F35: =SUM(F26,F29,F32) -> 409528 | G35: =G32+G29+G26 -> 359435 | H35: =H32+H29+H26 -> 313736 | I35: =I32+I29+I26 -> 0 | J35: =J32+J29+J26 -> 0 | K35: =K32+K29+K26 -> 0 | L35: =L32+L29+L26 -> 0 | M35: =M32+M29+M26 -> 0 | N35: =N32+N29+N26 -> 0 | ... P35: =P32+P29+P26 -> 0 | Q35: =SUM(E35:P35) -> 1419438
B36: 불량수량 | C36: =SUM(C27,C30,C33) -> 6 | D36: =SUM(D27,D30,D33) -> 6 | E36: =SUM(E27,E30,E33) -> 14 | F36: =SUM(F27,F30,F33) -> 10 | G36: =G33+G30+G27 -> 8 | H36: =H33+H30+H27 -> 7 | I36: =I33+I30+I27 -> 0 | J36: =J33+J30+J27 -> 0 | K36: =K33+K30+K27 -> 0 | L36: =L33+L30+L27 -> 0 | M36: =M33+M30+M27 -> 0 | N36: =N33+N30+N27 -> 0 | ... P36: =P33+P30+P27 -> 0 | Q36: =SUM(E36:P36) -> 39
B37: 불량율(PPM) | C37: =IF(C35="","",C36/C35*1000000) -> 13.260606 | D37: =D36/D35*1000000 -> 14.05893 | E37: =IF(E35="","",E36/E35*1000000) -> 41.575226 | F37: =IF(F35="","",F36/F35*1000000) -> 24.418355 | G37: =IF(G35="","",G36/G35*1000000) -> 22.257154 | H37: =IF(H35="","",H36/H35*1000000) -> 22.311753 | I37: =IF(I35="","",I36/I35*1000000) -> #DIV/0! | J37: =IF(J35="","",J36/J35*1000000) -> #DIV/0! | K37: =IF(K35="","",K36/K35*1000000) -> #DIV/0! | L37: =IF(L35="","",L36/L35*1000000) -> #DIV/0! | ... P37: =IF(P35="","",P36/P35*1000000) -> #DIV/0! | Q37: =Q36/Q35*1000000 -> 27.475663

Sheet 생산효율
B2: 생산성 현황
B3: 항 목 | C3: 구 분 | G3: 2024년 생산성목표 | H3: 2023년 | J3: 2024년 | V3: 2024년 합 계 | W3: 비고 | X3: 비가동 및 LOSS 개선계획
H4: 11월 | I4: 12월 | J4: 1월 | K4: 2월 | L4: 3월 | M4: 4월 | N4: 5월 | O4: 6월 | P4: 7월 | Q4: 8월 | R4: 9월 | S4: 10월 | T4: 11월 | U4: 12월 | Y4: ★ 수립기준 (해당셀 수식 必 확인)
B5: 생산효율 | C5: 직접인원(명) | H5: 398 | I5: 401 | J5: 382 | K5: 376 | V5: =AVERAGE(H5:U5) -> 389.25 | X5: ◀ 생산계획 표준인원(100%) | Y5: ◀ 생산계획 표준인원(100%)
C6: 표준시간(Hr) | H6: 76839.804 | I6: 75872.566 | J6: 68463.478 | K6: 73661.272 | V6: =SUM(H6:U6) -> 294837.12 | X6: ◀ 생산계획 표준시간(100%) | Y6: ◀ 생산계획 표준시간(100%)
C7: 종합생산성 | G7: =+G6/G8 -> #DIV/0! | H7: =+H6/H8 -> 0.93649189 | I7: =+I6/I8 -> 0.87009387 | J7: =+J6/J8 -> 0.8896011 | K7: =+K6/K8 -> 0.91922261 | L7: =+L6/L8 -> #DIV/0! | M7: =+M6/M8 -> #DIV/0! | N7: =+N6/N8 -> #DIV/0! | ... V7: =+V6/V8 -> 0.90345172
C8: 투입시간(Hr) | H8: 82050.688 | I8: 87200.438 | J8: 76959.75 | K8: 80134.312 | V8: =SUM(H8:U8) -> 326345.19 | X8: ◀ 투입 필요시간(노무비 계획 연계) | Y8: ◀ 투입 필요시간(해당셀 수식 확인)
B9: 비가동 시간(Hr) | C9: 인정 비가동 | D9: 작업자 교육(신입포함) | E9: New manpower Education | H9: 132.66667 | I9: 200 | J9: 189.66667 | K9: 62.666667 | V9: =SUM(H9:U9) -> 585 | W9: 신입작업자 교육(3일 / 각 20분)
D10: 안전교육 | E10: Safety Education | H10: 431.5 | I10: 433 | J10: 430.5 | K10: 394.5 | V10: =SUM(H10:U10) -> 1689.5 | W10: 안전교육 시행(A/B조)[월 1회 / 1시간]
D11: 청소시간(시업종료 10분) | E11: Cleanning | J11: 0 | K11: 0 | V11: =SUM(H11:U11) -> 0
D12: 용접와이어 교체 | E12: Change the Welding Wire | H12: 157 | I12: 152.33333 | J12: 165.33333 | K12: 168.33333 | V12: =SUM(H12:U12) -> 643 | W12: CO2코일 교체(드럼코일 40분 / 스풀코일 20분)
D13: 팁 교체 | E13: Change the Welding Tip | H13: 313 | I13: 269.66667 | J13: 216.66667 | K13: 241.33333 | V13: =SUM(H13:U13) -> 1040.6667 | W13: CO2, SPOT TIP 교체 / 팁청소 및 티칭수정 10분
D14: 신차 작업 지원 | E14: Support to NEW Project | J14: 690 | K14: 0 | V14: =SUM(H14:U14) -> 690
D15: 계획비가동(상세기록 必) | E15: As per Plan(Need detail information) | F15: my machine, quality education | H15: 722.75 | I15: 790 | J15: 572.75 | K15: 779.75 | V15: =SUM(H15:U15) -> 2865.25 | W15: 1. 마이머신 시행(매주 수요일 / 8:10~8:40) 2. 품질교육 시행(매일 / 12:00~12:30) *요일별 지정 라인 교육진행
D16: 고객사 라인정지 | E16: Customer Line Stop | J16: 0 | K16: 0 | V16: =SUM(H16:U16) -> 0
D17: 지그교환(기준 정립 必) | E17: Change the Welding Fixture | H17: 45.333333 | I17: 45 | J17: 42.333333 | K17: 51.666667 | V17: =SUM(H17:U17) -> 184.33333 | W17: 지그교체 각 20분
D18: 금형교환(기준 정립 必) | E18: Change the Mold | H18: 321 | I18: 337 | J18: 316.33333 | K18: 328 | V18: =SUM(H18:U18) -> 1302.3333 | W18: 금형교체 각 20분
D19: 타부서지원 | E19: Support to Other Department | I19: 720 | J19: 690 | K19: 750 | V19: =SUM(H19:U19) -> 2160 | W19: 12월 ~ SU2I PE 차종양산 시작 (100일작전 인원투입 - 2 /2 = 4명)
D20: 정전 | E20: Power Cut | H20: 946.5 | I20: 1475 | J20: 1467.4667 | K20: 909.39919 | V20: =SUM(H20:U20) -> 4798.3659 | W20: 정전 1회 20분 * 출근인원 계산
D21: 시간(Hr) 소계 | G21: =SUM(G9:G20) -> 0 | H21: =SUM(H9:H20) -> 3069.75 | I21: =SUM(I9:I20) -> 4422 | J21: =SUM(J9:J20) -> 4781.05 | K21: =SUM(K9:K20) -> 3685.6492 | L21: =SUM(L9:L20) -> 0 | M21: =SUM(M9:M20) -> 0 | N21: =SUM(N9:N20) -> 0 | ... U21: =SUM(U9:U20) -> 0 | V21: =SUM(H21:U21) -> 15958.449
D22: 비율 | G22: =+G21/G8 -> #DIV/0! | H22: =+H21/H8 -> 0.037412849 | I22: =+I21/I8 -> 0.050710755 | J22: =+J21/J8 -> 0.062124032 | K22: =+K21/K8 -> 0.045993396 | L22: =+L21/L8 -> #DIV/0! | M22: =+M21/M8 -> #DIV/0! | N22: =+N21/N8 -> #DIV/0! | ... V22: =+V21/V8 -> 0.048900519 | X22: 1. 인정비가동 비율 인정(100%) | Y22: 1. 인정비가동 비율 인정(100%)
C23: 개선 비가동 | D23: 장비고장 | E23: Machine Problem | H23: 207.83 | I23: 319.09 | J23: 151.91 | K23: 232.99 | V23: =SUM(H23:U23) -> 911.82 | W23: 설비고장(로보트, 유틸리티, 프레스 등) | X23: 설비 PM업무 진행 철저
D24: 지그고장 | E24: Welding Fixture Problem | H24: 106.51 | I24: 59.5 | J24: 65.34 | K24: 90.81 | V24: =SUM(H24:U24) -> 322.16 | W24: 지그고장 | X24: 지그 PM업무 진행 철저
D25: 센서고장 | E25: Sensor Trouble | H25: 44.85 | I25: 23.67 | J25: 43 | K25: 41.24 | V25: =SUM(H25:U25) -> 152.76 | W25: 지그 센서고장 | X25: 설비별 고장 트렌트 확인 및 개선진행
D26: 바코드이상 | E26: Barcode Trouble | H26: 0 | I26: 23.84 | J26: 8.2 | K26: 5 | V26: =SUM(H26:U26) -> 37.04 | W26: 바코드 스캐너 고장
D27: 서보이상 | E27: Servo Problem | H27: 0 | I27: 10.25 | J27: 59.67 | K27: 0.67 | V27: =SUM(H27:U27) -> 70.59 | W27: 서보 모터 및 엠프 고장
D28: 공급자 품질문제 | E28: Supplier Quality Issue | H28: 0 | I28: 9 | J28: 0 | K28: 0 | V28: =SUM(H28:U28) -> 9 | W28: 공급자 품질문제
D29: 공급자 결품 | E29: Supplier Shortage | H29: 489.67 | I29: 266.9 | J29: 612.71 | K29: 256.06 | V29: =SUM(H29:U29) -> 1625.34 | W29: 공급자 결품(납품차 지연, 원자재 결품, 지연공급) | X29: 팀장급 생산성 회의 진행 및 개선진행(매일 15시)
D30: 공정품질문제 | E30: Inprocess Quality Issue | H30: 19.83 | I30: 30.5 | J30: 31.5 | K30: 19.33 | V30: =SUM(H30:U30) -> 101.16 | W30: 내부 품질문제
D31: 공정결품 | E31: Inprocess Shortage | H31: 80 | I31: 103 | J31: 127.86 | K31: 145.5 | V31: =SUM(H31:U31) -> 456.36 | W31: 내부 단품결품 | X31: TFT팀운영 및 용접&공정품질문제 개선
D32: 공정품 피딩지연 | E32: Inprocess Feeding Delay | H32: 0 | I32: 0 | J32: 0 | K32: 0 | V32: =SUM(H32:U32) -> 0
D33: 고객품질문제 | E33: Customer Quality Issue | F33: *support to other department | H33: 0 | I33: 0 | J33: 0 | K33: 0 | V33: =SUM(H33:U33) -> 0 | W33: 고객품질 문제 발생 시 추가 인원 투입 / 리워크
D34: 납품용기결품 | E34: Trolley Shortage | H34: 255 | I34: 743.8 | J34: 487 | K34: 454.42 | V34: =SUM(H34:U34) -> 1940.22 | W34: 납품용기 결품(계획변경, 교통체증) | X34: 팀장급 생산성 회의 진행 및 개선진행(매일 15시)
D35: 작업자결원 | E35: Manpower Shortage | F35: *leave + operator delay | H35: 360 | I35: 679.96 | J35: 542 | K35: 301 | V35: =SUM(H35:U35) -> 1882.96 | W35: 작업자 지연 투입(버스지연, 인원 결근, 지각) | X35: 팀장급 생산성 회의 진행 및 개선진행(매일 15시)
D36: 로보트 티칭수정 | E36: Robot Teaching Adjustment | H36: 138.4 | I36: 115.52 | J36: 135.04 | K36: 145.44 | V36: =SUM(H36:U36) -> 534.4 | W36: 로보트 티칭 수정 | X36: TFT팀운영 및 용접&공정품질문제 개선
D37: 금형수리(해당업장 限) | E37: Mold Problem | H37: 66.92 | I37: 15.74 | J37: 35.84 | K37: 13.83 | V37: =SUM(H37:U37) -> 132.33 | W37: 금형수리 | X37: 금형 PM업무 진행 철저
V38: =SUM(H38:U38) -> 0
D39: 시간(Hr) 소계 | G39: =SUM(G23:G38) -> 0 | H39: =SUM(H23:H38) -> 1769.01 | I39: =SUM(I23:I38) -> 2400.77 | J39: =SUM(J23:J38) -> 2300.07 | K39: =SUM(K23:K38) -> 1706.29 | L39: =SUM(L23:L38) -> 0 | M39: =SUM(M23:M38) -> 0 | N39: =SUM(N23:N38) -> 0 | ... U39: =SUM(U23:U38) -> 0 | V39: =SUM(H39:U39) -> 8176.14
D40: 비율 | G40: =+G39/G8 -> #DIV/0! | H40: =+H39/H8 -> 0.021559966 | I40: =+I39/I8 -> 0.027531628 | J40: =+J39/J8 -> 0.029886662 | K40: =+K39/K8 -> 0.021292876 | L40: =+L39/L8 -> #DIV/0! | M40: =+M39/M8 -> #DIV/0! | N40: =+N39/N8 -> #DIV/0! | ... V40: =+V39/V8 -> 0.025053656 | X40: 2. 개선비가동율 30% 개선(누계실적의 70% 적용) | Y40: 2. 개선비가동율 30% 개선(누계실적의 70% 적용)
B41: Loss | C41: 시간(Hr) 소계 | G41: =+G8-G6-G21-G39 -> 0 | H41: =+H8-H6-H21-H39 -> 372.12371 | I41: =+I8-I6-I21-I39 -> 4505.1017 | J41: =+J8-J6-J21-J39 -> 1415.1516 | K41: =+K8-K6-K21-K39 -> 1081.1012 | L41: =+L8-L6-L21-L39 -> 0 | M41: =+M8-M6-M21-M39 -> 0 | N41: =+N8-N6-N21-N39 -> 0 | ... V41: =+V8-V6-V21-V39 -> 7373.4783
C42: 비율 | G42: =+G41/G8 -> #DIV/0! | H42: =+H41/H8 -> 0.0045352906 | I42: =+I41/I8 -> 0.051663751 | J42: =+J41/J8 -> 0.018388204 | K42: =+K41/K8 -> 0.013491115 | L42: =+L41/L8 -> #DIV/0! | M42: =+M41/M8 -> #DIV/0! | N42: =+N41/N8 -> #DIV/0! | ... V42: =+V41/V8 -> 0.022594108 | X42: 3. LOSS율 70% 개선(누계실적의 30% 적용) | Y42: 3. LOSS율 70% 개선(누계실적의 30% 적용)
B43: 생산효율 | G43: =+(G6+G21)/G8 -> #DIV/0! | H43: =H6/(H8-H21) -> 0.9728905 | I43: =I6/(I8-I21) -> 0.91657403 | J43: =J6/(J8-J21) -> 0.94852745 | K43: =K6/(K8-K21) -> 0.96353905 | L43: =+(L6+L21)/L8 -> #DIV/0! | M43: =+(M6+M21)/M8 -> #DIV/0! | N43: =+(N6+N21)/N8 -> #DIV/0! | O43: =+(O6+O21)/O8 -> #DIV/0! | P43: =+(P6+P21)/P8 -> #DIV/0! | Q43: =+(Q6+Q21)/Q8 -> #DIV/0! | R43: =+(R6+R21)/R8 -> #DIV/0! | S43: =+(S6+S21)/S8 -> #DIV/0! | ... V43: =+(V6+V21)/V8 -> 0.95235224 | X43: ◀ 차년도 목표생산성

Sheet 클레임&폐기비
A1: 1. 2026년 목표 및 실적 불량율
A2: 구 분 | C2: 26.1월 | D2: 2월 | E2: 3월 | F2: 4월 | G2: 5월 | H2: 6월 | I2: 7월 | J2: 8월 | K2: 9월 | L2: 10월 | M2: 11월 | N2: 12월 | O2: 누적
A3: 매출액(백만원) | C3: =418534963*15.5/1000000 -> 6487.2919 | D3: =456134358*15.5/1000000 -> 7070.0825 | E3: 7235 | F3: =481802882*15.5/1000000 -> 7467.9447 | O3: =SUM(C3:N3) -> 28260.319
A4: 고객사 클레임 | B4: 필드클레임비 | O4: =SUM(C4:N4) -> 0 | R4: ← 완성차 발생 클레임비
B5: 기타클레임비 | C5: 2.03 | D5: 1.88 | E5: 1.881 | F5: 1.807 | O5: =SUM(C5:N5) -> 7.598 | R5: ← 고객사내(시트생산 등) 발생 클레임비
B6: 합 계 | C6: =SUM(C4:C5) -> 2.03 | D6: =SUM(D4:D5) -> 1.88 | E6: =SUM(E4:E5) -> 1.881 | F6: =SUM(F4:F5) -> 1.807 | G6: =SUM(G4:G5) -> 0 | H6: =SUM(H4:H5) -> 0 | I6: =SUM(I4:I5) -> 0 | J6: =SUM(J4:J5) -> 0 | ... N6: =SUM(N4:N5) -> 0 | O6: =SUM(C6:N6) -> 7.598
B7: 비율(%) | C7: =IF(C3="","",C6/C3) -> 0.00031291948 | D7: =IF(D3="","",D6/D3) -> 0.0002659092 | E7: =IF(E3="","",E6/E3) -> 0.00025998618 | F7: =IF(F3="","",F6/F3) -> 0.00024196751 | G7: =IF(G3="","",G6/G3) | H7: =IF(H3="","",H6/H3) | I7: =IF(I3="","",I6/I3) | J7: =IF(J3="","",J6/J3) | ... O7: =IF(O3="","",O6/O3) -> 0.00026885754
A8: 협력업체 클레임 | B8: 고객발생위계 | R8: ← 고객클레임 위계 처리액
B9: 사내활동클레임 | C9: 1.024 | D9: 2.188 | E9: 4.199 | F9: 2.249 | O9: =SUM(C9:N9) -> 9.66 | R9: ← 사내불량 저감활동 클레임 처리액
B10: 합 계 | C10: =SUM(C8:C9) -> 1.024 | D10: =SUM(D8:D9) -> 2.188 | E10: =SUM(E8:E9) -> 4.199 | F10: =SUM(F8:F9) -> 2.249 | G10: =SUM(G8:G9) -> 0 | H10: =SUM(H8:H9) -> 0 | I10: =SUM(I8:I9) -> 0 | J10: =SUM(J8:J9) -> 0 | ... N10: =SUM(N8:N9) -> 0 | O10: =SUM(C10:N10) -> 9.66
A11: 리워크 비용 | B11: 단품 | O11: =SUM(C11:N11) -> 0
B12: 반제품 | O12: =SUM(C12:N12) -> 0
B13: 완성품 | O13: =SUM(C13:N13) -> 0
B14: 원자재(철판) | O14: =SUM(C14:N14) -> 0
B15: 합계 | O15: =SUM(C15:N15) -> 0
A16: 폐기비 | B16: 단품 | O16: =SUM(C16:N16) -> 0
B17: 반제품 | O17: =SUM(C17:N17) -> 0
B18: 완성품 | O18: =SUM(C18:N18) -> 0
B19: 원자재(철판) | O19: =SUM(C19:N19) -> 0
B20: 합계 | C20: 3.74 | D20: 4.01 | E20: 6.086 | F20: 3.653 | O20: =SUM(C20:N20) -> 17.489
O21: =O20/O3 -> 0.00061885359
A22: 2. 2026년 목표달성방안
A23: 항 목 | B23: 목 표 | C23: 주요 문제점 | I23: 목표 달성을 위한 실행계획
A24: 고객 클레임 | B24: 필드클레임 (100% 개선) | C24: PS7i 클래임 증대 | I24: CKD 파손품 지속 모니터링
C25: └ CKD 파트 필드 파손 문제 발생 | I25: └ 필드 비용 산출 클래임 비용 변재 진행
I26: └ 개선 EO품 적용 완료 (예상 범위 파트 지속 모니터링)
B27: 기타클레임 (매출액 0.01%이하) | C27: 쿠션 와이어 밴딩 문제 집중 개선 필요 | I27: LAY-OUT 진행
C28: └ 40% 비용 점유 | I28: └ 장소 및 재품 보관 개선
I29: TFT팀 투입 및 집중 개선 예정
A30: 협력 업체 클레임 | B30: ⊙클레임 저감 ⊙협력사 변제율up | C30: 협력사 LOT 문제 관리 필요 (주요 워스트 협력사) | I30: 주요 문제 선정 (패널티 가감 적용 예정)
C31: └ CKD LOT 문제 증가 | I31: └LOT 및 재발 문제
C32: └ 협력사 LOT 문제 증가 | I32: └ 협력사 일부 품목 추가 이관 예정
A33: ▣ 2026년 협력업체 클레임 - 항목별 세부자료 별도 작성 | Q33: 클레임비 단위 : 천원
A34: 클레임 구분 | C34: 1월 | D34: 2월 | E34: 3월 | F34: 4월 | G34: 5월 | H34: 6월 | I34: 7월 | J34: 8월 | K34: 9월 | L34: 10월 | M34: 11월 | N34: 12월 | Q34: 합계
A35: 품질문제 등록 클레임 | Q35: =SUM(C35:N35) -> 0
A36: 기초불량 신고클레임 | Q36: =SUM(C36:N36) -> 0
A37: 폐기손실 비용클레임 | Q37: =SUM(C37:N37) -> 0
A38: 비가동현황 클레임 | Q38: =SUM(C38:N38) -> 0
A39: 클레임발생 통보 | Q39: =SUM(C39:N39) -> 0
A40: 결품 클레임 | Q40: =SUM(C40:N40) -> 0
A41: 수량착오 클레임 | Q41: =SUM(C41:N41) -> 0
A42: TOTAL | C42: =SUM(C35:C41) -> 0 | D42: =SUM(D35:D41) -> 0 | E42: =SUM(E35:E41) -> 0 | F42: =SUM(F35:F41) -> 0 | G42: =SUM(G35:G41) -> 0 | H42: =SUM(H35:H41) -> 0 | I42: =SUM(I35:I41) -> 0 | J42: =SUM(J35:J41) -> 0 | ... N42: =SUM(N35:N41) -> 0 | Q42: =SUM(C42:N42) -> 0

Sheet Sheet1

Sheet 항공물류
A1: 1. 2024년 항공물류 발생 현황 | O1: 단위 : 백만원
A2: 구 분 | C2: 1월 | D2: 2월 | E2: 3월 | F2: 4월 | G2: 5월 | H2: 6월 | I2: 7월 | J2: 8월 | K2: 9월 | L2: 10월 | M2: 11월 | N2: 12월 | O2: 누적
A3: 매출액(백만원) | C3: ='월계획 '!H112/1000 -> 8161.5523 | D3: ='월계획 '!I112/1000 -> 8923.5955 | E3: ='월계획 '!J112/1000 -> 0 | F3: ='월계획 '!K112/1000 -> 0 | G3: ='월계획 '!L112/1000 -> 0 | H3: ='월계획 '!M112/1000 -> 0 | I3: ='월계획 '!N112/1000 -> 0 | J3: ='월계획 '!O112/1000 -> 0 | ... N3: ='월계획 '!S112/1000 -> 0 | O3: =SUM(C3:N3) -> 17085.148
A4: 발생금액 | B4: 고객 귀책 | C4: =C16/1000000 -> 0 | D4: =D16/1000000 -> 0 | E4: =E16/1000000 -> 0 | F4: =F16/1000000 -> 0 | G4: =G16/1000000 -> 0 | H4: =H16/1000000 -> 0 | O4: =SUM(C4:N4) -> 0
B5: 법인 귀책 | O5: =SUM(C5:N5) -> 0
B6: 협력사 귀책 | O6: =SUM(C6:N6) -> 0
B7: 합 계 | C7: =SUM(C4:C6) -> 0 | D7: =SUM(D4:D6) -> 0 | E7: =SUM(E4:E6) -> 0 | F7: =SUM(F4:F6) -> 0 | G7: =SUM(G4:G6) -> 0 | H7: =SUM(H4:H6) -> 0 | I7: =SUM(I4:I6) -> 0 | J7: =SUM(J4:J6) -> 0 | ... N7: =SUM(N4:N6) -> 0 | O7: =SUM(C7:N7) -> 0
A8: 회수금액 | B8: 고객 귀책 | C8: =C17/1000000 -> 0 | D8: =D17/1000000 -> 0 | E8: =E17/1000000 -> 0 | F8: =F17/1000000 -> 0 | G8: =G17/1000000 -> 0 | H8: =H17/1000000 -> 0 | O8: =SUM(C8:N8) -> 0
B9: 법인 귀책 | O9: =SUM(C9:N9) -> 0
B10: 협력사 귀책 | O10: =SUM(C10:N10) -> 0
B11: 합 계 | C11: =SUM(C8:C10) -> 0 | D11: =SUM(D8:D10) -> 0 | E11: =SUM(E8:E10) -> 0 | F11: =SUM(F8:F10) -> 0 | G11: =SUM(G8:G10) -> 0 | H11: =SUM(H8:H10) -> 0 | I11: =SUM(I8:I10) -> 0 | J11: =SUM(J8:J10) -> 0 | ... N11: =SUM(N8:N10) -> 0 | O11: =SUM(C11:N11) -> 0

Sheet 불용재고
A1: 1. 2024년 불용재고 보유 현황 | O1: 단위 : 백만원
A2: 구 분 | C2: 1월 | D2: 2월 | E2: 3월 | F2: 4월 | G2: 5월 | H2: 6월 | I2: 7월 | J2: 8월 | K2: 9월 | L2: 10월 | M2: 11월 | N2: 12월 | O2: 누적
A3: 매출액(백만원) | C3: ='월계획 '!H112/1000 -> 8161.5523 | D3: ='월계획 '!I112/1000 -> 8923.5955 | E3: ='월계획 '!J112/1000 -> 0 | F3: ='월계획 '!K112/1000 -> 0 | G3: ='월계획 '!L112/1000 -> 0 | H3: ='월계획 '!M112/1000 -> 0 | I3: ='월계획 '!N112/1000 -> 0 | J3: ='월계획 '!O112/1000 -> 0 | ... N3: ='월계획 '!S112/1000 -> 0 | O3: =SUM(C3:N3) -> 17085.148
A4: 차종 단산 | B4: 재고 금액
B5: 회수 금액
B6: 폐기 금액
B7: 기 타
B8: 합 계 | C8: =C4-C5-C6-C7 -> 0 | D8: =D4-D5-D6-D7 -> 0 | E8: =E4-E5-E6-E7 -> 0 | F8: =F4-F5-F6-F7 -> 0 | G8: =G4-G5-G6-G7 -> 0 | H8: =H4-H5-H6-H7 -> 0 | I8: =I4-I5-I6-I7 -> 0 | J8: =J4-J5-J6-J7 -> 0 | ... O8: =O4-O5-O6-O7 -> 0
A9: EO 변경 | B9: 재고 금액
B10: 회수 금액
B11: 폐기 금액
B12: 기 타
B13: 합 계 | C13: =C9-C10-C11-C12 -> 0 | D13: =D9-D10-D11-D12 -> 0 | E13: =E9-E10-E11-E12 -> 0 | F13: =F9-F10-F11-F12 -> 0 | G13: =G9-G10-G11-G12 -> 0 | H13: =H9-H10-H11-H12 -> 0 | I13: =I9-I10-I11-I12 -> 0 | J13: =J9-J10-J11-J12 -> 0 | ... O13: =O9-O10-O11-O12 -> 0
A14: 발주 오류 | B14: 재고 금액
B15: 회수 금액
B16: 폐기 금액
B17: 기 타
B18: 합 계 | C18: =C14-C15-C16-C17 -> 0 | D18: =D14-D15-D16-D17 -> 0 | E18: =E14-E15-E16-E17 -> 0 | F18: =F14-F15-F16-F17 -> 0 | G18: =G14-G15-G16-G17 -> 0 | H18: =H14-H15-H16-H17 -> 0 | I18: =I14-I15-I16-I17 -> 0 | J18: =J14-J15-J16-J17 -> 0 | ... O18: =O14-O15-O16-O17 -> 0
A19: 사양 삭제 | B19: 재고 금액
B20: 회수 금액
B21: 폐기 금액
B22: 기 타
B23: 합 계 | C23: =C19-C20-C21-C22 -> 0 | D23: =D19-D20-D21-D22 -> 0 | E23: =E19-E20-E21-E22 -> 0 | F23: =F19-F20-F21-F22 -> 0 | G23: =G19-G20-G21-G22 -> 0 | H23: =H19-H20-H21-H22 -> 0 | I23: =I19-I20-I21-I22 -> 0 | J23: =J19-J20-J21-J22 -> 0 | ... O23: =O19-O20-O21-O22 -> 0

Sheet 3자검사
A1: 1. 2026년 3자검사 발생 현황 | O1: 단위 : 백만원
A2: 구 분 | C2: 1월 | D2: 2월 | E2: 3월 | F2: 4월 | G2: 5월 | H2: 6월 | I2: 7월 | J2: 8월 | K2: 9월 | L2: 10월 | M2: 11월 | N2: 12월 | O2: 누적
A3: 매출액(백만원) | C3: ='클레임&폐기비'!C3 -> 6487.2919 | D3: ='클레임&폐기비'!D3 -> 7070.0825 | E3: ='클레임&폐기비'!E3 -> 7235 | F3: ='클레임&폐기비'!F3 -> 7467.9447 | G3: ='클레임&폐기비'!G3 -> 0 | H3: ='클레임&폐기비'!H3 -> 0 | I3: ='클레임&폐기비'!I3 -> 0 | J3: ='클레임&폐기비'!J3 -> 0 | ... N3: ='클레임&폐기비'!N3 -> 0 | O3: =SUM(C3:N3) -> 28260.319
A4: 발생금액 | B4: 고객 귀책 | O4: =SUM(C4:N4) -> 0
B5: 법인 귀책 | O5: =SUM(C5:N5) -> 0
B6: 협력사 귀책 | O6: =SUM(C6:N6) -> 0
B7: 합 계 | C7: =SUM(C4:C6) -> 0 | D7: =SUM(D4:D6) -> 0 | E7: =SUM(E4:E6) -> 0 | F7: =SUM(F4:F6) -> 0 | G7: =SUM(G4:G6) -> 0 | H7: =SUM(H4:H6) -> 0 | I7: =SUM(I4:I6) -> 0 | J7: =SUM(J4:J6) -> 0 | ... N7: =SUM(N4:N6) -> 0 | O7: =SUM(C7:N7) -> 0
A8: 회수금액 | B8: 고객 귀책 | O8: =SUM(C8:N8) -> 0
B9: 법인 귀책 | O9: =SUM(C9:N9) -> 0
B10: 협력사 귀책 | O10: =SUM(C10:N10) -> 0
B11: 합 계 | C11: =SUM(C8:C10) -> 0 | D11: =SUM(D8:D10) -> 0 | E11: =SUM(E8:E10) -> 0 | F11: =SUM(F8:F10) -> 0 | G11: =SUM(G8:G10) -> 0 | H11: =SUM(H8:H10) -> 0 | I11: =SUM(I8:I10) -> 0 | J11: =SUM(J8:J10) -> 0 | ... N11: =SUM(N8:N10) -> 0 | O11: =SUM(C11:N11) -> 0

Sheet 원가절감
A1: ■ 원가절감 실적 및 계획
A3: 1. 2024년 계획(상반기 70% 이상 달성목표) | I3: (금액단위 : 백만원)
A5: 항목 | B5: 2023년 실적 | E5: 2024년 계획 | H5: 연초계획 | J5: 완료실적 | L5: 수정계획 | N5: 연초 계획대비 미달성 대책
B6: 년간목표 | C6: 완료실적 | D6: 달성율 | E6: 년간목표 | F6: 요약내용 | G6: 팀 | H6: 예정월 | I6: 예상효과 | J6: 완료월 | K6: 인정실적 | L6: 수정월 | M6: 수정금액
A7: 재료비 | F7: 84443-BV000 BRKT-SUPT COWL PNL MT'G(SU2I) 금형 공정개선 | G7: 기술 | H7: 3월 | I7: 30.5
F8: 89329/429-K6010 FR BRKT-RR BACK SIDE HINGE,LH/RH(AI3) 금형 공정개선 | G8: 기술 | H8: 3월 | I8: 75.5 | J8: 2월 | K8: 25.766
F9: 84424-K6910 BRKT BRAKE STOPPER LINK(AI3) 금형 공정개선 | G9: 기술 | H9: 3월 | I9: 12.7
F10: 84469-BV000 BRKT-C/PAD MT'G CTR LWR, PASS(PS7I) 금형 공정개선 | G10: 기술 | H10: 3월 | I10: 12.1
F11: 89328/428-K6010 BRKT - RR BACK SIDE HINGE,LH/RH(AI3) 금형 공정개선 | G11: 기술 | H11: 3월 | I11: 57
B12: 777.6 | C12: 454.707 | D12: =C12/B12 -> 0.58475694 | E12: =SUM(I7:I22) -> 1066.5 | F12: 84415-K6000 BRKT-S/COLUMN UNIT HINGE MTG(AI3) 금형 공정개선 | G12: 기술 | H12: 9월 | I12: 10.8
F13: X89336-K6010 BRKT - RR CTR HINGE, RR(AI3) 금형 공정개선 | G13: 기술 | H13: 9월 | I13: 29.4
F14: 84424-K6920 BRAKE STOPPER(AI3) 금형 공정개선 | G14: 기술 | H14: 9월 | I14: 21
F15: 84447-BV000 BRKT - COWL PNL RR MT'G, REINF(SU2I) 금형 공정개선 | G15: 기술 | H15: 7월 | I15: 12.5
F16: 사급원자재 시중구매 차액 | G16: 자재 | H16: 1월 | I16: 300 | J16: 1월 | K16: 316.102
F17: SU2i 렛치 앗세이 현지화 | G17: 자재 | H17: 9월 | I17: 200
F18: 하드웨어 자재 Nut, Bolt, Rivet 류 현지화 | G18: 개발 | H18: 3월 | I18: 62
F19: QXI SBR Cush 단가 인상(QXI Cush 단가 동일하게 적용) | G19: 개발 | H19: 3월 | I19: 32
F20: 추가 발굴 | G20: 개발 | H20: 7월 | I20: 211
A23: 직접노무비 | F23: 84420-K6010 BRKT-PASS C/PAD MTG(AI3) 금형 공정개선 | G23: 기술 | H23: 3월 | I23: 5.5
F24: 84419-K6010 BRKT-DRV C/PAD MTG UPR(AI3) 금형 공정개선 | G24: 기술 | H24: 3월 | I24: 4.8
F25: 84421-K6010 BRKT-HVAC CTR MTG(AI3) 금형 공정개선 | G25: 기술 | H25: 3월 | I25: 8.6
F26: 84422-K6010 BRKT-C/PAD DRV MTG,CTR(AI3) 금형 공정개선 | G26: 기술 | H26: 3월 | I26: 7.1 | J26: 2월 | K26: 5.677
F27: 84485-BV000 BRKT-PIPE REINF 금형 공정개선 | G27: 기술 | H27: 3월 | I27: 3.6
B28: 131.5 | C28: 21.256 | D28: =C28/B28 -> 0.16164259 | E28: =SUM(I23:I36) -> 101.6 | F28: 31541-SU2IO CUSH DIVE MTG BRKT(PS7I) 금형 공정개선 | G28: 기술 | H28: 9월 | I28: 9
F29: SAB, Seat belt 사급관리비 인상 적용 1%=>4% | G29: 개발 | H29: 1월 | I29: 13
F30: 직접인원 축소 | G30: 생산 | H30: 7월 | I30: 50
A37: 간접노무비 | F37: 간접인원 축소 | G37: 품질 | H37: 7월 | I37: 10
B39: 35.116398 | D39: =C39/B39 -> 0 | E39: =SUM(I37:I41) -> 10
A42: 경비 | F42: AI3 CCB 5차 신규공정 범용설비재활용(유휴설비 재활용) | G42: 기술 | H42: 3월 | I42: 30.7
F43: SU2I FSB 설비 재활용 CO2로보트&부스 2대(유휴설비 재활용) | G43: 기술 | H43: 7월 | I43: 30
F44: KM seat(2공장), DSA(4공장) 관세 벌금 납부 금액 환수 | G44: 자재 | H44: 3월 | I44: 65
F45: 트랜시스 결제대금 일정변경에 따른 현금확보액, 대출 상환으로 인한 이자 비용감소 | G45: 회계 | H45: 3월 | I45: 250
F46: 청소인원 급여 카테고리 변경 | G46: 인사 | H46: 7월 | I46: 15
B48: 579 | C48: 181.626 | D48: =C48/B48 -> 0.31368912 | E48: =SUM(I42:I55) -> 390.7
A56: 합 계 | B56: =SUM(B7:B55) -> 1523.2164 | C56: =SUM(C7:C55) -> 657.589 | D56: =C56/B56 -> 0.43171082 | E56: =SUM(E7:E55) -> 1568.8 | I56: =SUM(I7:I55) -> 1568.8 | K56: =SUM(K7:K55) -> 347.545 | M56: =SUM(M7:M55) -> 0
K59: 구분 | L59: 1월 | M59: 2월 | N59: 3월 | O59: 4월 | P59: 5월 | Q59: 6월 | R59: 7월 | S59: 8월 | T59: 9월 | U59: 10월 | V59: 11월 | W59: 12월 | X59: 합계
K60: 재료비 절감 | L60: =SUMIF($H$7:$H$22,L59,$I$7:$I$22) -> 300 | M60: =SUMIF($H$7:$H$22,M59,$I$7:$I$22) -> 0 | N60: =SUMIF($H$7:$H$22,N59,$I$7:$I$22) -> 281.8 | O60: =SUMIF($H$7:$H$22,O59,$I$7:$I$22) -> 0 | P60: =SUMIF($H$7:$H$22,P59,$I$7:$I$22) -> 0 | Q60: =SUMIF($H$7:$H$22,Q59,$I$7:$I$22) -> 0 | R60: =SUMIF($H$7:$H$22,R59,$I$7:$I$22) -> 223.5 | S60: =SUMIF($H$7:$H$22,S59,$I$7:$I$22) -> 0 | ... W60: =SUMIF($H$7:$H$22,W59,$I$7:$I$22) -> 0 | X60: =SUM(L60:W60) -> 1066.5
K61: 직접노무비 절감 | L61: =SUMIF(H23:$H$36,L59,$I$23:$I$36) -> 13 | M61: =SUMIF($H23:I$36,M59,$I$23:$I$36) -> 0 | N61: =SUMIF($H23:I$36,N59,$I$23:$I$36) -> 29.6 | O61: =SUMIF($H23:J$36,O59,$I$23:$I$36) -> 0 | P61: =SUMIF($H23:K$36,P59,$I$23:$I$36) -> 0 | Q61: =SUMIF($H23:L$36,Q59,$I$23:$I$36) -> 0 | R61: =SUMIF($H23:M$36,R59,$I$23:$I$36) -> 50 | S61: =SUMIF($H23:N$36,S59,$I$23:$I$36) -> 0 | T61: =SUMIF($H23:O$36,T59,$I$23:$I$36) -> 9 | U61: =SUMIF($H23:P$36,U59,$I$23:$I$36) -> 0 | V61: =SUMIF($H23:Q$36,V59,$I$23:$I$36) -> 0 | W61: =SUMIF($H23:T$36,W59,$I$23:$I$36) -> 0 | X61: =SUM(L61:W61) -> 101.6
K62: 간접노무비 절감 | L62: =SUMIF(H37:$H$41,L59,$I$37:$I$41) -> 0 | M62: =SUMIF($H37:I$41,M59,$I$37:$I$41) -> 0 | N62: =SUMIF($H37:I$41,N59,$I$37:$I$41) -> 0 | O62: =SUMIF($H37:J$41,O59,$I$37:$I$41) -> 0 | P62: =SUMIF($H37:K$41,P59,$I$37:$I$41) -> 0 | Q62: =SUMIF($H37:L$41,Q59,$I$37:$I$41) -> 0 | R62: =SUMIF($H37:M$41,R59,$I$37:$I$41) -> 10 | S62: =SUMIF($H37:N$41,S59,$I$37:$I$41) -> 0 | T62: =SUMIF($H37:O$41,T59,$I$37:$I$41) -> 0 | U62: =SUMIF($H37:P$41,U59,$I$37:$I$41) -> 0 | V62: =SUMIF($H37:Q$41,V59,$I$37:$I$41) -> 0 | W62: =SUMIF($H37:T$41,W59,$I$37:$I$41) -> 0 | X62: =SUM(L62:W62) -> 10
K63: 경비 절감 | L63: =SUMIF(H42:$H$55,L59,$I$42:$I$55) -> 0 | M63: =SUMIF($H42:I$55,M59,$I$42:$I$55) -> 0 | N63: =SUMIF($H42:I$55,N59,$I$42:$I$55) -> 345.7 | O63: =SUMIF($H42:J$55,O59,$I$42:$I$55) -> 0 | P63: =SUMIF($H42:K$55,P59,$I$42:$I$55) -> 0 | Q63: =SUMIF($H42:L$55,Q59,$I$42:$I$55) -> 0 | R63: =SUMIF($H42:O$55,R59,$I$42:$I$55) -> 45 | S63: =SUMIF($H42:P$55,S59,$I$42:$I$55) -> 0 | T63: =SUMIF($H42:Q$55,T59,$I$42:$I$55) -> 0 | U63: =SUMIF($H42:R$55,U59,$I$42:$I$55) -> 0 | V63: =SUMIF($H42:S$55,V59,$I$42:$I$55) -> 0 | W63: =SUMIF($H42:T$55,W59,$I$42:$I$55) -> 0 | X63: =SUM(L63:W63) -> 390.7
K64: 합계 | L64: =SUM(L60:L63) -> 313 | M64: =SUM(M60:M63) -> 0 | N64: =SUM(N60:N63) -> 657.1 | O64: =SUM(O60:O63) -> 0 | P64: =SUM(P60:P63) -> 0 | Q64: =SUM(Q60:Q63) -> 0 | R64: =SUM(R60:R63) -> 328.5 | S64: =SUM(S60:S63) -> 0 | ... W64: =SUM(W60:W63) -> 0 | X64: =SUM(L64:W64) -> 1568.8
K67: 구분 | L67: 1월 | M67: 2월 | N67: 3월 | O67: 4월 | P67: 5월 | Q67: 6월 | R67: 7월 | S67: 8월 | T67: 9월 | U67: 10월 | V67: 11월 | W67: 12월 | X67: 합계
K68: 재료비 절감 | L68: =SUMIF($J$7:$J$22,L67,$K$7:$K$22) -> 316.102 | M68: =SUMIF($J$7:$J$22,M67,$K$7:$K$22) -> 25.766 | N68: =SUMIF($J$7:$J$22,N67,$K$7:$K$22) -> 0 | O68: =SUMIF($J$7:$J$22,O67,$K$7:$K$22) -> 0 | P68: =SUMIF($J$7:$J$22,P67,$K$7:$K$22) -> 0 | Q68: =SUMIF($J$7:$J$22,Q67,$K$7:$K$22) -> 0 | R68: =SUMIF($J$7:$J$22,R67,$K$7:$K$22) -> 0 | S68: =SUMIF($J$7:$J$22,S67,$K$7:$K$22) -> 0 | ... W68: =SUMIF($J$7:$J$22,W67,$K$7:$K$22) -> 0 | X68: =SUM(L68:W68) -> 341.868
K69: 직접노무비 절감 | L69: =SUMIF($J$23:$J$36,L67,$K$23:$K$36) -> 0 | M69: =SUMIF($J$23:$J$36,M67,$K$23:$K$36) -> 5.677 | N69: =SUMIF($J$23:$J$36,N67,$K$23:$K$36) -> 0 | O69: =SUMIF($J$23:$J$36,O67,$K$23:$K$36) -> 0 | P69: =SUMIF($J$23:$J$36,P67,$K$23:$K$36) -> 0 | Q69: =SUMIF($J$23:$J$36,Q67,$K$23:$K$36) -> 0 | R69: =SUMIF($J$23:$J$36,R67,$K$23:$K$36) -> 0 | S69: =SUMIF($J$23:$J$36,S67,$K$23:$K$36) -> 0 | ... W69: =SUMIF($J$23:$J$36,W67,$K$23:$K$36) -> 0 | X69: =SUM(L69:W69) -> 5.677
K70: 간접노무비 절감 | L70: =SUMIF($J$37:$J$41,L67,$K$37:$K$41) -> 0 | M70: =SUMIF($J$37:$J$41,M67,$K$37:$K$41) -> 0 | N70: =SUMIF($J$37:$J$41,N67,$K$37:$K$41) -> 0 | O70: =SUMIF($J$37:$J$41,O67,$K$37:$K$41) -> 0 | P70: =SUMIF($J$37:$J$41,P67,$K$37:$K$41) -> 0 | Q70: =SUMIF($J$37:$J$41,Q67,$K$37:$K$41) -> 0 | R70: =SUMIF($J$37:$J$41,R67,$K$37:$K$41) -> 0 | S70: =SUMIF($J$37:$J$41,S67,$K$37:$K$41) -> 0 | ... W70: =SUMIF($J$37:$J$41,W67,$K$37:$K$41) -> 0 | X70: =SUM(L70:W70) -> 0
K71: 경비 절감 | L71: =SUMIF($J$42:$J$55,L67,$K$42:$K$55) -> 0 | M71: =SUMIF($J$42:$J$55,M67,$K$42:$K$55) -> 0 | N71: =SUMIF($J$42:$J$55,N67,$K$42:$K$55) -> 0 | O71: =SUMIF($J$42:$J$55,O67,$K$42:$K$55) -> 0 | P71: =SUMIF($J$42:$J$55,P67,$K$42:$K$55) -> 0 | Q71: =SUMIF($J$42:$J$55,Q67,$K$42:$K$55) -> 0 | R71: =SUMIF($J$42:$J$55,R67,$K$42:$K$55) -> 0 | S71: =SUMIF($J$42:$J$55,S67,$K$42:$K$55) -> 0 | ... W71: =SUMIF($J$42:$J$55,W67,$K$42:$K$55) -> 0 | X71: =SUM(L71:W71) -> 0
K72: 합계 | L72: =SUM(L68:L71) -> 316.102 | M72: =SUM(M68:M71) -> 31.443 | N72: =SUM(N68:N71) -> 0 | O72: =SUM(O68:O71) -> 0 | P72: =SUM(P68:P71) -> 0 | Q72: =SUM(Q68:Q71) -> 0 | R72: =SUM(R68:R71) -> 0 | S72: =SUM(S68:S71) -> 0 | ... W72: =SUM(W68:W71) -> 0 | X72: =SUM(L72:W72) -> 347.545
K77: ■ 부서별 24년 원가절감 계획
K79: 부서별 | L79: 항목 | R79: 내용 | W79: 시행월 | X79: 백만원
K80: 인사총무 | L80: 간접 노무비 | N80: =F46 -> 청소인원 급여 카테고리 변경 | W80: =H46 -> 7월 | X80: =I46 -> 15
N83: 소계 | X83: =SUM(X80:X82) -> 15
L84: 경비
N87: 소계 | X87: =SUM(X84:X86) -> 0
N88: 인사총무 총계 | X88: =X83+X87 -> 15
K89: 재경팀 | L89: 간접 노무비
N92: 소계 | X92: =SUM(X89:X91) -> 0
L93: 경비 | N93: =F45 -> 트랜시스 결제대금 일정변경에 따른 현금확보액, 대출 상환으로 인한 이자 비용감소 | W93: =H45 -> 3월 | X93: =I45 -> 250
N96: 소계 | X96: =SUM(X93:X95) -> 250
N97: 재경팀 총계 | X97: =X92+X96 -> 250
K98: 영업팀 | L98: 재료비
N101: 소계 | X101: =SUM(X98:X100) -> 0
L102: 직접노무비
N105: 소계 | X105: =SUM(X102:X104) -> 0
L106: 경비
N109: 소계 | X109: =SUM(X106:X108) -> 0
N110: 영업팀 총계 | X110: =X101+X109+X105 -> 0
K111: 자재팀 | L111: 재료비 | N111: =F16 -> 사급원자재 시중구매 차액 | W111: =H16 -> 1월 | X111: =I16 -> 300
N112: =F17 -> SU2i 렛치 앗세이 현지화 | W112: =H17 -> 9월 | X112: =I17 -> 200
N114: 소계 | X114: =SUM(X111:X113) -> 500
L115: 직접노무비
N118: 소계 | X118: =SUM(X115:X117) -> 0
L119: 경비 | N119: =F44 -> KM seat(2공장), DSA(4공장) 관세 벌금 납부 금액 환수 | W119: =H44 -> 3월 | X119: =I44 -> 65
N122: 소계 | X122: =SUM(X119:X121) -> 65
N123: 자재팀 총계 | X123: =X114+X122+X118 -> 565
K124: 개발팀 | L124: 재료비 | N124: =F18 -> 하드웨어 자재 Nut, Bolt, Rivet 류 현지화 | W124: =H18 -> 3월 | X124: =I18 -> 62
N125: =F19 -> QXI SBR Cush 단가 인상(QXI Cush 단가 동일하게 적용) | W125: =H19 -> 3월 | X125: =I19 -> 32
N126: =F20 -> 추가 발굴 | W126: =H20 -> 7월 | X126: =I20 -> 211
N129: 소계 | X129: =SUM(X124:X128) -> 305
L130: 직접노무비 | N130: =F29 -> SAB, Seat belt 사급관리비 인상 적용 1%=>4% | W130: =H29 -> 1월 | X130: =I29 -> 13
N133: 소계 | X133: =SUM(X130:X132) -> 13
L134: 경비
N137: 소계 | X137: =SUM(X134:X136) -> 0
N138: 개발팀 총계 | X138: =X129+X137+X133 -> 318
K139: 생관/생산팀 | L139: 재료비
N145: 소계 | X145: =SUM(X139:X144) -> 0
L146: 직접노무비 | N146: =F30 -> 직접인원 축소 | W146: =H30 -> 7월 | X146: =I30 -> 50
N149: 소계 | X149: =SUM(X146:X148) -> 50
L150: 경비
N153: 소계 | X153: =SUM(X150:X152) -> 0
N154: 생관/생산팀 총계 | X154: =X145+X153+X149 -> 50
L155: 재료비 | N155: =F7 -> 84443-BV000 BRKT-SUPT COWL PNL MT'G(SU2I) 금형 공정개선 | W155: =H7 -> 3월 | X155: =I7 -> 30.5
N156: =F8 -> 89329/429-K6010 FR BRKT-RR BACK SIDE HINGE,LH/RH(AI3) 금형 공정개선 | W156: =H8 -> 3월 | X156: =I8 -> 75.5
N157: =F9 -> 84424-K6910 BRKT BRAKE STOPPER LINK(AI3) 금형 공정개선 | W157: =H9 -> 3월 | X157: =I9 -> 12.7
N158: =F10 -> 84469-BV000 BRKT-C/PAD MT'G CTR LWR, PASS(PS7I) 금형 공정개선 | W158: =H10 -> 3월 | X158: =I10 -> 12.1
N159: =F11 -> 89328/428-K6010 BRKT - RR BACK SIDE HINGE,LH/RH(AI3) 금형 공정개선 | W159: =H11 -> 3월 | X159: =I11 -> 57
N160: =F12 -> 84415-K6000 BRKT-S/COLUMN UNIT HINGE MTG(AI3) 금형 공정개선 | W160: =H12 -> 9월 | X160: =I12 -> 10.8
N161: =F13 -> X89336-K6010 BRKT - RR CTR HINGE, RR(AI3) 금형 공정개선 | W161: =H13 -> 9월 | X161: =I13 -> 29.4
N162: =F14 -> 84424-K6920 BRAKE STOPPER(AI3) 금형 공정개선 | W162: =H14 -> 9월 | X162: =I14 -> 21
N163: =F15 -> 84447-BV000 BRKT - COWL PNL RR MT'G, REINF(SU2I) 금형 공정개선 | W163: =H15 -> 7월 | X163: =I15 -> 12.5
N165: 소계 | X165: =SUM(X155:X164) -> 261.5
...

Sheet 손익계산서
B2: 손익계산서 Statements of Profit or Loss
B3: Year ended 31.03.2024
B5: Daechang India Seat Pvt. Ltd. | Q5: (Unit : Rs)
B6: 과 목 | C6: Account | D6: Note | E6: This Month(Jan.) | F6: This Month(Feb.) | G6: This Month(Mar.) | H6: This Month(Apr.) | I6: This Month(May) | J6: This Month(Jun.) | K6: This Month(Jul.) | L6: This Month(Aug.) | M6: This Month(Sep.) | N6: This Month(Oct.) | O6: This Month(Nov.) | P6: This Month(Dec.) | Q6: Accumulated
B7: Ⅰ. 매출액 | C7: Ⅰ. Sales | E7: =SUM(E8:E10) -> 5.1009702e+08 | F7: =SUM(F8:F10) -> 5.5772472e+08 | G7: =SUM(G8:G10) -> 0 | H7: =SUM(H8:H10) -> 0 | I7: =SUM(I8:I10) -> 0 | J7: =SUM(J8:J10) -> 0 | K7: =SUM(K8:K10) -> 0 | L7: =SUM(L8:L10) -> 0 | ... Q7: =SUM(Q8:Q10) -> 1.0678217e+09
B8: (1) 제품매출 | C8: (1) Sales-finished goods | E8: =IS!G11 -> 5.1009702e+08 | F8: =IS!O11 -> 5.5772472e+08 | G8: =IS!W11 -> 0 | H8: =IS!AE11 -> 0 | I8: =IS!AM11 -> 0 | J8: =IS!AU11 -> 0 | K8: =IS!BC11 -> 0 | L8: =IS!BK11 -> 0 | M8: =IS!BS11 -> 0 | N8: =IS!CA11 -> 0 | O8: =IS!CI11 -> 0 | P8: =IS!CQ11 -> 0 | Q8: =SUM(E8:P8) -> 1.0678217e+09
B9: (2) 상품매출 | C9: (2) Sales-merchandises | Q9: =SUM(E9:P9) -> 0
B10: (3) 용역매출 | C10: (3) Sales-services | Q10: =SUM(E10:P10) -> 0
B11: Ⅱ. 매출원가 | C11: Ⅱ. Cost of sales | E11: =E12+E18+E24 -> 4.2225064e+08 | F11: =F12+F18+F24 -> 4.4773818e+08 | G11: =G12+G18+G24 -> 0 | H11: =H12+H18+H24 -> 0 | I11: =I12+I18+I24 -> 0 | J11: =J12+J18+J24 -> 0 | K11: =K12+K18+K24 -> 0 | L11: =L12+L18+L24 -> 0 | ... Q11: =Q12+Q18+Q24 -> 8.6998882e+08
B12: (1) 제품매출원가 | C12: (1) Cost of finished goods sales | E12: =E13+E14-E17 -> 4.2225064e+08 | F12: =F13+F14-F17 -> 4.4773818e+08 | G12: =G13+G14-G17 -> 0 | H12: =H13+H14-H17 -> 0 | I12: =I13+I14-I17 -> 0 | J12: =J13+J14-J17 -> 0 | K12: =K13+K14-K17 -> 0 | L12: =L13+L14-L17 -> 0 | ... Q12: =Q13+Q14-Q17 -> 8.6998882e+08
B13: 기초제품재고액 | C13: Beginning inventory of finished goods | E13: =제조원가명세서!E9 -> 201520109 | F13: =제조원가명세서!F9 -> 200086662 | G13: =제조원가명세서!G9 -> 199242762 | H13: =제조원가명세서!H9 -> 0 | I13: =제조원가명세서!I9 -> 0 | J13: =제조원가명세서!J9 -> 0 | K13: =제조원가명세서!K9 -> 0 | L13: =제조원가명세서!L9 -> 0 | ... Q13: =제조원가명세서!Q9 -> 201520109
B14: 당기제품제조원가 | C14: Cost of finished goods during the year | E14: =제조원가명세서!E10+제조원가명세서!E15 -> 4.2081719e+08 | F14: =제조원가명세서!F10+제조원가명세서!F15 -> 4.4689428e+08 | G14: =제조원가명세서!G10+제조원가명세서!G15 -> 0 | H14: =제조원가명세서!H10+제조원가명세서!H15 -> 0 | I14: =제조원가명세서!I10+제조원가명세서!I15 -> 0 | J14: =제조원가명세서!J10+제조원가명세서!J15 -> 0 | K14: =제조원가명세서!K10+제조원가명세서!K15 -> 0 | L14: =제조원가명세서!L10+제조원가명세서!L15 -> 0 | ... Q14: =제조원가명세서!Q10+제조원가명세서!Q15 -> 8.6771148e+08
B15: 관세환급금 | C15: Customs duty refunds
B16: 타계정으로대체액 | C16: Transfered to other accounts
B17: 기말제품재고액 | C17: Ending inventory of finished goods | E17: =제조원가명세서!E12 -> 200086662 | F17: =제조원가명세서!F12 -> 199242762 | G17: =제조원가명세서!G12 -> 199242762 | H17: =제조원가명세서!H12 -> 0 | I17: =제조원가명세서!I12 -> 0 | J17: =제조원가명세서!J12 -> 0 | K17: =제조원가명세서!K12 -> 0 | L17: =제조원가명세서!L12 -> 0 | ... Q17: =제조원가명세서!Q12 -> 199242762
B18: (2) 상품매출원가 | C18: (2) Cost of merchandises sales | E18: =SUM(E19:E24) -> 0 | F18: =SUM(F19:F24) -> 0 | G18: =SUM(G19:G24) -> 0 | H18: =SUM(H19:H24) -> 0 | I18: =SUM(I19:I24) -> 0 | J18: =SUM(J19:J24) -> 0 | K18: =SUM(K19:K24) -> 0 | L18: =SUM(L19:L24) -> 0 | ... Q18: =SUM(Q19:Q24) -> 0
B19: 기초상품재고액 | C19: Beginning Inventory of merchandises | Q19: =SUM(E19:P19) -> 0
B20: 당기상품매입액 | C20: Purchase of Merchandises during the year | Q20: =SUM(E20:P20) -> 0
B21: 관세환급금 | C21: Customs duty refunds | Q21: =SUM(E21:P21) -> 0
B22: 타계정으로대체액 | C22: Transfered to other accounts | Q22: =SUM(E22:P22) -> 0
B23: 기말상품재고액 | C23: Ending inventory of merchandises | Q23: =SUM(E23:P23) -> 0
B24: (3) 용역매출원가 | C24: (3) Cost of services sales | Q24: =SUM(E24:P24) -> 0
B25: Ⅲ. 매출총이익(손실) | C25: Ⅲ. Gross profit(loss) | E25: =E7-E11 -> 87846379 | F25: =F7-F11 -> 1.0998653e+08 | G25: =G7-G11 -> 0 | H25: =H7-H11 -> 0 | I25: =I7-I11 -> 0 | J25: =J7-J11 -> 0 | K25: =K7-K11 -> 0 | L25: =L7-L11 -> 0 | ... Q25: =Q7-Q11 -> 1.9783291e+08
B26: Ⅳ. 판매비와관리비 | C26: Ⅳ. Selling and administrative expenses | E26: =SUM(E27:E51) -> 64407795 | F26: =SUM(F27:F51) -> 63352876 | G26: =SUM(G27:G51) -> 0 | H26: =SUM(H27:H51) -> 0 | I26: =SUM(I27:I51) -> 0 | J26: =SUM(J27:J51) -> 0 | K26: =SUM(K27:K51) -> 0 | L26: =SUM(L27:L51) -> 0 | ... Q26: =SUM(Q27:Q51) -> 1.2776067e+08
B27: 급여 | C27: Salaries | D27: Labor Costs | E27: =IS!G29 -> 20373489 | F27: =IS!O29 -> 19718460 | G27: =IS!W29 -> 0 | H27: =IS!AE29 -> 0 | I27: =IS!AM29 -> 0 | J27: =IS!AU29 -> 0 | K27: =IS!BC29 -> 0 | L27: =IS!BK29 -> 0 | M27: =IS!BS29 -> 0 | N27: =IS!CA29 -> 0 | O27: =IS!CI29 -> 0 | P27: =IS!CQ29 -> 0 | Q27: =SUM(E27:P27) -> 40091948
B28: 상여금 | C28: Bonuses | Q28: =SUM(E28:P28) -> 0
B29: 잡금 | C29: Miscellaneous Salaries | Q29: =SUM(E29:P29) -> 0
B30: 퇴직급여 | C30: Severance benefits | Q30: =SUM(E30:P30) -> 0
B31: 복리후생비 | C31: Employee benefits | D31: ESIC Account, Food and Beverage Exp Non FBT, Gift & Presentation, Guest House Expenses, Labour Welfare Fund, Pf Account, Staff Welfare, Staff Welfare Korean Staff (Non FBT), Uniform Expenses | E31: =IS!E176 -> 3199206.6 | F31: =IS!F176 -> 3223577.9 | G31: =IS!G176 -> 0 | H31: =IS!H176 -> 0 | I31: =IS!I176 -> 0 | J31: =IS!J176 -> 0 | K31: =IS!K176 -> 0 | L31: =IS!L176 -> 0 | ... P31: =IS!P176 -> 0 | Q31: =SUM(E31:P31) -> 6422784.6
B32: 여비교통비 | C32: Travel expenses | D32: Conveyance Staff, Travelling & Conveyance | E32: =IS!E190 -> 2306965.2 | F32: =IS!F190 -> 2459781.1 | G32: =IS!G190 -> 0 | H32: =IS!H190 -> 0 | I32: =IS!I190 -> 0 | J32: =IS!J190 -> 0 | K32: =IS!K190 -> 0 | L32: =IS!L190 -> 0 | ... P32: =IS!P190 -> 0 | Q32: =SUM(E32:P32) -> 4766746.2
B33: 통신비 | C33: Communication expenses | D33: Telephone & Internet Charges | E33: =IS!E192 -> 23963 | F33: =IS!F192 -> 64004.64 | G33: =IS!G192 -> 0 | H33: =IS!H192 -> 0 | I33: =IS!I192 -> 0 | J33: =IS!J192 -> 0 | K33: =IS!K192 -> 0 | L33: =IS!L192 -> 0 | ... P33: =IS!P192 -> 0 | Q33: =SUM(E33:P33) -> 87967.64
B34: 세금과공과 | C34: Taxes and dues | D34: Registration Exp | Q34: =SUM(E34:P34) -> 0
B35: 지급임차료 | C35: Rent expense | D35: Forklift Charges, Rent Account, Plant rental | E35: =IS!E188+IS!E189 -> 273746 | F35: =IS!F188+IS!F189 -> 244870 | G35: =IS!G188+IS!G189 -> 0 | H35: =IS!H188+IS!H189 -> 0 | I35: =IS!I188+IS!I189 -> 0 | J35: =IS!J188+IS!J189 -> 0 | K35: =IS!K188+IS!K189 -> 0 | L35: =IS!L188+IS!L189 -> 0 | ... P35: =IS!P188+IS!P189 -> 0 | Q35: =SUM(E35:P35) -> 518616
B36: 운반비 | C36: Freight expenses | D36: Freight Charges, Transport Charges | E36: =IS!E183+IS!E184 -> 2928490.4 | F36: =IS!F183+IS!F184 -> 3080445.5 | G36: =IS!G183+IS!G184 -> 0 | H36: =IS!H183+IS!H184 -> 0 | I36: =IS!I183+IS!I184 -> 0 | J36: =IS!J183+IS!J184 -> 0 | K36: =IS!K183+IS!K184 -> 0 | L36: =IS!L183+IS!L184 -> 0 | ... P36: =IS!P183+IS!P184 -> 0 | Q36: =SUM(E36:P36) -> 6008935.9
B37: 전력비 | C37: 0 | D37: Electricity Charges, Generator Exp, | E37: =IS!E177+IS!E178 -> 4236322 | F37: =IS!F177+IS!F178 -> 4020722 | G37: =IS!G177+IS!G178 -> 0 | H37: =IS!H177+IS!H178 -> 0 | I37: =IS!I177+IS!I178 -> 0 | J37: =IS!J177+IS!J178 -> 0 | K37: =IS!K177+IS!K178 -> 0 | L37: =IS!L177+IS!L178 -> 0 | ... P37: =IS!P177+IS!P178 -> 0 | Q37: =SUM(E37:P37) -> 8257044
B38: 차량유지비 | C38: Packaging expenses | D38: Vehicle Maintenance and insurance | E38: =IS!E194 -> 39234 | F38: =IS!F194 -> 272933 | G38: =IS!G194 -> 0 | H38: =IS!H194 -> 0 | I38: =IS!I194 -> 0 | J38: =IS!J194 -> 0 | K38: =IS!K194 -> 0 | L38: =IS!L194 -> 0 | ... P38: =IS!P194 -> 0 | Q38: =SUM(E38:P38) -> 312167
B39: 소모품비 | C39: Supplies expenses | D39: Consumables Exp, House Keeping Expenses, Printing & Stationary | E39: =IS!E185+IS!E186 -> 1427160 | F39: =IS!F185+IS!F186 -> 1056229.8 | G39: =IS!G185+IS!G186 -> 0 | H39: =IS!H185+IS!H186 -> 0 | I39: =IS!I185+IS!I186 -> 0 | J39: =IS!J185+IS!J186 -> 0 | K39: =IS!K185+IS!K186 -> 0 | L39: =IS!L185+IS!L186 -> 0 | ... P39: =IS!P185+IS!P186 -> 0 | Q39: =SUM(E39:P39) -> 2483389.8
B40: 수선비 | C40: Repairs expenses | D40: Factory Maintanance, R&M Computers, Repairs and Maintenance, Tools and spares | E40: =IS!E181+IS!E182 -> 3752869.9 | F40: =IS!F181+IS!F182 -> 4857254.7 | G40: =IS!G181+IS!G182 -> 0 | H40: =IS!H181+IS!H182 -> 0 | I40: =IS!I181+IS!I182 -> 0 | J40: =IS!J181+IS!J182 -> 0 | K40: =IS!K181+IS!K182 -> 0 | L40: =IS!L181+IS!L182 -> 0 | ... P40: =IS!P181+IS!P182 -> 0 | Q40: =SUM(E40:P40) -> 8610124.6
B41: 지급수수료 | C41: Service Fees | D41: Audit Fees, Bank Charges, Export expenses, Postage & Courier, Professional Charges, Subscription, Testing charges, Visa Expenses, | E41: =IS!E187 -> 649086.31 | F41: =IS!F187 -> 303770.85 | G41: =IS!G187 -> 0 | H41: =IS!H187 -> 0 | I41: =IS!I187 -> 0 | J41: =IS!J187 -> 0 | K41: =IS!K187 -> 0 | L41: =IS!L187 -> 0 | ... P41: =IS!P187 -> 0 | Q41: =SUM(E41:P41) -> 952857.16
B42: 대손상각비 | C42: Bad debt expense | Q42: =SUM(E42:P42) -> 0
B43: 감가상각비 | C43: Depreciation | D43: Deperication | E43: =IS!E196 -> 14906804 | F43: =IS!F196 -> 14906804 | G43: =IS!G196 -> 0 | H43: =IS!H196 -> 0 | I43: =IS!I196 -> 0 | J43: =IS!J196 -> 0 | K43: =IS!K196 -> 0 | L43: =IS!L196 -> 0 | ... P43: =IS!P196 -> 0 | Q43: =SUM(E43:P43) -> 29813608
B44: 무형자산상각비 | C44: Amortization expenses on Intagible assets | Q44: =SUM(E44:P44) -> 0
B45: 접대비 | C45: Training expenses | D45: Club Expenses, Customer Support Expenses, Factory Admin Exp, | E45: =IS!E191 -> 0 | F45: =IS!F191 -> 120756 | G45: =IS!G191 -> 0 | H45: =IS!H191 -> 0 | I45: =IS!I191 -> 0 | J45: =IS!J191 -> 0 | K45: =IS!K191 -> 0 | L45: =IS!L191 -> 0 | ... P45: =IS!P191 -> 0 | Q45: =SUM(E45:P45) -> 120756
B46: 기술지원료 | C46: Royalty expenses | D46: Technical Supporting Fee / Royalty | E46: =IS!E180 -> 7986640 | F46: =IS!F180 -> 8835523 | G46: =IS!G180 -> 0 | H46: =IS!H180 -> 0 | I46: =IS!I180 -> 0 | J46: =IS!J180 -> 0 | K46: =IS!K180 -> 0 | L46: =IS!L180 -> 0 | ... P46: =IS!P180 -> 0 | Q46: =SUM(E46:P46) -> 16822163
B47: 보험료 | C47: Insurance premium | D47: Insurance | E47: =IS!E193 -> 2130016.7 | F47: =IS!F193 -> 0 | G47: =IS!G193 -> 0 | H47: =IS!H193 -> 0 | I47: =IS!I193 -> 0 | J47: =IS!J193 -> 0 | K47: =IS!K193 -> 0 | L47: =IS!L193 -> 0 | ... P47: =IS!P193 -> 0 | Q47: =SUM(E47:P47) -> 2130016.7
B48: 광고선전비 | C48: 0 | Q48: =SUM(E48:P48) -> 0
B49: 도서인쇄비 | C49: 0 | Q49: =SUM(E49:P49) -> 0
B50: 수도광열비 | C50: 0 | D50: Water Charges | E50: =IS!E179 -> 173802 | F50: =IS!F179 -> 187744 | G50: =IS!G179 -> 0 | H50: =IS!H179 -> 0 | I50: =IS!I179 -> 0 | J50: =IS!J179 -> 0 | K50: =IS!K179 -> 0 | L50: =IS!L179 -> 0 | ... P50: =IS!P179 -> 0 | Q50: =SUM(E50:P50) -> 361546
B51: 기타경비 | C51: Miscellaneous Expenses | D51: Miscellaneous Expenses | E51: =IS!E195 -> 0 | F51: =IS!F195 -> 0 | G51: =IS!G195 -> 0 | H51: =IS!H195 -> 0 | I51: =IS!I195 -> 0 | J51: =IS!J195 -> 0 | K51: =IS!K195 -> 0 | L51: =IS!L195 -> 0 | ... P51: =IS!P195 -> 0 | Q51: =SUM(E51:P51) -> 0
B52: Ⅴ. 영업이익(손실) | C52: Ⅴ. Profit(loss) from operating activities | E52: =E25-E26 -> 23438584 | F52: =F25-F26 -> 46633659 | G52: =G25-G26 -> 0 | H52: =H25-H26 -> 0 | I52: =I25-I26 -> 0 | J52: =J25-J26 -> 0 | K52: =K25-K26 -> 0 | L52: =L25-L26 -> 0 | ... Q52: =Q25-Q26 -> 70072243
B53: Ⅵ. 영업외수익 | C53: Ⅵ. Non-operating income | E53: =SUM(E54:E66) -> 10171089 | F53: =SUM(F54:F66) -> 2154170.8 | G53: =SUM(G54:G66) -> 0 | H53: =SUM(H54:H66) -> 0 | I53: =SUM(I54:I66) -> 0 | J53: =SUM(J54:J66) -> 0 | K53: =SUM(K54:K66) -> 0 | L53: =SUM(L54:L66) -> 0 | ... Q53: =SUM(Q54:Q66) -> 12325260
B54: 이자수익 | C54: Interest income | D54: Other Income | E54: =IS!G96 -> 1464249.7 | F54: =IS!O96 -> 85582.18 | G54: =IS!W96 -> 0 | H54: =IS!AE96 -> 0 | I54: =IS!AM96 -> 0 | J54: =IS!AU96 -> 0 | K54: =IS!BC96 -> 0 | L54: =IS!BK96 -> 0 | M54: =IS!BS96 -> 0 | N54: =IS!CA96 -> 0 | O54: =IS!CI96 -> 0 | P54: =IS!CQ96 -> 0 | Q54: =SUM(E54:P54) -> 1549831.9
B55: 배당금수익 | C55: Dividend income | Q55: =SUM(E55:P55) -> 0
B56: 임대료수익 | C56: Rental income | D56: Rental Income | E56: =IS!G94 -> 2000000 | F56: =IS!O94 -> 1000000 | G56: =IS!W94 -> 0 | H56: =IS!AE94 -> 0 | I56: =IS!AM94 -> 0 | J56: =IS!AU94 -> 0 | K56: =IS!BC94 -> 0 | L56: =IS!BK94 -> 0 | M56: =IS!BS94 -> 0 | N56: =IS!CA94 -> 0 | O56: =IS!CI94 -> 0 | P56: =IS!CQ94 -> 0 | Q56: =SUM(E56:P56) -> 3000000
B57: 단기투자자산처분이익 | C57: Gain on disposal of short-term investments | Q57: =SUM(E57:P57) -> 0
